Workbook

Sheet 2nd Batch rcvd 08.2025
A1: PO NO. | B1: Color | C1: W (inch) | D1: L (inch) | E1: W (mm) | F1: L (mm) | G1: NOS | H1: m2
A2: 24045976 | B2: ASC 0096-Glossy Black | C2: 49 | D2: 96 | E2: 1245 | F2: 2440 | G2: 2000 | H2: 6075.6
A3: 24045976 | B3: ASC 0096-Glossy Black | C3: 49 | D3: 108 | E3: 1245 | F3: 2745 | G3: 600 | H3: 2050.515
A4: 24045985 | B4: ASC 0096-Glossy Black | C4: 49 | D4: 96 | E4: 1245 | F4: 2440 | G4: 800 | H4: 2430.24
A5: 24045985 | B5: ASC 0069-Glossy White | C5: 49 | D5: 96 | E5: 1245 | F5: 2440 | G5: 800 | H5: 2430.24
A6: 24045985 | B6: AMC 0103-Silver Frost | C6: 49 | D6: 96 | E6: 1245 | F6: 2440 | G6: 600 | H6: 1822.68
A7: 24045985 | B7: AMC 0086-Charcoal Metallic | C7: 49 | D7: 96 | E7: 1245 | F7: 2440 | G7: 600 | H7: 1822.68
A8: 24045987 | B8: ASC 0096-Glossy Black | C8: 49 | D8: 96 | E8: 1245 | F8: 2440 | G8: 200 | H8: 607.56
A9: 24045987 | B9: ASC 0096-Glossy Black | C9: 49 | D9: 108 | E9: 1245 | F9: 2745 | G9: 400 | H9: 1367.01
A10: 24045987 | B10: ASC 0069-Glossy White | C10: 49 | D10: 96 | E10: 1245 | F10: 2440 | G10: 800 | H10: 2430.24
A11: 24045987 | B11: ASC 0069-Glossy White | C11: 49 | D11: 108 | E11: 1245 | F11: 2745 | G11: 400 | H11: 1367.01
A12: 24045987 | B12: AMC 0103-Silver Frost | C12: 49 | D12: 96 | E12: 1245 | F12: 2440 | G12: 200 | H12: 607.56
A13: 24045987 | B13: AMC 0103-Silver Frost | C13: 49 | D13: 108 | E13: 1245 | F13: 2745 | G13: 200 | H13: 683.505
... A58: 52923929 | B58: AMC 0086-Charcoal Metallic | C58: 49 | D58: 108 | E58: 1245 | F58: 2745 | G58: 400 | H58: 1367.01
G59: =SUM(G2:G58) -> 34000 | H59: =SUM(H2:H58) -> 108825.45

Sheet Dashboard
Q2: TOTAL VOLUME
C3: ORDER STATUS (ACTIVE ONLY) | D3: South Paris, ME | E3: Ashburn, GA | F3: Hillsboro, TX | G3: Nampa, ID | H3: Granger, IN | I3: Gordon, PA | J3: Minneota, MN | K3: Houston, TX | L3: Twin Falls, ID | M3: Savannah, GA | N3: TOTALS | Q3: COLORS (Purple are Standard Colors) | R3: Sheets | S3: MSF | T3: M2 | U3: $
C4: PO Received | D4: =COUNTIFS('Order Summary'!$G:$G,"Yes",'Order Summary'!$I:$I,Dashboard!D$3,'Order Summary'!$E:$E,Dashboard!$C4) -> 1 | E4: =COUNTIFS('Order Summary'!$G:$G,"Yes",'Order Summary'!$I:$I,Dashboard!E$3,'Order Summary'!$E:$E,Dashboard!$C4) -> 0 | F4: =COUNTIFS('Order Summary'!$G:$G,"Yes",'Order Summary'!$I:$I,Dashboard!F$3,'Order Summary'!$E:$E,Dashboard!$C4) -> 8 | G4: =COUNTIFS('Order Summary'!$G:$G,"Yes",'Order Summary'!$I:$I,Dashboard!G$3,'Order Summary'!$E:$E,Dashboard!$C4) -> 2 | H4: =COUNTIFS('Order Summary'!$G:$G,"Yes",'Order Summary'!$I:$I,Dashboard!H$3,'Order Summary'!$E:$E,Dashboard!$C4) -> 5 | I4: =COUNTIFS('Order Summary'!$G:$G,"Yes",'Order Summary'!$I:$I,Dashboard!I$3,'Order Summary'!$E:$E,Dashboard!$C4) -> 1 | J4: =COUNTIFS('Order Summary'!$G:$G,"Yes",'Order Summary'!$I:$I,Dashboard!J$3,'Order Summary'!$E:$E,Dashboard!$C4) -> 6 | K4: =COUNTIFS('Order Summary'!$G:$G,"Yes",'Order Summary'!$I:$I,Dashboard!K$3,'Order Summary'!$E:$E,Dashboard!$C4) -> 0 | ... M4: =COUNTIFS('Order Summary'!$G:$G,"Yes",'Order Summary'!$I:$I,Dashboard!M$3,'Order Summary'!$E:$E,Dashboard!$C4) -> 0 | N4: =SUM(D4:M4) -> 24 | Q4: ASC 0096 GLOSSY BLACK | R4: =SUMIFS('Order Details'!$Q:$Q,'Order Details'!$N:$N,Dashboard!$Q4,'Order Details'!$E:$E,"Yes") -> 87500 | S4: =SUMIFS('Order Details'!$O:$O,'Order Details'!$N:$N,Dashboard!$Q4,'Order Details'!$E:$E,"Yes") -> 3060.12 | T4: =SUMIFS('Order Details'!$P:$P,'Order Details'!$N:$N,Dashboard!$Q4,'Order Details'!$E:$E,"Yes") -> 281970.21 | U4: =SUMIFS('Order Details'!$V:$V,'Order Details'!$N:$N,Dashboard!$Q4,'Order Details'!$E:$E,"Yes") -> 2144825.6 | AB4: Purchase Order to Proforma Invoice:
C5: Proforma Invoice Sent | D5: =COUNTIFS('Order Summary'!$G:$G,"Yes",'Order Summary'!$I:$I,Dashboard!D$3,'Order Summary'!$E:$E,Dashboard!$C5) -> 2 | E5: =COUNTIFS('Order Summary'!$G:$G,"Yes",'Order Summary'!$I:$I,Dashboard!E$3,'Order Summary'!$E:$E,Dashboard!$C5) -> 0 | F5: =COUNTIFS('Order Summary'!$G:$G,"Yes",'Order Summary'!$I:$I,Dashboard!F$3,'Order Summary'!$E:$E,Dashboard!$C5) -> 1 | G5: =COUNTIFS('Order Summary'!$G:$G,"Yes",'Order Summary'!$I:$I,Dashboard!G$3,'Order Summary'!$E:$E,Dashboard!$C5) -> 0 | H5: =COUNTIFS('Order Summary'!$G:$G,"Yes",'Order Summary'!$I:$I,Dashboard!H$3,'Order Summary'!$E:$E,Dashboard!$C5) -> 0 | I5: =COUNTIFS('Order Summary'!$G:$G,"Yes",'Order Summary'!$I:$I,Dashboard!I$3,'Order Summary'!$E:$E,Dashboard!$C5) -> 10 | J5: =COUNTIFS('Order Summary'!$G:$G,"Yes",'Order Summary'!$I:$I,Dashboard!J$3,'Order Summary'!$E:$E,Dashboard!$C5) -> 0 | K5: =COUNTIFS('Order Summary'!$G:$G,"Yes",'Order Summary'!$I:$I,Dashboard!K$3,'Order Summary'!$E:$E,Dashboard!$C5) -> 0 | ... M5: =COUNTIFS('Order Summary'!$G:$G,"Yes",'Order Summary'!$I:$I,Dashboard!M$3,'Order Summary'!$E:$E,Dashboard!$C5) -> 0 | N5: =SUM(D5:M5) -> 13 | Q5: ASC 0069 GLOSSY WHITE | R5: =SUMIFS('Order Details'!$Q:$Q,'Order Details'!$N:$N,Dashboard!$Q5,'Order Details'!$E:$E,"Yes") -> 121850 | S5: =SUMIFS('Order Details'!$O:$O,'Order Details'!$N:$N,Dashboard!$Q5,'Order Details'!$E:$E,"Yes") -> 4169.1193 | T5: =SUMIFS('Order Details'!$P:$P,'Order Details'!$N:$N,Dashboard!$Q5,'Order Details'!$E:$E,"Yes") -> 387377.83 | U5: =SUMIFS('Order Details'!$V:$V,'Order Details'!$N:$N,Dashboard!$Q5,'Order Details'!$E:$E,"Yes") -> 2958298.3 | AB5: Average Days: | AC5: =AVERAGEIFS('Order Summary'!$O$4:$O$200,'Order Summary'!$O$4:$O$200,"<>"&"",'Order Summary'!$G$4:$G$200,"Yes") -> 7.6058394
C6: Downpayment Received | D6: =COUNTIFS('Order Summary'!$G:$G,"Yes",'Order Summary'!$I:$I,Dashboard!D$3,'Order Summary'!$E:$E,Dashboard!$C6) -> 0 | E6: =COUNTIFS('Order Summary'!$G:$G,"Yes",'Order Summary'!$I:$I,Dashboard!E$3,'Order Summary'!$E:$E,Dashboard!$C6) -> 3 | F6: =COUNTIFS('Order Summary'!$G:$G,"Yes",'Order Summary'!$I:$I,Dashboard!F$3,'Order Summary'!$E:$E,Dashboard!$C6) -> 2 | G6: =COUNTIFS('Order Summary'!$G:$G,"Yes",'Order Summary'!$I:$I,Dashboard!G$3,'Order Summary'!$E:$E,Dashboard!$C6) -> 11 | H6: =COUNTIFS('Order Summary'!$G:$G,"Yes",'Order Summary'!$I:$I,Dashboard!H$3,'Order Summary'!$E:$E,Dashboard!$C6) -> 3 | I6: =COUNTIFS('Order Summary'!$G:$G,"Yes",'Order Summary'!$I:$I,Dashboard!I$3,'Order Summary'!$E:$E,Dashboard!$C6) -> 1 | J6: =COUNTIFS('Order Summary'!$G:$G,"Yes",'Order Summary'!$I:$I,Dashboard!J$3,'Order Summary'!$E:$E,Dashboard!$C6) -> 0 | K6: =COUNTIFS('Order Summary'!$G:$G,"Yes",'Order Summary'!$I:$I,Dashboard!K$3,'Order Summary'!$E:$E,Dashboard!$C6) -> 0 | ... M6: =COUNTIFS('Order Summary'!$G:$G,"Yes",'Order Summary'!$I:$I,Dashboard!M$3,'Order Summary'!$E:$E,Dashboard!$C6) -> 0 | N6: =SUM(D6:M6) -> 21 | Q6: AMC 0103 SILVER FROST | R6: =SUMIFS('Order Details'!$Q:$Q,'Order Details'!$N:$N,Dashboard!$Q6,'Order Details'!$E:$E,"Yes") -> 70650 | S6: =SUMIFS('Order Details'!$O:$O,'Order Details'!$N:$N,Dashboard!$Q6,'Order Details'!$E:$E,"Yes") -> 2449.2863 | T6: =SUMIFS('Order Details'!$P:$P,'Order Details'!$N:$N,Dashboard!$Q6,'Order Details'!$E:$E,"Yes") -> 227447.62 | U6: =SUMIFS('Order Details'!$V:$V,'Order Details'!$N:$N,Dashboard!$Q6,'Order Details'!$E:$E,"Yes") -> 1728889.6 | AB6: POs without PIs: | AC6: =COUNTIFS('Order Summary'!$O$4:$O$200,"",'Order Summary'!$F$4:$F$200,"<>"&"",'Order Summary'!$G$4:$G$200,"Yes") -> 11
C7: In Production | D7: =COUNTIFS('Order Summary'!$G:$G,"Yes",'Order Summary'!$I:$I,Dashboard!D$3,'Order Summary'!$E:$E,Dashboard!$C7) -> 0 | E7: =COUNTIFS('Order Summary'!$G:$G,"Yes",'Order Summary'!$I:$I,Dashboard!E$3,'Order Summary'!$E:$E,Dashboard!$C7) -> 0 | F7: =COUNTIFS('Order Summary'!$G:$G,"Yes",'Order Summary'!$I:$I,Dashboard!F$3,'Order Summary'!$E:$E,Dashboard!$C7) -> 0 | G7: =COUNTIFS('Order Summary'!$G:$G,"Yes",'Order Summary'!$I:$I,Dashboard!G$3,'Order Summary'!$E:$E,Dashboard!$C7) -> 0 | H7: =COUNTIFS('Order Summary'!$G:$G,"Yes",'Order Summary'!$I:$I,Dashboard!H$3,'Order Summary'!$E:$E,Dashboard!$C7) -> 0 | I7: =COUNTIFS('Order Summary'!$G:$G,"Yes",'Order Summary'!$I:$I,Dashboard!I$3,'Order Summary'!$E:$E,Dashboard!$C7) -> 0 | J7: =COUNTIFS('Order Summary'!$G:$G,"Yes",'Order Summary'!$I:$I,Dashboard!J$3,'Order Summary'!$E:$E,Dashboard!$C7) -> 0 | K7: =COUNTIFS('Order Summary'!$G:$G,"Yes",'Order Summary'!$I:$I,Dashboard!K$3,'Order Summary'!$E:$E,Dashboard!$C7) -> 0 | ... M7: =COUNTIFS('Order Summary'!$G:$G,"Yes",'Order Summary'!$I:$I,Dashboard!M$3,'Order Summary'!$E:$E,Dashboard!$C7) -> 2 | N7: =SUM(D7:M7) -> 6 | Q7: AMC 0086 CHARCOAL METALLIC | R7: =SUMIFS('Order Details'!$Q:$Q,'Order Details'!$N:$N,Dashboard!$Q7,'Order Details'!$E:$E,"Yes") -> 66950 | S7: =SUMIFS('Order Details'!$O:$O,'Order Details'!$N:$N,Dashboard!$Q7,'Order Details'!$E:$E,"Yes") -> 2304.3303 | T7: =SUMIFS('Order Details'!$P:$P,'Order Details'!$N:$N,Dashboard!$Q7,'Order Details'!$E:$E,"Yes") -> 213971.61 | U7: =SUMIFS('Order Details'!$V:$V,'Order Details'!$N:$N,Dashboard!$Q7,'Order Details'!$E:$E,"Yes") -> 1739662
C8: Container Loaded | D8: =COUNTIFS('Order Summary'!$G:$G,"Yes",'Order Summary'!$I:$I,Dashboard!D$3,'Order Summary'!$E:$E,Dashboard!$C8) -> 0 | E8: =COUNTIFS('Order Summary'!$G:$G,"Yes",'Order Summary'!$I:$I,Dashboard!E$3,'Order Summary'!$E:$E,Dashboard!$C8) -> 0 | F8: =COUNTIFS('Order Summary'!$G:$G,"Yes",'Order Summary'!$I:$I,Dashboard!F$3,'Order Summary'!$E:$E,Dashboard!$C8) -> 0 | G8: =COUNTIFS('Order Summary'!$G:$G,"Yes",'Order Summary'!$I:$I,Dashboard!G$3,'Order Summary'!$E:$E,Dashboard!$C8) -> 0 | H8: =COUNTIFS('Order Summary'!$G:$G,"Yes",'Order Summary'!$I:$I,Dashboard!H$3,'Order Summary'!$E:$E,Dashboard!$C8) -> 0 | I8: =COUNTIFS('Order Summary'!$G:$G,"Yes",'Order Summary'!$I:$I,Dashboard!I$3,'Order Summary'!$E:$E,Dashboard!$C8) -> 0 | J8: =COUNTIFS('Order Summary'!$G:$G,"Yes",'Order Summary'!$I:$I,Dashboard!J$3,'Order Summary'!$E:$E,Dashboard!$C8) -> 0 | K8: =COUNTIFS('Order Summary'!$G:$G,"Yes",'Order Summary'!$I:$I,Dashboard!K$3,'Order Summary'!$E:$E,Dashboard!$C8) -> 1 | ... M8: =COUNTIFS('Order Summary'!$G:$G,"Yes",'Order Summary'!$I:$I,Dashboard!M$3,'Order Summary'!$E:$E,Dashboard!$C8) -> 2 | N8: =SUM(D8:M8) -> 3 | Q8: ASC 0099 MATTE BLACK | R8: =SUMIFS('Order Details'!$Q:$Q,'Order Details'!$N:$N,Dashboard!$Q8,'Order Details'!$E:$E,"Yes") -> 7800 | S8: =SUMIFS('Order Details'!$O:$O,'Order Details'!$N:$N,Dashboard!$Q8,'Order Details'!$E:$E,"Yes") -> 261.74167 | T8: =SUMIFS('Order Details'!$P:$P,'Order Details'!$N:$N,Dashboard!$Q8,'Order Details'!$E:$E,"Yes") -> 24338.505 | U8: =SUMIFS('Order Details'!$V:$V,'Order Details'!$N:$N,Dashboard!$Q8,'Order Details'!$E:$E,"Yes") -> 196411.74 | AB8: Proforma Invoice to Downpayment:
C9: Commercial Invoice Sent | D9: =COUNTIFS('Order Summary'!$G:$G,"Yes",'Order Summary'!$I:$I,Dashboard!D$3,'Order Summary'!$E:$E,Dashboard!$C9) -> 0 | E9: =COUNTIFS('Order Summary'!$G:$G,"Yes",'Order Summary'!$I:$I,Dashboard!E$3,'Order Summary'!$E:$E,Dashboard!$C9) -> 0 | F9: =COUNTIFS('Order Summary'!$G:$G,"Yes",'Order Summary'!$I:$I,Dashboard!F$3,'Order Summary'!$E:$E,Dashboard!$C9) -> 0 | G9: =COUNTIFS('Order Summary'!$G:$G,"Yes",'Order Summary'!$I:$I,Dashboard!G$3,'Order Summary'!$E:$E,Dashboard!$C9) -> 2 | H9: =COUNTIFS('Order Summary'!$G:$G,"Yes",'Order Summary'!$I:$I,Dashboard!H$3,'Order Summary'!$E:$E,Dashboard!$C9) -> 1 | I9: =COUNTIFS('Order Summary'!$G:$G,"Yes",'Order Summary'!$I:$I,Dashboard!I$3,'Order Summary'!$E:$E,Dashboard!$C9) -> 0 | J9: =COUNTIFS('Order Summary'!$G:$G,"Yes",'Order Summary'!$I:$I,Dashboard!J$3,'Order Summary'!$E:$E,Dashboard!$C9) -> 0 | K9: =COUNTIFS('Order Summary'!$G:$G,"Yes",'Order Summary'!$I:$I,Dashboard!K$3,'Order Summary'!$E:$E,Dashboard!$C9) -> 5 | ... M9: =COUNTIFS('Order Summary'!$G:$G,"Yes",'Order Summary'!$I:$I,Dashboard!M$3,'Order Summary'!$E:$E,Dashboard!$C9) -> 4 | N9: =SUM(D9:M9) -> 13 | Q9: ASC 0092 PEPSI BLUE | R9: =SUMIFS('Order Details'!$Q:$Q,'Order Details'!$N:$N,Dashboard!$Q9,'Order Details'!$E:$E,"Yes") -> 800 | S9: =SUMIFS('Order Details'!$O:$O,'Order Details'!$N:$N,Dashboard!$Q9,'Order Details'!$E:$E,"Yes") -> 28.652 | T9: =SUMIFS('Order Details'!$P:$P,'Order Details'!$N:$N,Dashboard!$Q9,'Order Details'!$E:$E,"Yes") -> 2664.3 | U9: =SUMIFS('Order Details'!$V:$V,'Order Details'!$N:$N,Dashboard!$Q9,'Order Details'!$E:$E,"Yes") -> 20214.069 | AB9: Average Days: | AC9: =AVERAGEIFS('Order Summary'!$R$4:$R$200,'Order Summary'!$R$4:$R$200,"<>"&"",'Order Summary'!$G$4:$G$200,"Yes") -> 30.146789
C10: Balance Payment Received | D10: =COUNTIFS('Order Summary'!$G:$G,"Yes",'Order Summary'!$I:$I,Dashboard!D$3,'Order Summary'!$E:$E,Dashboard!$C10) -> 0 | E10: =COUNTIFS('Order Summary'!$G:$G,"Yes",'Order Summary'!$I:$I,Dashboard!E$3,'Order Summary'!$E:$E,Dashboard!$C10) -> 4 | F10: =COUNTIFS('Order Summary'!$G:$G,"Yes",'Order Summary'!$I:$I,Dashboard!F$3,'Order Summary'!$E:$E,Dashboard!$C10) -> 0 | G10: =COUNTIFS('Order Summary'!$G:$G,"Yes",'Order Summary'!$I:$I,Dashboard!G$3,'Order Summary'!$E:$E,Dashboard!$C10) -> 3 | H10: =COUNTIFS('Order Summary'!$G:$G,"Yes",'Order Summary'!$I:$I,Dashboard!H$3,'Order Summary'!$E:$E,Dashboard!$C10) -> 3 | I10: =COUNTIFS('Order Summary'!$G:$G,"Yes",'Order Summary'!$I:$I,Dashboard!I$3,'Order Summary'!$E:$E,Dashboard!$C10) -> 0 | J10: =COUNTIFS('Order Summary'!$G:$G,"Yes",'Order Summary'!$I:$I,Dashboard!J$3,'Order Summary'!$E:$E,Dashboard!$C10) -> 1 | K10: =COUNTIFS('Order Summary'!$G:$G,"Yes",'Order Summary'!$I:$I,Dashboard!K$3,'Order Summary'!$E:$E,Dashboard!$C10) -> 8 | ... M10: =COUNTIFS('Order Summary'!$G:$G,"Yes",'Order Summary'!$I:$I,Dashboard!M$3,'Order Summary'!$E:$E,Dashboard!$C10) -> 4 | N10: =SUM(D10:M10) -> 23 | Q10: ASC 0089 VICTORY RED | R10: =SUMIFS('Order Details'!$Q:$Q,'Order Details'!$N:$N,Dashboard!$Q10,'Order Details'!$E:$E,"Yes") -> 9400 | S10: =SUMIFS('Order Details'!$O:$O,'Order Details'!$N:$N,Dashboard!$Q10,'Order Details'!$E:$E,"Yes") -> 325.98533 | T10: =SUMIFS('Order Details'!$P:$P,'Order Details'!$N:$N,Dashboard!$Q10,'Order Details'!$E:$E,"Yes") -> 30314.007 | U10: =SUMIFS('Order Details'!$V:$V,'Order Details'!$N:$N,Dashboard!$Q10,'Order Details'!$E:$E,"Yes") -> 231395.9 | AB10: Unpaid PIs: | AC10: =COUNTIFS('Order Summary'!$R$4:$R$200,"",'Order Summary'!$N$4:$N$200,"<>"&"",'Order Summary'!$G$4:$G$200,"Yes") -> 26
C11: Telex / Seaway Released | D11: =COUNTIFS('Order Summary'!$G:$G,"Yes",'Order Summary'!$I:$I,Dashboard!D$3,'Order Summary'!$E:$E,Dashboard!$C11) -> 1 | E11: =COUNTIFS('Order Summary'!$G:$G,"Yes",'Order Summary'!$I:$I,Dashboard!E$3,'Order Summary'!$E:$E,Dashboard!$C11) -> 6 | F11: =COUNTIFS('Order Summary'!$G:$G,"Yes",'Order Summary'!$I:$I,Dashboard!F$3,'Order Summary'!$E:$E,Dashboard!$C11) -> 11 | G11: =COUNTIFS('Order Summary'!$G:$G,"Yes",'Order Summary'!$I:$I,Dashboard!G$3,'Order Summary'!$E:$E,Dashboard!$C11) -> 11 | H11: =COUNTIFS('Order Summary'!$G:$G,"Yes",'Order Summary'!$I:$I,Dashboard!H$3,'Order Summary'!$E:$E,Dashboard!$C11) -> 11 | I11: =COUNTIFS('Order Summary'!$G:$G,"Yes",'Order Summary'!$I:$I,Dashboard!I$3,'Order Summary'!$E:$E,Dashboard!$C11) -> 2 | J11: =COUNTIFS('Order Summary'!$G:$G,"Yes",'Order Summary'!$I:$I,Dashboard!J$3,'Order Summary'!$E:$E,Dashboard!$C11) -> 2 | K11: =COUNTIFS('Order Summary'!$G:$G,"Yes",'Order Summary'!$I:$I,Dashboard!K$3,'Order Summary'!$E:$E,Dashboard!$C11) -> 0 | ... M11: =COUNTIFS('Order Summary'!$G:$G,"Yes",'Order Summary'!$I:$I,Dashboard!M$3,'Order Summary'!$E:$E,Dashboard!$C11) -> 2 | N11: =SUM(D11:M11) -> 46 | Q11: AMC 0104 PEWTER | R11: =SUMIFS('Order Details'!$Q:$Q,'Order Details'!$N:$N,Dashboard!$Q11,'Order Details'!$E:$E,"Yes") -> 0 | S11: =SUMIFS('Order Details'!$O:$O,'Order Details'!$N:$N,Dashboard!$Q11,'Order Details'!$E:$E,"Yes") -> 0 | T11: =SUMIFS('Order Details'!$P:$P,'Order Details'!$N:$N,Dashboard!$Q11,'Order Details'!$E:$E,"Yes") -> 0 | U11: =SUMIFS('Order Details'!$V:$V,'Order Details'!$N:$N,Dashboard!$Q11,'Order Details'!$E:$E,"Yes") -> 0 | AB11: Unpaid Value: | AC11: =SUMIFS('Order Summary'!$P$4:$P$200,'Order Summary'!$R$4:$R$200,"",'Order Summary'!$N$4:$N$200,"<>"&"",'Order Summary'!$G$4:$G$200,"Yes")*'Master Data'!$P$12 -> 843699.41
C12: Arrived | D12: =COUNTIFS('Order Summary'!$G:$G,"Yes",'Order Summary'!$I:$I,Dashboard!D$3,'Order Summary'!$AO:$AO,"<>"&"",'Order Summary'!$AO:$AO,"<>"&"PENDING") -> 1 | E12: =COUNTIFS('Order Summary'!$G:$G,"Yes",'Order Summary'!$I:$I,Dashboard!E$3,'Order Summary'!$AO:$AO,"<>"&"",'Order Summary'!$AO:$AO,"<>"&"PENDING") -> 6 | F12: =COUNTIFS('Order Summary'!$G:$G,"Yes",'Order Summary'!$I:$I,Dashboard!F$3,'Order Summary'!$AO:$AO,"<>"&"",'Order Summary'!$AO:$AO,"<>"&"PENDING") -> 9 | G12: =COUNTIFS('Order Summary'!$G:$G,"Yes",'Order Summary'!$I:$I,Dashboard!G$3,'Order Summary'!$AO:$AO,"<>"&"",'Order Summary'!$AO:$AO,"<>"&"PENDING") -> 9 | H12: =COUNTIFS('Order Summary'!$G:$G,"Yes",'Order Summary'!$I:$I,Dashboard!H$3,'Order Summary'!$AO:$AO,"<>"&"",'Order Summary'!$AO:$AO,"<>"&"PENDING") -> 13 | I12: =COUNTIFS('Order Summary'!$G:$G,"Yes",'Order Summary'!$I:$I,Dashboard!I$3,'Order Summary'!$AO:$AO,"<>"&"",'Order Summary'!$AO:$AO,"<>"&"PENDING") -> 1 | J12: =COUNTIFS('Order Summary'!$G:$G,"Yes",'Order Summary'!$I:$I,Dashboard!J$3,'Order Summary'!$AO:$AO,"<>"&"",'Order Summary'!$AO:$AO,"<>"&"PENDING") -> 3 | K12: =COUNTIFS('Order Summary'!$G:$G,"Yes",'Order Summary'!$I:$I,Dashboard!K$3,'Order Summary'!$AO:$AO,"<>"&"",'Order Summary'!$AO:$AO,"<>"&"PENDING") -> 0 | ... M12: =COUNTIFS('Order Summary'!$G:$G,"Yes",'Order Summary'!$I:$I,Dashboard!M$3,'Order Summary'!$AO:$AO,"<>"&"",'Order Summary'!$AO:$AO,"<>"&"PENDING") -> 2 | N12: =SUM(D12:M12) -> 44 | Q12: ASC 0105 INDIGO BLUE | R12: =SUMIFS('Order Details'!$Q:$Q,'Order Details'!$N:$N,Dashboard!$Q12,'Order Details'!$E:$E,"Yes") -> 8950 | S12: =SUMIFS('Order Details'!$O:$O,'Order Details'!$N:$N,Dashboard!$Q12,'Order Details'!$E:$E,"Yes") -> 306.18033 | T12: =SUMIFS('Order Details'!$P:$P,'Order Details'!$N:$N,Dashboard!$Q12,'Order Details'!$E:$E,"Yes") -> 28472.341 | U12: =SUMIFS('Order Details'!$V:$V,'Order Details'!$N:$N,Dashboard!$Q12,'Order Details'!$E:$E,"Yes") -> 232869.04
C13: TOTALS | D13: =SUM(D4:D11) -> 4 | E13: =SUM(E4:E11) -> 13 | F13: =SUM(F4:F11) -> 22 | G13: =SUM(G4:G11) -> 29 | H13: =SUM(H4:H11) -> 23 | I13: =SUM(I4:I11) -> 14 | J13: =SUM(J4:J11) -> 9 | K13: =SUM(K4:K11) -> 14 | ... N13: =SUM(N4:N11) -> 149 | Q13: ASC 0164 ARMY GREEN | R13: =SUMIFS('Order Details'!$Q:$Q,'Order Details'!$N:$N,Dashboard!$Q13,'Order Details'!$E:$E,"Yes") -> 4200 | S13: =SUMIFS('Order Details'!$O:$O,'Order Details'!$N:$N,Dashboard!$Q13,'Order Details'!$E:$E,"Yes") -> 139.343 | T13: =SUMIFS('Order Details'!$P:$P,'Order Details'!$N:$N,Dashboard!$Q13,'Order Details'!$E:$E,"Yes") -> 12957.213 | U13: =SUMIFS('Order Details'!$V:$V,'Order Details'!$N:$N,Dashboard!$Q13,'Order Details'!$E:$E,"Yes") -> 106305.72 | AB13: Downpayment to Actual Shipping Departure:
Q14: ASC 0127 SAND SAHARA | R14: =SUMIFS('Order Details'!$Q:$Q,'Order Details'!$N:$N,Dashboard!$Q14,'Order Details'!$E:$E,"Yes") -> 1400 | S14: =SUMIFS('Order Details'!$O:$O,'Order Details'!$N:$N,Dashboard!$Q14,'Order Details'!$E:$E,"Yes") -> 45.733 | T14: =SUMIFS('Order Details'!$P:$P,'Order Details'!$N:$N,Dashboard!$Q14,'Order Details'!$E:$E,"Yes") -> 4252.173 | U14: =SUMIFS('Order Details'!$V:$V,'Order Details'!$N:$N,Dashboard!$Q14,'Order Details'!$E:$E,"Yes") -> 34315.036 | AB14: Average Days: | AC14: =AVERAGEIFS('Order Summary'!$AB$4:$AB$200,'Order Summary'!$AB$4:$AB$200,"<>"&"",'Order Summary'!$G$4:$G$200,"Yes") -> 67.821429
Q15: ASC 0208 SAND SAHARA MATTE | R15: =SUMIFS('Order Details'!$Q:$Q,'Order Details'!$N:$N,Dashboard!$Q15,'Order Details'!$E:$E,"Yes") -> 2400 | S15: =SUMIFS('Order Details'!$O:$O,'Order Details'!$N:$N,Dashboard!$Q15,'Order Details'!$E:$E,"Yes") -> 80.169 | T15: =SUMIFS('Order Details'!$P:$P,'Order Details'!$N:$N,Dashboard!$Q15,'Order Details'!$E:$E,"Yes") -> 7455.06 | U15: =SUMIFS('Order Details'!$V:$V,'Order Details'!$N:$N,Dashboard!$Q15,'Order Details'!$E:$E,"Yes") -> 61653.346 | AB15: DP Received, Unshipped: | AC15: =COUNTIFS('Order Summary'!$Q4:$Q200,"<>"&"",'Order Summary'!$AA4:$AA200,"",'Order Summary'!$G$4:$G$200,"Yes") -> 36
C16: Open Orders | D16: =SUM(D4:D7) -> 3 | E16: =SUM(E4:E7) -> 3 | F16: =SUM(F4:F7) -> 11 | G16: =SUM(G4:G7) -> 13 | H16: =SUM(H4:H7) -> 8 | I16: =SUM(I4:I7) -> 12 | J16: =SUM(J4:J7) -> 6 | K16: =SUM(K4:K7) -> 0 | ... N16: =SUM(N4:N7) -> 64 | Q16: ASC 0090 YELLOW | R16: =SUMIFS('Order Details'!$Q:$Q,'Order Details'!$N:$N,Dashboard!$Q16,'Order Details'!$E:$E,"Yes") -> 0 | S16: =SUMIFS('Order Details'!$O:$O,'Order Details'!$N:$N,Dashboard!$Q16,'Order Details'!$E:$E,"Yes") -> 0 | T16: =SUMIFS('Order Details'!$P:$P,'Order Details'!$N:$N,Dashboard!$Q16,'Order Details'!$E:$E,"Yes") -> 0 | U16: =SUMIFS('Order Details'!$V:$V,'Order Details'!$N:$N,Dashboard!$Q16,'Order Details'!$E:$E,"Yes") -> 0
C17: Shipped | D17: =SUM(D8:D11)-D12 -> 0 | E17: =SUM(E8:E11)-E12 -> 4 | F17: =SUM(F8:F11)-F12 -> 2 | G17: =SUM(G8:G11)-G12 -> 7 | H17: =SUM(H8:H11)-H12 -> 2 | I17: =SUM(I8:I11)-I12 -> 1 | J17: =SUM(J8:J11)-J12 -> 0 | K17: =SUM(K8:K11)-K12 -> 14 | ... N17: =SUM(N8:N11)-N12 -> 41 | Q17: ASC 0091 ORANGE | R17: =SUMIFS('Order Details'!$Q:$Q,'Order Details'!$N:$N,Dashboard!$Q17,'Order Details'!$E:$E,"Yes") -> 0 | S17: =SUMIFS('Order Details'!$O:$O,'Order Details'!$N:$N,Dashboard!$Q17,'Order Details'!$E:$E,"Yes") -> 0 | T17: =SUMIFS('Order Details'!$P:$P,'Order Details'!$N:$N,Dashboard!$Q17,'Order Details'!$E:$E,"Yes") -> 0 | U17: =SUMIFS('Order Details'!$V:$V,'Order Details'!$N:$N,Dashboard!$Q17,'Order Details'!$E:$E,"Yes") -> 0 | AB17: Commercial Invoice to Balance Payment:
C18: Arrived | D18: =D12 -> 1 | E18: =E12 -> 6 | F18: =F12 -> 9 | G18: =G12 -> 9 | H18: =H12 -> 13 | I18: =I12 -> 1 | J18: =J12 -> 3 | K18: =K12 -> 0 | ... N18: =N12 -> 44 | Q18: ASC 0126 BRANDY WINE | R18: =SUMIFS('Order Details'!$Q:$Q,'Order Details'!$N:$N,Dashboard!$Q18,'Order Details'!$E:$E,"Yes") -> 0 | S18: =SUMIFS('Order Details'!$O:$O,'Order Details'!$N:$N,Dashboard!$Q18,'Order Details'!$E:$E,"Yes") -> 0 | T18: =SUMIFS('Order Details'!$P:$P,'Order Details'!$N:$N,Dashboard!$Q18,'Order Details'!$E:$E,"Yes") -> 0 | U18: =SUMIFS('Order Details'!$V:$V,'Order Details'!$N:$N,Dashboard!$Q18,'Order Details'!$E:$E,"Yes") -> 0 | AB18: Average Days: | AC18: =AVERAGEIFS('Order Summary'!$AK$4:$AK$200,'Order Summary'!$AK$4:$AK$200,"<>"&"",'Order Summary'!$G$4:$G$200,"Yes") -> 19.03125
Q19: TOTALS | R19: =SUM(R4:R18) -> 381900 | S19: =SUM(S4:S18) -> 13170.66 | T19: =SUM(T4:T18) -> 1221220.9 | U19: =SUM(U4:U18) -> 9454840.3 | AB19: Unpaid CIs: | AC19: =COUNTIFS('Order Summary'!$AK$4:$AK$200,"",'Order Summary'!$AD$4:$AD$200,"<>"&"",'Order Summary'!$G$4:$G$200,"Yes") -> 19
AB20: Unpaid Value: | AC20: =SUMIFS('Order Summary'!$AI$4:$AI$200,'Order Summary'!$AK$4:$AK$200,"",'Order Summary'!$AD$4:$AD$200,"<>"&"",'Order Summary'!$G$4:$G$200,"Yes") -> 758670.85
Q22: VOLUME ON ORDER (NOT SHIPPED) | AB22: Balance Payment to Telex/Seaway Release:
Q23: COLORS (Purple are Standard Colors) | R23: Sheets | S23: MSF | T23: M2 | U23: $ | AB23: Average Days: | AC23: =AVERAGEIFS('Order Summary'!$AN$4:$AN$200,'Order Summary'!$AN$4:$AN$200,"<>"&"",'Order Summary'!$G$4:$G$200,"Yes") -> 40.6
Q24: ASC 0096 GLOSSY BLACK | R24: =SUMIFS('Order Details'!$Q:$Q,'Order Details'!$N:$N,Dashboard!$Q24,'Order Details'!$E:$E,"Yes",'Order Details'!$C:$C,'Master Data'!$C$4)+SUMIFS('Order Details'!$Q:$Q,'Order Details'!$N:$N,Dashboard!$Q24,'Order Details'!$E:$E,"Yes",'Order Details'!$C:$C,'Master Data'!$C$5)+SUMIFS('Order Details'!$Q:$Q,'Order Details'!$N:$N,Dashboard!$Q24,'Order Details'!$E:$E,"Yes",'Order Details'!$C:$C,'Master Data'!$C$6)+SUMIFS('Order Details'!$Q:$Q,'Order Details'!$N:$N,Dashboard!$Q24,'Order Details'!$E:$E,"Yes",'Order Details'!$C:$C,'Master Data'!$C$7) -> 36500 | S24: =SUMIFS('Order Details'!$O:$O,'Order Details'!$N:$N,Dashboard!$Q24,'Order Details'!$E:$E,"Yes",'Order Details'!$C:$C,'Master Data'!$C$4)+SUMIFS('Order Details'!$O:$O,'Order Details'!$N:$N,Dashboard!$Q24,'Order Details'!$E:$E,"Yes",'Order Details'!$C:$C,'Master Data'!$C$5)+SUMIFS('Order Details'!$O:$O,'Order Details'!$N:$N,Dashboard!$Q24,'Order Details'!$E:$E,"Yes",'Order Details'!$C:$C,'Master Data'!$C$6)+SUMIFS('Order Details'!$O:$O,'Order Details'!$N:$N,Dashboard!$Q24,'Order Details'!$E:$E,"Yes",'Order Details'!$C:$C,'Master Data'!$C$7) -> 1252.426 | T24: =SUMIFS('Order Details'!$P:$P,'Order Details'!$N:$N,Dashboard!$Q24,'Order Details'!$E:$E,"Yes",'Order Details'!$C:$C,'Master Data'!$C$4)+SUMIFS('Order Details'!$P:$P,'Order Details'!$N:$N,Dashboard!$Q24,'Order Details'!$E:$E,"Yes",'Order Details'!$C:$C,'Master Data'!$C$5)+SUMIFS('Order Details'!$P:$P,'Order Details'!$N:$N,Dashboard!$Q24,'Order Details'!$E:$E,"Yes",'Order Details'!$C:$C,'Master Data'!$C$6)+SUMIFS('Order Details'!$P:$P,'Order Details'!$N:$N,Dashboard!$Q24,'Order Details'!$E:$E,"Yes",'Order Details'!$C:$C,'Master Data'!$C$7) -> 116462.16 | U24: =SUMIFS('Order Details'!$V:$V,'Order Details'!$N:$N,Dashboard!$Q24,'Order Details'!$E:$E,"Yes",'Order Details'!$C:$C,'Master Data'!$C$4)+SUMIFS('Order Details'!$V:$V,'Order Details'!$N:$N,Dashboard!$Q24,'Order Details'!$E:$E,"Yes",'Order Details'!$C:$C,'Master Data'!$C$5)+SUMIFS('Order Details'!$V:$V,'Order Details'!$N:$N,Dashboard!$Q24,'Order Details'!$E:$E,"Yes",'Order Details'!$C:$C,'Master Data'!$C$6)+SUMIFS('Order Details'!$V:$V,'Order Details'!$N:$N,Dashboard!$Q24,'Order Details'!$E:$E,"Yes",'Order Details'!$C:$C,'Master Data'!$C$7) -> 898551.29 | AB24: Pending Telex / Seaway: | AC24: =COUNTIFS('Order Summary'!$AJ4:$AJ200,"<>"&"",'Order Summary'!$AM4:$AM200,"",'Order Summary'!$G$4:$G$200,"Yes")+COUNTIFS('Order Summary'!$AJ4:$AJ200,"<>"&"",'Order Summary'!$AM4:$AM200,"PENDING",'Order Summary'!$G$4:$G$200,"Yes") -> 33
Q25: ASC 0069 GLOSSY WHITE | R25: =SUMIFS('Order Details'!$Q:$Q,'Order Details'!$N:$N,Dashboard!$Q25,'Order Details'!$E:$E,"Yes",'Order Details'!$C:$C,'Master Data'!$C$4)+SUMIFS('Order Details'!$Q:$Q,'Order Details'!$N:$N,Dashboard!$Q25,'Order Details'!$E:$E,"Yes",'Order Details'!$C:$C,'Master Data'!$C$5)+SUMIFS('Order Details'!$Q:$Q,'Order Details'!$N:$N,Dashboard!$Q25,'Order Details'!$E:$E,"Yes",'Order Details'!$C:$C,'Master Data'!$C$6)+SUMIFS('Order Details'!$Q:$Q,'Order Details'!$N:$N,Dashboard!$Q25,'Order Details'!$E:$E,"Yes",'Order Details'!$C:$C,'Master Data'!$C$7) -> 66100 | S25: =SUMIFS('Order Details'!$O:$O,'Order Details'!$N:$N,Dashboard!$Q25,'Order Details'!$E:$E,"Yes",'Order Details'!$C:$C,'Master Data'!$C$4)+SUMIFS('Order Details'!$O:$O,'Order Details'!$N:$N,Dashboard!$Q25,'Order Details'!$E:$E,"Yes",'Order Details'!$C:$C,'Master Data'!$C$5)+SUMIFS('Order Details'!$O:$O,'Order Details'!$N:$N,Dashboard!$Q25,'Order Details'!$E:$E,"Yes",'Order Details'!$C:$C,'Master Data'!$C$6)+SUMIFS('Order Details'!$O:$O,'Order Details'!$N:$N,Dashboard!$Q25,'Order Details'!$E:$E,"Yes",'Order Details'!$C:$C,'Master Data'!$C$7) -> 2234.434 | T25: =SUMIFS('Order Details'!$P:$P,'Order Details'!$N:$N,Dashboard!$Q25,'Order Details'!$E:$E,"Yes",'Order Details'!$C:$C,'Master Data'!$C$4)+SUMIFS('Order Details'!$P:$P,'Order Details'!$N:$N,Dashboard!$Q25,'Order Details'!$E:$E,"Yes",'Order Details'!$C:$C,'Master Data'!$C$5)+SUMIFS('Order Details'!$P:$P,'Order Details'!$N:$N,Dashboard!$Q25,'Order Details'!$E:$E,"Yes",'Order Details'!$C:$C,'Master Data'!$C$6)+SUMIFS('Order Details'!$P:$P,'Order Details'!$N:$N,Dashboard!$Q25,'Order Details'!$E:$E,"Yes",'Order Details'!$C:$C,'Master Data'!$C$7) -> 207781.16 | U25: =SUMIFS('Order Details'!$V:$V,'Order Details'!$N:$N,Dashboard!$Q25,'Order Details'!$E:$E,"Yes",'Order Details'!$C:$C,'Master Data'!$C$4)+SUMIFS('Order Details'!$V:$V,'Order Details'!$N:$N,Dashboard!$Q25,'Order Details'!$E:$E,"Yes",'Order Details'!$C:$C,'Master Data'!$C$5)+SUMIFS('Order Details'!$V:$V,'Order Details'!$N:$N,Dashboard!$Q25,'Order Details'!$E:$E,"Yes",'Order Details'!$C:$C,'Master Data'!$C$6)+SUMIFS('Order Details'!$V:$V,'Order Details'!$N:$N,Dashboard!$Q25,'Order Details'!$E:$E,"Yes",'Order Details'!$C:$C,'Master Data'!$C$7) -> 1604447.2
Q26: AMC 0103 SILVER FROST | R26: =SUMIFS('Order Details'!$Q:$Q,'Order Details'!$N:$N,Dashboard!$Q26,'Order Details'!$E:$E,"Yes",'Order Details'!$C:$C,'Master Data'!$C$4)+SUMIFS('Order Details'!$Q:$Q,'Order Details'!$N:$N,Dashboard!$Q26,'Order Details'!$E:$E,"Yes",'Order Details'!$C:$C,'Master Data'!$C$5)+SUMIFS('Order Details'!$Q:$Q,'Order Details'!$N:$N,Dashboard!$Q26,'Order Details'!$E:$E,"Yes",'Order Details'!$C:$C,'Master Data'!$C$6)+SUMIFS('Order Details'!$Q:$Q,'Order Details'!$N:$N,Dashboard!$Q26,'Order Details'!$E:$E,"Yes",'Order Details'!$C:$C,'Master Data'!$C$7) -> 25200 | S26: =SUMIFS('Order Details'!$O:$O,'Order Details'!$N:$N,Dashboard!$Q26,'Order Details'!$E:$E,"Yes",'Order Details'!$C:$C,'Master Data'!$C$4)+SUMIFS('Order Details'!$O:$O,'Order Details'!$N:$N,Dashboard!$Q26,'Order Details'!$E:$E,"Yes",'Order Details'!$C:$C,'Master Data'!$C$5)+SUMIFS('Order Details'!$O:$O,'Order Details'!$N:$N,Dashboard!$Q26,'Order Details'!$E:$E,"Yes",'Order Details'!$C:$C,'Master Data'!$C$6)+SUMIFS('Order Details'!$O:$O,'Order Details'!$N:$N,Dashboard!$Q26,'Order Details'!$E:$E,"Yes",'Order Details'!$C:$C,'Master Data'!$C$7) -> 857.805 | T26: =SUMIFS('Order Details'!$P:$P,'Order Details'!$N:$N,Dashboard!$Q26,'Order Details'!$E:$E,"Yes",'Order Details'!$C:$C,'Master Data'!$C$4)+SUMIFS('Order Details'!$P:$P,'Order Details'!$N:$N,Dashboard!$Q26,'Order Details'!$E:$E,"Yes",'Order Details'!$C:$C,'Master Data'!$C$5)+SUMIFS('Order Details'!$P:$P,'Order Details'!$N:$N,Dashboard!$Q26,'Order Details'!$E:$E,"Yes",'Order Details'!$C:$C,'Master Data'!$C$6)+SUMIFS('Order Details'!$P:$P,'Order Details'!$N:$N,Dashboard!$Q26,'Order Details'!$E:$E,"Yes",'Order Details'!$C:$C,'Master Data'!$C$7) -> 79768.146 | U26: =SUMIFS('Order Details'!$V:$V,'Order Details'!$N:$N,Dashboard!$Q26,'Order Details'!$E:$E,"Yes",'Order Details'!$C:$C,'Master Data'!$C$4)+SUMIFS('Order Details'!$V:$V,'Order Details'!$N:$N,Dashboard!$Q26,'Order Details'!$E:$E,"Yes",'Order Details'!$C:$C,'Master Data'!$C$5)+SUMIFS('Order Details'!$V:$V,'Order Details'!$N:$N,Dashboard!$Q26,'Order Details'!$E:$E,"Yes",'Order Details'!$C:$C,'Master Data'!$C$6)+SUMIFS('Order Details'!$V:$V,'Order Details'!$N:$N,Dashboard!$Q26,'Order Details'!$E:$E,"Yes",'Order Details'!$C:$C,'Master Data'!$C$7) -> 616120.48
Q27: AMC 0086 CHARCOAL METALLIC | R27: =SUMIFS('Order Details'!$Q:$Q,'Order Details'!$N:$N,Dashboard!$Q27,'Order Details'!$E:$E,"Yes",'Order Details'!$C:$C,'Master Data'!$C$4)+SUMIFS('Order Details'!$Q:$Q,'Order Details'!$N:$N,Dashboard!$Q27,'Order Details'!$E:$E,"Yes",'Order Details'!$C:$C,'Master Data'!$C$5)+SUMIFS('Order Details'!$Q:$Q,'Order Details'!$N:$N,Dashboard!$Q27,'Order Details'!$E:$E,"Yes",'Order Details'!$C:$C,'Master Data'!$C$6)+SUMIFS('Order Details'!$Q:$Q,'Order Details'!$N:$N,Dashboard!$Q27,'Order Details'!$E:$E,"Yes",'Order Details'!$C:$C,'Master Data'!$C$7) -> 15750 | S27: =SUMIFS('Order Details'!$O:$O,'Order Details'!$N:$N,Dashboard!$Q27,'Order Details'!$E:$E,"Yes",'Order Details'!$C:$C,'Master Data'!$C$4)+SUMIFS('Order Details'!$O:$O,'Order Details'!$N:$N,Dashboard!$Q27,'Order Details'!$E:$E,"Yes",'Order Details'!$C:$C,'Master Data'!$C$5)+SUMIFS('Order Details'!$O:$O,'Order Details'!$N:$N,Dashboard!$Q27,'Order Details'!$E:$E,"Yes",'Order Details'!$C:$C,'Master Data'!$C$6)+SUMIFS('Order Details'!$O:$O,'Order Details'!$N:$N,Dashboard!$Q27,'Order Details'!$E:$E,"Yes",'Order Details'!$C:$C,'Master Data'!$C$7) -> 541.586 | T27: =SUMIFS('Order Details'!$P:$P,'Order Details'!$N:$N,Dashboard!$Q27,'Order Details'!$E:$E,"Yes",'Order Details'!$C:$C,'Master Data'!$C$4)+SUMIFS('Order Details'!$P:$P,'Order Details'!$N:$N,Dashboard!$Q27,'Order Details'!$E:$E,"Yes",'Order Details'!$C:$C,'Master Data'!$C$5)+SUMIFS('Order Details'!$P:$P,'Order Details'!$N:$N,Dashboard!$Q27,'Order Details'!$E:$E,"Yes",'Order Details'!$C:$C,'Master Data'!$C$6)+SUMIFS('Order Details'!$P:$P,'Order Details'!$N:$N,Dashboard!$Q27,'Order Details'!$E:$E,"Yes",'Order Details'!$C:$C,'Master Data'!$C$7) -> 50362.18 | U27: =SUMIFS('Order Details'!$V:$V,'Order Details'!$N:$N,Dashboard!$Q27,'Order Details'!$E:$E,"Yes",'Order Details'!$C:$C,'Master Data'!$C$4)+SUMIFS('Order Details'!$V:$V,'Order Details'!$N:$N,Dashboard!$Q27,'Order Details'!$E:$E,"Yes",'Order Details'!$C:$C,'Master Data'!$C$5)+SUMIFS('Order Details'!$V:$V,'Order Details'!$N:$N,Dashboard!$Q27,'Order Details'!$E:$E,"Yes",'Order Details'!$C:$C,'Master Data'!$C$6)+SUMIFS('Order Details'!$V:$V,'Order Details'!$N:$N,Dashboard!$Q27,'Order Details'!$E:$E,"Yes",'Order Details'!$C:$C,'Master Data'!$C$7) -> 416252.2
Q28: ASC 0099 MATTE BLACK | R28: =SUMIFS('Order Details'!$Q:$Q,'Order Details'!$N:$N,Dashboard!$Q28,'Order Details'!$E:$E,"Yes",'Order Details'!$C:$C,'Master Data'!$C$4)+SUMIFS('Order Details'!$Q:$Q,'Order Details'!$N:$N,Dashboard!$Q28,'Order Details'!$E:$E,"Yes",'Order Details'!$C:$C,'Master Data'!$C$5)+SUMIFS('Order Details'!$Q:$Q,'Order Details'!$N:$N,Dashboard!$Q28,'Order Details'!$E:$E,"Yes",'Order Details'!$C:$C,'Master Data'!$C$6)+SUMIFS('Order Details'!$Q:$Q,'Order Details'!$N:$N,Dashboard!$Q28,'Order Details'!$E:$E,"Yes",'Order Details'!$C:$C,'Master Data'!$C$7) -> 0 | S28: =SUMIFS('Order Details'!$O:$O,'Order Details'!$N:$N,Dashboard!$Q28,'Order Details'!$E:$E,"Yes",'Order Details'!$C:$C,'Master Data'!$C$4)+SUMIFS('Order Details'!$O:$O,'Order Details'!$N:$N,Dashboard!$Q28,'Order Details'!$E:$E,"Yes",'Order Details'!$C:$C,'Master Data'!$C$5)+SUMIFS('Order Details'!$O:$O,'Order Details'!$N:$N,Dashboard!$Q28,'Order Details'!$E:$E,"Yes",'Order Details'!$C:$C,'Master Data'!$C$6)+SUMIFS('Order Details'!$O:$O,'Order Details'!$N:$N,Dashboard!$Q28,'Order Details'!$E:$E,"Yes",'Order Details'!$C:$C,'Master Data'!$C$7) -> 0 | T28: =SUMIFS('Order Details'!$P:$P,'Order Details'!$N:$N,Dashboard!$Q28,'Order Details'!$E:$E,"Yes",'Order Details'!$C:$C,'Master Data'!$C$4)+SUMIFS('Order Details'!$P:$P,'Order Details'!$N:$N,Dashboard!$Q28,'Order Details'!$E:$E,"Yes",'Order Details'!$C:$C,'Master Data'!$C$5)+SUMIFS('Order Details'!$P:$P,'Order Details'!$N:$N,Dashboard!$Q28,'Order Details'!$E:$E,"Yes",'Order Details'!$C:$C,'Master Data'!$C$6)+SUMIFS('Order Details'!$P:$P,'Order Details'!$N:$N,Dashboard!$Q28,'Order Details'!$E:$E,"Yes",'Order Details'!$C:$C,'Master Data'!$C$7) -> 0 | U28: =SUMIFS('Order Details'!$V:$V,'Order Details'!$N:$N,Dashboard!$Q28,'Order Details'!$E:$E,"Yes",'Order Details'!$C:$C,'Master Data'!$C$4)+SUMIFS('Order Details'!$V:$V,'Order Details'!$N:$N,Dashboard!$Q28,'Order Details'!$E:$E,"Yes",'Order Details'!$C:$C,'Master Data'!$C$5)+SUMIFS('Order Details'!$V:$V,'Order Details'!$N:$N,Dashboard!$Q28,'Order Details'!$E:$E,"Yes",'Order Details'!$C:$C,'Master Data'!$C$6)+SUMIFS('Order Details'!$V:$V,'Order Details'!$N:$N,Dashboard!$Q28,'Order Details'!$E:$E,"Yes",'Order Details'!$C:$C,'Master Data'!$C$7) -> 0
Q29: ASC 0092 PEPSI BLUE | R29: =SUMIFS('Order Details'!$Q:$Q,'Order Details'!$N:$N,Dashboard!$Q29,'Order Details'!$E:$E,"Yes",'Order Details'!$C:$C,'Master Data'!$C$4)+SUMIFS('Order Details'!$Q:$Q,'Order Details'!$N:$N,Dashboard!$Q29,'Order Details'!$E:$E,"Yes",'Order Details'!$C:$C,'Master Data'!$C$5)+SUMIFS('Order Details'!$Q:$Q,'Order Details'!$N:$N,Dashboard!$Q29,'Order Details'!$E:$E,"Yes",'Order Details'!$C:$C,'Master Data'!$C$6)+SUMIFS('Order Details'!$Q:$Q,'Order Details'!$N:$N,Dashboard!$Q29,'Order Details'!$E:$E,"Yes",'Order Details'!$C:$C,'Master Data'!$C$7) -> 200 | S29: =SUMIFS('Order Details'!$O:$O,'Order Details'!$N:$N,Dashboard!$Q29,'Order Details'!$E:$E,"Yes",'Order Details'!$C:$C,'Master Data'!$C$4)+SUMIFS('Order Details'!$O:$O,'Order Details'!$N:$N,Dashboard!$Q29,'Order Details'!$E:$E,"Yes",'Order Details'!$C:$C,'Master Data'!$C$5)+SUMIFS('Order Details'!$O:$O,'Order Details'!$N:$N,Dashboard!$Q29,'Order Details'!$E:$E,"Yes",'Order Details'!$C:$C,'Master Data'!$C$6)+SUMIFS('Order Details'!$O:$O,'Order Details'!$N:$N,Dashboard!$Q29,'Order Details'!$E:$E,"Yes",'Order Details'!$C:$C,'Master Data'!$C$7) -> 8.167 | T29: =SUMIFS('Order Details'!$P:$P,'Order Details'!$N:$N,Dashboard!$Q29,'Order Details'!$E:$E,"Yes",'Order Details'!$C:$C,'Master Data'!$C$4)+SUMIFS('Order Details'!$P:$P,'Order Details'!$N:$N,Dashboard!$Q29,'Order Details'!$E:$E,"Yes",'Order Details'!$C:$C,'Master Data'!$C$5)+SUMIFS('Order Details'!$P:$P,'Order Details'!$N:$N,Dashboard!$Q29,'Order Details'!$E:$E,"Yes",'Order Details'!$C:$C,'Master Data'!$C$6)+SUMIFS('Order Details'!$P:$P,'Order Details'!$N:$N,Dashboard!$Q29,'Order Details'!$E:$E,"Yes",'Order Details'!$C:$C,'Master Data'!$C$7) -> 759.45 | U29: =SUMIFS('Order Details'!$V:$V,'Order Details'!$N:$N,Dashboard!$Q29,'Order Details'!$E:$E,"Yes",'Order Details'!$C:$C,'Master Data'!$C$4)+SUMIFS('Order Details'!$V:$V,'Order Details'!$N:$N,Dashboard!$Q29,'Order Details'!$E:$E,"Yes",'Order Details'!$C:$C,'Master Data'!$C$5)+SUMIFS('Order Details'!$V:$V,'Order Details'!$N:$N,Dashboard!$Q29,'Order Details'!$E:$E,"Yes",'Order Details'!$C:$C,'Master Data'!$C$6)+SUMIFS('Order Details'!$V:$V,'Order Details'!$N:$N,Dashboard!$Q29,'Order Details'!$E:$E,"Yes",'Order Details'!$C:$C,'Master Data'!$C$7) -> 5870.5485
Q30: ASC 0089 VICTORY RED | R30: =SUMIFS('Order Details'!$Q:$Q,'Order Details'!$N:$N,Dashboard!$Q30,'Order Details'!$E:$E,"Yes",'Order Details'!$C:$C,'Master Data'!$C$4)+SUMIFS('Order Details'!$Q:$Q,'Order Details'!$N:$N,Dashboard!$Q30,'Order Details'!$E:$E,"Yes",'Order Details'!$C:$C,'Master Data'!$C$5)+SUMIFS('Order Details'!$Q:$Q,'Order Details'!$N:$N,Dashboard!$Q30,'Order Details'!$E:$E,"Yes",'Order Details'!$C:$C,'Master Data'!$C$6)+SUMIFS('Order Details'!$Q:$Q,'Order Details'!$N:$N,Dashboard!$Q30,'Order Details'!$E:$E,"Yes",'Order Details'!$C:$C,'Master Data'!$C$7) -> 8400 | S30: =SUMIFS('Order Details'!$O:$O,'Order Details'!$N:$N,Dashboard!$Q30,'Order Details'!$E:$E,"Yes",'Order Details'!$C:$C,'Master Data'!$C$4)+SUMIFS('Order Details'!$O:$O,'Order Details'!$N:$N,Dashboard!$Q30,'Order Details'!$E:$E,"Yes",'Order Details'!$C:$C,'Master Data'!$C$5)+SUMIFS('Order Details'!$O:$O,'Order Details'!$N:$N,Dashboard!$Q30,'Order Details'!$E:$E,"Yes",'Order Details'!$C:$C,'Master Data'!$C$6)+SUMIFS('Order Details'!$O:$O,'Order Details'!$N:$N,Dashboard!$Q30,'Order Details'!$E:$E,"Yes",'Order Details'!$C:$C,'Master Data'!$C$7) -> 291.685 | T30: =SUMIFS('Order Details'!$P:$P,'Order Details'!$N:$N,Dashboard!$Q30,'Order Details'!$E:$E,"Yes",'Order Details'!$C:$C,'Master Data'!$C$4)+SUMIFS('Order Details'!$P:$P,'Order Details'!$N:$N,Dashboard!$Q30,'Order Details'!$E:$E,"Yes",'Order Details'!$C:$C,'Master Data'!$C$5)+SUMIFS('Order Details'!$P:$P,'Order Details'!$N:$N,Dashboard!$Q30,'Order Details'!$E:$E,"Yes",'Order Details'!$C:$C,'Master Data'!$C$6)+SUMIFS('Order Details'!$P:$P,'Order Details'!$N:$N,Dashboard!$Q30,'Order Details'!$E:$E,"Yes",'Order Details'!$C:$C,'Master Data'!$C$7) -> 27124.317 | U30: =SUMIFS('Order Details'!$V:$V,'Order Details'!$N:$N,Dashboard!$Q30,'Order Details'!$E:$E,"Yes",'Order Details'!$C:$C,'Master Data'!$C$4)+SUMIFS('Order Details'!$V:$V,'Order Details'!$N:$N,Dashboard!$Q30,'Order Details'!$E:$E,"Yes",'Order Details'!$C:$C,'Master Data'!$C$5)+SUMIFS('Order Details'!$V:$V,'Order Details'!$N:$N,Dashboard!$Q30,'Order Details'!$E:$E,"Yes",'Order Details'!$C:$C,'Master Data'!$C$6)+SUMIFS('Order Details'!$V:$V,'Order Details'!$N:$N,Dashboard!$Q30,'Order Details'!$E:$E,"Yes",'Order Details'!$C:$C,'Master Data'!$C$7) -> 207377.53
Q31: AMC 0104 PEWTER | R31: =SUMIFS('Order Details'!$Q:$Q,'Order Details'!$N:$N,Dashboard!$Q31,'Order Details'!$E:$E,"Yes",'Order Details'!$C:$C,'Master Data'!$C$4)+SUMIFS('Order Details'!$Q:$Q,'Order Details'!$N:$N,Dashboard!$Q31,'Order Details'!$E:$E,"Yes",'Order Details'!$C:$C,'Master Data'!$C$5)+SUMIFS('Order Details'!$Q:$Q,'Order Details'!$N:$N,Dashboard!$Q31,'Order Details'!$E:$E,"Yes",'Order Details'!$C:$C,'Master Data'!$C$6)+SUMIFS('Order Details'!$Q:$Q,'Order Details'!$N:$N,Dashboard!$Q31,'Order Details'!$E:$E,"Yes",'Order Details'!$C:$C,'Master Data'!$C$7) -> 0 | S31: =SUMIFS('Order Details'!$O:$O,'Order Details'!$N:$N,Dashboard!$Q31,'Order Details'!$E:$E,"Yes",'Order Details'!$C:$C,'Master Data'!$C$4)+SUMIFS('Order Details'!$O:$O,'Order Details'!$N:$N,Dashboard!$Q31,'Order Details'!$E:$E,"Yes",'Order Details'!$C:$C,'Master Data'!$C$5)+SUMIFS('Order Details'!$O:$O,'Order Details'!$N:$N,Dashboard!$Q31,'Order Details'!$E:$E,"Yes",'Order Details'!$C:$C,'Master Data'!$C$6)+SUMIFS('Order Details'!$O:$O,'Order Details'!$N:$N,Dashboard!$Q31,'Order Details'!$E:$E,"Yes",'Order Details'!$C:$C,'Master Data'!$C$7) -> 0 | T31: =SUMIFS('Order Details'!$P:$P,'Order Details'!$N:$N,Dashboard!$Q31,'Order Details'!$E:$E,"Yes",'Order Details'!$C:$C,'Master Data'!$C$4)+SUMIFS('Order Details'!$P:$P,'Order Details'!$N:$N,Dashboard!$Q31,'Order Details'!$E:$E,"Yes",'Order Details'!$C:$C,'Master Data'!$C$5)+SUMIFS('Order Details'!$P:$P,'Order Details'!$N:$N,Dashboard!$Q31,'Order Details'!$E:$E,"Yes",'Order Details'!$C:$C,'Master Data'!$C$6)+SUMIFS('Order Details'!$P:$P,'Order Details'!$N:$N,Dashboard!$Q31,'Order Details'!$E:$E,"Yes",'Order Details'!$C:$C,'Master Data'!$C$7) -> 0 | U31: =SUMIFS('Order Details'!$V:$V,'Order Details'!$N:$N,Dashboard!$Q31,'Order Details'!$E:$E,"Yes",'Order Details'!$C:$C,'Master Data'!$C$4)+SUMIFS('Order Details'!$V:$V,'Order Details'!$N:$N,Dashboard!$Q31,'Order Details'!$E:$E,"Yes",'Order Details'!$C:$C,'Master Data'!$C$5)+SUMIFS('Order Details'!$V:$V,'Order Details'!$N:$N,Dashboard!$Q31,'Order Details'!$E:$E,"Yes",'Order Details'!$C:$C,'Master Data'!$C$6)+SUMIFS('Order Details'!$V:$V,'Order Details'!$N:$N,Dashboard!$Q31,'Order Details'!$E:$E,"Yes",'Order Details'!$C:$C,'Master Data'!$C$7) -> 0
Q32: ASC 0105 INDIGO BLUE | R32: =SUMIFS('Order Details'!$Q:$Q,'Order Details'!$N:$N,Dashboard!$Q32,'Order Details'!$E:$E,"Yes",'Order Details'!$C:$C,'Master Data'!$C$4)+SUMIFS('Order Details'!$Q:$Q,'Order Details'!$N:$N,Dashboard!$Q32,'Order Details'!$E:$E,"Yes",'Order Details'!$C:$C,'Master Data'!$C$5)+SUMIFS('Order Details'!$Q:$Q,'Order Details'!$N:$N,Dashboard!$Q32,'Order Details'!$E:$E,"Yes",'Order Details'!$C:$C,'Master Data'!$C$6)+SUMIFS('Order Details'!$Q:$Q,'Order Details'!$N:$N,Dashboard!$Q32,'Order Details'!$E:$E,"Yes",'Order Details'!$C:$C,'Master Data'!$C$7) -> 7750 | S32: =SUMIFS('Order Details'!$O:$O,'Order Details'!$N:$N,Dashboard!$Q32,'Order Details'!$E:$E,"Yes",'Order Details'!$C:$C,'Master Data'!$C$4)+SUMIFS('Order Details'!$O:$O,'Order Details'!$N:$N,Dashboard!$Q32,'Order Details'!$E:$E,"Yes",'Order Details'!$C:$C,'Master Data'!$C$5)+SUMIFS('Order Details'!$O:$O,'Order Details'!$N:$N,Dashboard!$Q32,'Order Details'!$E:$E,"Yes",'Order Details'!$C:$C,'Master Data'!$C$6)+SUMIFS('Order Details'!$O:$O,'Order Details'!$N:$N,Dashboard!$Q32,'Order Details'!$E:$E,"Yes",'Order Details'!$C:$C,'Master Data'!$C$7) -> 266.981 | T32: =SUMIFS('Order Details'!$P:$P,'Order Details'!$N:$N,Dashboard!$Q32,'Order Details'!$E:$E,"Yes",'Order Details'!$C:$C,'Master Data'!$C$4)+SUMIFS('Order Details'!$P:$P,'Order Details'!$N:$N,Dashboard!$Q32,'Order Details'!$E:$E,"Yes",'Order Details'!$C:$C,'Master Data'!$C$5)+SUMIFS('Order Details'!$P:$P,'Order Details'!$N:$N,Dashboard!$Q32,'Order Details'!$E:$E,"Yes",'Order Details'!$C:$C,'Master Data'!$C$6)+SUMIFS('Order Details'!$P:$P,'Order Details'!$N:$N,Dashboard!$Q32,'Order Details'!$E:$E,"Yes",'Order Details'!$C:$C,'Master Data'!$C$7) -> 24826.981 | U32: =SUMIFS('Order Details'!$V:$V,'Order Details'!$N:$N,Dashboard!$Q32,'Order Details'!$E:$E,"Yes",'Order Details'!$C:$C,'Master Data'!$C$4)+SUMIFS('Order Details'!$V:$V,'Order Details'!$N:$N,Dashboard!$Q32,'Order Details'!$E:$E,"Yes",'Order Details'!$C:$C,'Master Data'!$C$5)+SUMIFS('Order Details'!$V:$V,'Order Details'!$N:$N,Dashboard!$Q32,'Order Details'!$E:$E,"Yes",'Order Details'!$C:$C,'Master Data'!$C$6)+SUMIFS('Order Details'!$V:$V,'Order Details'!$N:$N,Dashboard!$Q32,'Order Details'!$E:$E,"Yes",'Order Details'!$C:$C,'Master Data'!$C$7) -> 203450.98
Q33: ASC 0164 ARMY GREEN | R33: =SUMIFS('Order Details'!$Q:$Q,'Order Details'!$N:$N,Dashboard!$Q33,'Order Details'!$E:$E,"Yes",'Order Details'!$C:$C,'Master Data'!$C$4)+SUMIFS('Order Details'!$Q:$Q,'Order Details'!$N:$N,Dashboard!$Q33,'Order Details'!$E:$E,"Yes",'Order Details'!$C:$C,'Master Data'!$C$5)+SUMIFS('Order Details'!$Q:$Q,'Order Details'!$N:$N,Dashboard!$Q33,'Order Details'!$E:$E,"Yes",'Order Details'!$C:$C,'Master Data'!$C$6)+SUMIFS('Order Details'!$Q:$Q,'Order Details'!$N:$N,Dashboard!$Q33,'Order Details'!$E:$E,"Yes",'Order Details'!$C:$C,'Master Data'!$C$7) -> 2800 | S33: =SUMIFS('Order Details'!$O:$O,'Order Details'!$N:$N,Dashboard!$Q33,'Order Details'!$E:$E,"Yes",'Order Details'!$C:$C,'Master Data'!$C$4)+SUMIFS('Order Details'!$O:$O,'Order Details'!$N:$N,Dashboard!$Q33,'Order Details'!$E:$E,"Yes",'Order Details'!$C:$C,'Master Data'!$C$5)+SUMIFS('Order Details'!$O:$O,'Order Details'!$N:$N,Dashboard!$Q33,'Order Details'!$E:$E,"Yes",'Order Details'!$C:$C,'Master Data'!$C$6)+SUMIFS('Order Details'!$O:$O,'Order Details'!$N:$N,Dashboard!$Q33,'Order Details'!$E:$E,"Yes",'Order Details'!$C:$C,'Master Data'!$C$7) -> 93.61 | T33: =SUMIFS('Order Details'!$P:$P,'Order Details'!$N:$N,Dashboard!$Q33,'Order Details'!$E:$E,"Yes",'Order Details'!$C:$C,'Master Data'!$C$4)+SUMIFS('Order Details'!$P:$P,'Order Details'!$N:$N,Dashboard!$Q33,'Order Details'!$E:$E,"Yes",'Order Details'!$C:$C,'Master Data'!$C$5)+SUMIFS('Order Details'!$P:$P,'Order Details'!$N:$N,Dashboard!$Q33,'Order Details'!$E:$E,"Yes",'Order Details'!$C:$C,'Master Data'!$C$6)+SUMIFS('Order Details'!$P:$P,'Order Details'!$N:$N,Dashboard!$Q33,'Order Details'!$E:$E,"Yes",'Order Details'!$C:$C,'Master Data'!$C$7) -> 8705.04 | U33: =SUMIFS('Order Details'!$V:$V,'Order Details'!$N:$N,Dashboard!$Q33,'Order Details'!$E:$E,"Yes",'Order Details'!$C:$C,'Master Data'!$C$4)+SUMIFS('Order Details'!$V:$V,'Order Details'!$N:$N,Dashboard!$Q33,'Order Details'!$E:$E,"Yes",'Order Details'!$C:$C,'Master Data'!$C$5)+SUMIFS('Order Details'!$V:$V,'Order Details'!$N:$N,Dashboard!$Q33,'Order Details'!$E:$E,"Yes",'Order Details'!$C:$C,'Master Data'!$C$6)+SUMIFS('Order Details'!$V:$V,'Order Details'!$N:$N,Dashboard!$Q33,'Order Details'!$E:$E,"Yes",'Order Details'!$C:$C,'Master Data'!$C$7) -> 71990.681
Q34: ASC 0127 SAND SAHARA | R34: =SUMIFS('Order Details'!$Q:$Q,'Order Details'!$N:$N,Dashboard!$Q34,'Order Details'!$E:$E,"Yes",'Order Details'!$C:$C,'Master Data'!$C$4)+SUMIFS('Order Details'!$Q:$Q,'Order Details'!$N:$N,Dashboard!$Q34,'Order Details'!$E:$E,"Yes",'Order Details'!$C:$C,'Master Data'!$C$5)+SUMIFS('Order Details'!$Q:$Q,'Order Details'!$N:$N,Dashboard!$Q34,'Order Details'!$E:$E,"Yes",'Order Details'!$C:$C,'Master Data'!$C$6)+SUMIFS('Order Details'!$Q:$Q,'Order Details'!$N:$N,Dashboard!$Q34,'Order Details'!$E:$E,"Yes",'Order Details'!$C:$C,'Master Data'!$C$7) -> 0 | S34: =SUMIFS('Order Details'!$O:$O,'Order Details'!$N:$N,Dashboard!$Q34,'Order Details'!$E:$E,"Yes",'Order Details'!$C:$C,'Master Data'!$C$4)+SUMIFS('Order Details'!$O:$O,'Order Details'!$N:$N,Dashboard!$Q34,'Order Details'!$E:$E,"Yes",'Order Details'!$C:$C,'Master Data'!$C$5)+SUMIFS('Order Details'!$O:$O,'Order Details'!$N:$N,Dashboard!$Q34,'Order Details'!$E:$E,"Yes",'Order Details'!$C:$C,'Master Data'!$C$6)+SUMIFS('Order Details'!$O:$O,'Order Details'!$N:$N,Dashboard!$Q34,'Order Details'!$E:$E,"Yes",'Order Details'!$C:$C,'Master Data'!$C$7) -> 0 | T34: =SUMIFS('Order Details'!$P:$P,'Order Details'!$N:$N,Dashboard!$Q34,'Order Details'!$E:$E,"Yes",'Order Details'!$C:$C,'Master Data'!$C$4)+SUMIFS('Order Details'!$P:$P,'Order Details'!$N:$N,Dashboard!$Q34,'Order Details'!$E:$E,"Yes",'Order Details'!$C:$C,'Master Data'!$C$5)+SUMIFS('Order Details'!$P:$P,'Order Details'!$N:$N,Dashboard!$Q34,'Order Details'!$E:$E,"Yes",'Order Details'!$C:$C,'Master Data'!$C$6)+SUMIFS('Order Details'!$P:$P,'Order Details'!$N:$N,Dashboard!$Q34,'Order Details'!$E:$E,"Yes",'Order Details'!$C:$C,'Master Data'!$C$7) -> 0 | U34: =SUMIFS('Order Details'!$V:$V,'Order Details'!$N:$N,Dashboard!$Q34,'Order Details'!$E:$E,"Yes",'Order Details'!$C:$C,'Master Data'!$C$4)+SUMIFS('Order Details'!$V:$V,'Order Details'!$N:$N,Dashboard!$Q34,'Order Details'!$E:$E,"Yes",'Order Details'!$C:$C,'Master Data'!$C$5)+SUMIFS('Order Details'!$V:$V,'Order Details'!$N:$N,Dashboard!$Q34,'Order Details'!$E:$E,"Yes",'Order Details'!$C:$C,'Master Data'!$C$6)+SUMIFS('Order Details'!$V:$V,'Order Details'!$N:$N,Dashboard!$Q34,'Order Details'!$E:$E,"Yes",'Order Details'!$C:$C,'Master Data'!$C$7) -> 0
Q35: ASC 0208 SAND SAHARA MATTE | R35: =SUMIFS('Order Details'!$Q:$Q,'Order Details'!$N:$N,Dashboard!$Q35,'Order Details'!$E:$E,"Yes",'Order Details'!$C:$C,'Master Data'!$C$4)+SUMIFS('Order Details'!$Q:$Q,'Order Details'!$N:$N,Dashboard!$Q35,'Order Details'!$E:$E,"Yes",'Order Details'!$C:$C,'Master Data'!$C$5)+SUMIFS('Order Details'!$Q:$Q,'Order Details'!$N:$N,Dashboard!$Q35,'Order Details'!$E:$E,"Yes",'Order Details'!$C:$C,'Master Data'!$C$6)+SUMIFS('Order Details'!$Q:$Q,'Order Details'!$N:$N,Dashboard!$Q35,'Order Details'!$E:$E,"Yes",'Order Details'!$C:$C,'Master Data'!$C$7) -> 2400 | S35: =SUMIFS('Order Details'!$O:$O,'Order Details'!$N:$N,Dashboard!$Q35,'Order Details'!$E:$E,"Yes",'Order Details'!$C:$C,'Master Data'!$C$4)+SUMIFS('Order Details'!$O:$O,'Order Details'!$N:$N,Dashboard!$Q35,'Order Details'!$E:$E,"Yes",'Order Details'!$C:$C,'Master Data'!$C$5)+SUMIFS('Order Details'!$O:$O,'Order Details'!$N:$N,Dashboard!$Q35,'Order Details'!$E:$E,"Yes",'Order Details'!$C:$C,'Master Data'!$C$6)+SUMIFS('Order Details'!$O:$O,'Order Details'!$N:$N,Dashboard!$Q35,'Order Details'!$E:$E,"Yes",'Order Details'!$C:$C,'Master Data'!$C$7) -> 80.169 | T35: =SUMIFS('Order Details'!$P:$P,'Order Details'!$N:$N,Dashboard!$Q35,'Order Details'!$E:$E,"Yes",'Order Details'!$C:$C,'Master Data'!$C$4)+SUMIFS('Order Details'!$P:$P,'Order Details'!$N:$N,Dashboard!$Q35,'Order Details'!$E:$E,"Yes",'Order Details'!$C:$C,'Master Data'!$C$5)+SUMIFS('Order Details'!$P:$P,'Order Details'!$N:$N,Dashboard!$Q35,'Order Details'!$E:$E,"Yes",'Order Details'!$C:$C,'Master Data'!$C$6)+SUMIFS('Order Details'!$P:$P,'Order Details'!$N:$N,Dashboard!$Q35,'Order Details'!$E:$E,"Yes",'Order Details'!$C:$C,'Master Data'!$C$7) -> 7455.06 | U35: =SUMIFS('Order Details'!$V:$V,'Order Details'!$N:$N,Dashboard!$Q35,'Order Details'!$E:$E,"Yes",'Order Details'!$C:$C,'Master Data'!$C$4)+SUMIFS('Order Details'!$V:$V,'Order Details'!$N:$N,Dashboard!$Q35,'Order Details'!$E:$E,"Yes",'Order Details'!$C:$C,'Master Data'!$C$5)+SUMIFS('Order Details'!$V:$V,'Order Details'!$N:$N,Dashboard!$Q35,'Order Details'!$E:$E,"Yes",'Order Details'!$C:$C,'Master Data'!$C$6)+SUMIFS('Order Details'!$V:$V,'Order Details'!$N:$N,Dashboard!$Q35,'Order Details'!$E:$E,"Yes",'Order Details'!$C:$C,'Master Data'!$C$7) -> 61653.346
Q36: ASC 0090 YELLOW | R36: =SUMIFS('Order Details'!$Q:$Q,'Order Details'!$N:$N,Dashboard!$Q36,'Order Details'!$E:$E,"Yes",'Order Details'!$C:$C,'Master Data'!$C$4)+SUMIFS('Order Details'!$Q:$Q,'Order Details'!$N:$N,Dashboard!$Q36,'Order Details'!$E:$E,"Yes",'Order Details'!$C:$C,'Master Data'!$C$5)+SUMIFS('Order Details'!$Q:$Q,'Order Details'!$N:$N,Dashboard!$Q36,'Order Details'!$E:$E,"Yes",'Order Details'!$C:$C,'Master Data'!$C$6)+SUMIFS('Order Details'!$Q:$Q,'Order Details'!$N:$N,Dashboard!$Q36,'Order Details'!$E:$E,"Yes",'Order Details'!$C:$C,'Master Data'!$C$7) -> 0 | S36: =SUMIFS('Order Details'!$O:$O,'Order Details'!$N:$N,Dashboard!$Q36,'Order Details'!$E:$E,"Yes",'Order Details'!$C:$C,'Master Data'!$C$4)+SUMIFS('Order Details'!$O:$O,'Order Details'!$N:$N,Dashboard!$Q36,'Order Details'!$E:$E,"Yes",'Order Details'!$C:$C,'Master Data'!$C$5)+SUMIFS('Order Details'!$O:$O,'Order Details'!$N:$N,Dashboard!$Q36,'Order Details'!$E:$E,"Yes",'Order Details'!$C:$C,'Master Data'!$C$6)+SUMIFS('Order Details'!$O:$O,'Order Details'!$N:$N,Dashboard!$Q36,'Order Details'!$E:$E,"Yes",'Order Details'!$C:$C,'Master Data'!$C$7) -> 0 | T36: =SUMIFS('Order Details'!$P:$P,'Order Details'!$N:$N,Dashboard!$Q36,'Order Details'!$E:$E,"Yes",'Order Details'!$C:$C,'Master Data'!$C$4)+SUMIFS('Order Details'!$P:$P,'Order Details'!$N:$N,Dashboard!$Q36,'Order Details'!$E:$E,"Yes",'Order Details'!$C:$C,'Master Data'!$C$5)+SUMIFS('Order Details'!$P:$P,'Order Details'!$N:$N,Dashboard!$Q36,'Order Details'!$E:$E,"Yes",'Order Details'!$C:$C,'Master Data'!$C$6)+SUMIFS('Order Details'!$P:$P,'Order Details'!$N:$N,Dashboard!$Q36,'Order Details'!$E:$E,"Yes",'Order Details'!$C:$C,'Master Data'!$C$7) -> 0 | U36: =SUMIFS('Order Details'!$V:$V,'Order Details'!$N:$N,Dashboard!$Q36,'Order Details'!$E:$E,"Yes",'Order Details'!$C:$C,'Master Data'!$C$4)+SUMIFS('Order Details'!$V:$V,'Order Details'!$N:$N,Dashboard!$Q36,'Order Details'!$E:$E,"Yes",'Order Details'!$C:$C,'Master Data'!$C$5)+SUMIFS('Order Details'!$V:$V,'Order Details'!$N:$N,Dashboard!$Q36,'Order Details'!$E:$E,"Yes",'Order Details'!$C:$C,'Master Data'!$C$6)+SUMIFS('Order Details'!$V:$V,'Order Details'!$N:$N,Dashboard!$Q36,'Order Details'!$E:$E,"Yes",'Order Details'!$C:$C,'Master Data'!$C$7) -> 0
... Q38: ASC 0126 BRANDY WINE | R38: =SUMIFS('Order Details'!$Q:$Q,'Order Details'!$N:$N,Dashboard!$Q38,'Order Details'!$E:$E,"Yes",'Order Details'!$C:$C,'Master Data'!$C$4)+SUMIFS('Order Details'!$Q:$Q,'Order Details'!$N:$N,Dashboard!$Q38,'Order Details'!$E:$E,"Yes",'Order Details'!$C:$C,'Master Data'!$C$5)+SUMIFS('Order Details'!$Q:$Q,'Order Details'!$N:$N,Dashboard!$Q38,'Order Details'!$E:$E,"Yes",'Order Details'!$C:$C,'Master Data'!$C$6)+SUMIFS('Order Details'!$Q:$Q,'Order Details'!$N:$N,Dashboard!$Q38,'Order Details'!$E:$E,"Yes",'Order Details'!$C:$C,'Master Data'!$C$7) -> 0 | S38: =SUMIFS('Order Details'!$O:$O,'Order Details'!$N:$N,Dashboard!$Q38,'Order Details'!$E:$E,"Yes",'Order Details'!$C:$C,'Master Data'!$C$4)+SUMIFS('Order Details'!$O:$O,'Order Details'!$N:$N,Dashboard!$Q38,'Order Details'!$E:$E,"Yes",'Order Details'!$C:$C,'Master Data'!$C$5)+SUMIFS('Order Details'!$O:$O,'Order Details'!$N:$N,Dashboard!$Q38,'Order Details'!$E:$E,"Yes",'Order Details'!$C:$C,'Master Data'!$C$6)+SUMIFS('Order Details'!$O:$O,'Order Details'!$N:$N,Dashboard!$Q38,'Order Details'!$E:$E,"Yes",'Order Details'!$C:$C,'Master Data'!$C$7) -> 0 | T38: =SUMIFS('Order Details'!$P:$P,'Order Details'!$N:$N,Dashboard!$Q38,'Order Details'!$E:$E,"Yes",'Order Details'!$C:$C,'Master Data'!$C$4)+SUMIFS('Order Details'!$P:$P,'Order Details'!$N:$N,Dashboard!$Q38,'Order Details'!$E:$E,"Yes",'Order Details'!$C:$C,'Master Data'!$C$5)+SUMIFS('Order Details'!$P:$P,'Order Details'!$N:$N,Dashboard!$Q38,'Order Details'!$E:$E,"Yes",'Order Details'!$C:$C,'Master Data'!$C$6)+SUMIFS('Order Details'!$P:$P,'Order Details'!$N:$N,Dashboard!$Q38,'Order Details'!$E:$E,"Yes",'Order Details'!$C:$C,'Master Data'!$C$7) -> 0 | U38: =SUMIFS('Order Details'!$V:$V,'Order Details'!$N:$N,Dashboard!$Q38,'Order Details'!$E:$E,"Yes",'Order Details'!$C:$C,'Master Data'!$C$4)+SUMIFS('Order Details'!$V:$V,'Order Details'!$N:$N,Dashboard!$Q38,'Order Details'!$E:$E,"Yes",'Order Details'!$C:$C,'Master Data'!$C$5)+SUMIFS('Order Details'!$V:$V,'Order Details'!$N:$N,Dashboard!$Q38,'Order Details'!$E:$E,"Yes",'Order Details'!$C:$C,'Master Data'!$C$6)+SUMIFS('Order Details'!$V:$V,'Order Details'!$N:$N,Dashboard!$Q38,'Order Details'!$E:$E,"Yes",'Order Details'!$C:$C,'Master Data'!$C$7) -> 0
Q39: TOTALS | R39: =SUM(R24:R38) -> 165100 | S39: =SUM(S24:S38) -> 5626.863 | T39: =SUM(T24:T38) -> 523244.49 | U39: =SUM(U24:U38) -> 4085714.3
Q42: VOLUME SHIPPED
Q43: COLORS (Purple are Standard Colors) | R43: Sheets | S43: MSF | T43: M2 | U43: $
Q44: ASC 0096 GLOSSY BLACK | R44: =R4-R24 -> 51000 | S44: =S4-S24 -> 1807.694 | T44: =T4-T24 -> 165508.06 | U44: =U4-U24 -> 1246274.3
Q45: ASC 0069 GLOSSY WHITE | R45: =R5-R25 -> 55750 | S45: =S5-S25 -> 1934.6853 | T45: =T5-T25 -> 179596.67 | U45: =U5-U25 -> 1353851.1
Q46: AMC 0103 SILVER FROST | R46: =R6-R26 -> 45450 | S46: =S6-S26 -> 1591.4813 | T46: =T6-T26 -> 147679.47 | U46: =U6-U26 -> 1112769.2
Q47: AMC 0086 CHARCOAL METALLIC | R47: =R7-R27 -> 51200 | S47: =S7-S27 -> 1762.7443 | T47: =T7-T27 -> 163609.43 | U47: =U7-U27 -> 1323409.8
Q48: ASC 0099 MATTE BLACK | R48: =R8-R28 -> 7800 | S48: =S8-S28 -> 261.74167 | T48: =T8-T28 -> 24338.505 | U48: =U8-U28 -> 196411.74
Q49: ASC 0092 PEPSI BLUE | R49: =R9-R29 -> 600 | S49: =S9-S29 -> 20.485 | T49: =T9-T29 -> 1904.85 | U49: =U9-U29 -> 14343.521
Q50: ASC 0089 VICTORY RED | R50: =R10-R30 -> 1000 | S50: =S10-S30 -> 34.300333 | T50: =T10-T30 -> 3189.69 | U50: =U10-U30 -> 24018.366
Q51: AMC 0104 PEWTER | R51: =R11-R31 -> 0 | S51: =S11-S31 -> 0 | T51: =T11-T31 -> 0 | U51: =U11-U31 -> 0
Q52: ASC 0105 INDIGO BLUE | R52: =R12-R32 -> 1200 | S52: =S12-S32 -> 39.199333 | T52: =T12-T32 -> 3645.36 | U52: =U12-U32 -> 29418.055
Q53: ASC 0164 ARMY GREEN | R53: =R13-R33 -> 1400 | S53: =S13-S33 -> 45.733 | T53: =T13-T33 -> 4252.173 | U53: =U13-U33 -> 34315.036
Q54: ASC 0127 SAND SAHARA | R54: =R14-R34 -> 1400 | S54: =S14-S34 -> 45.733 | T54: =T14-T34 -> 4252.173 | U54: =U14-U34 -> 34315.036
Q55: ASC 0208 SAND SAHARA MATTE | R55: =R15-R35 -> 0 | S55: =S15-S35 -> 0 | T55: =T15-T35 -> 0 | U55: =U15-U35 -> 0
... Q58: ASC 0126 BRANDY WINE | R58: =R18-R38 -> 0 | S58: =S18-S38 -> 0 | T58: =T18-T38 -> 0 | U58: =U18-U38 -> 0
Q59: TOTALS | R59: =SUM(R44:R58) -> 216800 | S59: =SUM(S44:S58) -> 7543.7973 | T59: =SUM(T44:T58) -> 697976.38 | U59: =SUM(U44:U58) -> 5369126.1

Sheet Item Summary
B2: BACKLOG (SHEETS) | Q2: SHIPPED (SHEETS)
B3: ITEM | D3: STOCKING LOCATION | Q3: ITEM | S3: STOCKING LOCATION
B4: Product Code | C4: Description | D4: South Paris, ME | E4: Ashburn, GA | F4: Hillsboro, TX | G4: Nampa, ID | H4: Granger, IN | I4: Gordon, PA | J4: Minneota, MN | K4: Houston, TX | L4: Twin Falls, ID | M4: Savannah, GA | N4: TOTALS | Q4: Product Code | R4: Description | S4: South Paris, ME | T4: Ashburn, GA | U4: Hillsboro, TX | V4: Nampa, ID | W4: Granger, IN | X4: Gordon, PA | Y4: Minneota, MN | Z4: Houston, TX | AA4: Twin Falls, ID | AB4: Savannah, GA | AC4: TOTALS
B5: 704984 | C5: =VLOOKUP($B5,'Pricing Table - eff 27-Jan-2026'!$A:$L,9,FALSE)&""" "&VLOOKUP($B5,'Pricing Table - eff 27-Jan-2026'!$A:$L,12,FALSE) -> 84" GLOSSY BLACK | D5: =SUMIFS('Order Details'!$Q:$Q,'Order Details'!$E:$E,"Yes",'Order Details'!$I:$I,'Item Summary'!$B5,'Order Details'!$F:$F,'Item Summary'!D$4,'Order Details'!$C:$C,"PO Received")+SUMIFS('Order Details'!$Q:$Q,'Order Details'!$E:$E,"Yes",'Order Details'!$I:$I,'Item Summary'!$B5,'Order Details'!$F:$F,'Item Summary'!D$4,'Order Details'!$C:$C,"Proforma Invoice Sent")+SUMIFS('Order Details'!$Q:$Q,'Order Details'!$E:$E,"Yes",'Order Details'!$I:$I,'Item Summary'!$B5,'Order Details'!$F:$F,'Item Summary'!D$4,'Order Details'!$C:$C,"Downpayment Received")+SUMIFS('Order Details'!$Q:$Q,'Order Details'!$E:$E,"Yes",'Order Details'!$I:$I,'Item Summary'!$B5,'Order Details'!$F:$F,'Item Summary'!D$4,'Order Details'!$C:$C,"In Production") -> 0 | E5: =SUMIFS('Order Details'!$Q:$Q,'Order Details'!$E:$E,"Yes",'Order Details'!$I:$I,'Item Summary'!$B5,'Order Details'!$F:$F,'Item Summary'!E$4,'Order Details'!$C:$C,"PO Received")+SUMIFS('Order Details'!$Q:$Q,'Order Details'!$E:$E,"Yes",'Order Details'!$I:$I,'Item Summary'!$B5,'Order Details'!$F:$F,'Item Summary'!E$4,'Order Details'!$C:$C,"Proforma Invoice Sent")+SUMIFS('Order Details'!$Q:$Q,'Order Details'!$E:$E,"Yes",'Order Details'!$I:$I,'Item Summary'!$B5,'Order Details'!$F:$F,'Item Summary'!E$4,'Order Details'!$C:$C,"Downpayment Received")+SUMIFS('Order Details'!$Q:$Q,'Order Details'!$E:$E,"Yes",'Order Details'!$I:$I,'Item Summary'!$B5,'Order Details'!$F:$F,'Item Summary'!E$4,'Order Details'!$C:$C,"In Production") -> 0 | F5: =SUMIFS('Order Details'!$Q:$Q,'Order Details'!$E:$E,"Yes",'Order Details'!$I:$I,'Item Summary'!$B5,'Order Details'!$F:$F,'Item Summary'!F$4,'Order Details'!$C:$C,"PO Received")+SUMIFS('Order Details'!$Q:$Q,'Order Details'!$E:$E,"Yes",'Order Details'!$I:$I,'Item Summary'!$B5,'Order Details'!$F:$F,'Item Summary'!F$4,'Order Details'!$C:$C,"Proforma Invoice Sent")+SUMIFS('Order Details'!$Q:$Q,'Order Details'!$E:$E,"Yes",'Order Details'!$I:$I,'Item Summary'!$B5,'Order Details'!$F:$F,'Item Summary'!F$4,'Order Details'!$C:$C,"Downpayment Received")+SUMIFS('Order Details'!$Q:$Q,'Order Details'!$E:$E,"Yes",'Order Details'!$I:$I,'Item Summary'!$B5,'Order Details'!$F:$F,'Item Summary'!F$4,'Order Details'!$C:$C,"In Production") -> 0 | G5: =SUMIFS('Order Details'!$Q:$Q,'Order Details'!$E:$E,"Yes",'Order Details'!$I:$I,'Item Summary'!$B5,'Order Details'!$F:$F,'Item Summary'!G$4,'Order Details'!$C:$C,"PO Received")+SUMIFS('Order Details'!$Q:$Q,'Order Details'!$E:$E,"Yes",'Order Details'!$I:$I,'Item Summary'!$B5,'Order Details'!$F:$F,'Item Summary'!G$4,'Order Details'!$C:$C,"Proforma Invoice Sent")+SUMIFS('Order Details'!$Q:$Q,'Order Details'!$E:$E,"Yes",'Order Details'!$I:$I,'Item Summary'!$B5,'Order Details'!$F:$F,'Item Summary'!G$4,'Order Details'!$C:$C,"Downpayment Received")+SUMIFS('Order Details'!$Q:$Q,'Order Details'!$E:$E,"Yes",'Order Details'!$I:$I,'Item Summary'!$B5,'Order Details'!$F:$F,'Item Summary'!G$4,'Order Details'!$C:$C,"In Production") -> 0 | H5: =SUMIFS('Order Details'!$Q:$Q,'Order Details'!$E:$E,"Yes",'Order Details'!$I:$I,'Item Summary'!$B5,'Order Details'!$F:$F,'Item Summary'!H$4,'Order Details'!$C:$C,"PO Received")+SUMIFS('Order Details'!$Q:$Q,'Order Details'!$E:$E,"Yes",'Order Details'!$I:$I,'Item Summary'!$B5,'Order Details'!$F:$F,'Item Summary'!H$4,'Order Details'!$C:$C,"Proforma Invoice Sent")+SUMIFS('Order Details'!$Q:$Q,'Order Details'!$E:$E,"Yes",'Order Details'!$I:$I,'Item Summary'!$B5,'Order Details'!$F:$F,'Item Summary'!H$4,'Order Details'!$C:$C,"Downpayment Received")+SUMIFS('Order Details'!$Q:$Q,'Order Details'!$E:$E,"Yes",'Order Details'!$I:$I,'Item Summary'!$B5,'Order Details'!$F:$F,'Item Summary'!H$4,'Order Details'!$C:$C,"In Production") -> 0 | I5: =SUMIFS('Order Details'!$Q:$Q,'Order Details'!$E:$E,"Yes",'Order Details'!$I:$I,'Item Summary'!$B5,'Order Details'!$F:$F,'Item Summary'!I$4,'Order Details'!$C:$C,"PO Received")+SUMIFS('Order Details'!$Q:$Q,'Order Details'!$E:$E,"Yes",'Order Details'!$I:$I,'Item Summary'!$B5,'Order Details'!$F:$F,'Item Summary'!I$4,'Order Details'!$C:$C,"Proforma Invoice Sent")+SUMIFS('Order Details'!$Q:$Q,'Order Details'!$E:$E,"Yes",'Order Details'!$I:$I,'Item Summary'!$B5,'Order Details'!$F:$F,'Item Summary'!I$4,'Order Details'!$C:$C,"Downpayment Received")+SUMIFS('Order Details'!$Q:$Q,'Order Details'!$E:$E,"Yes",'Order Details'!$I:$I,'Item Summary'!$B5,'Order Details'!$F:$F,'Item Summary'!I$4,'Order Details'!$C:$C,"In Production") -> 0 | J5: =SUMIFS('Order Details'!$Q:$Q,'Order Details'!$E:$E,"Yes",'Order Details'!$I:$I,'Item Summary'!$B5,'Order Details'!$F:$F,'Item Summary'!J$4,'Order Details'!$C:$C,"PO Received")+SUMIFS('Order Details'!$Q:$Q,'Order Details'!$E:$E,"Yes",'Order Details'!$I:$I,'Item Summary'!$B5,'Order Details'!$F:$F,'Item Summary'!J$4,'Order Details'!$C:$C,"Proforma Invoice Sent")+SUMIFS('Order Details'!$Q:$Q,'Order Details'!$E:$E,"Yes",'Order Details'!$I:$I,'Item Summary'!$B5,'Order Details'!$F:$F,'Item Summary'!J$4,'Order Details'!$C:$C,"Downpayment Received")+SUMIFS('Order Details'!$Q:$Q,'Order Details'!$E:$E,"Yes",'Order Details'!$I:$I,'Item Summary'!$B5,'Order Details'!$F:$F,'Item Summary'!J$4,'Order Details'!$C:$C,"In Production") -> 0 | K5: =SUMIFS('Order Details'!$Q:$Q,'Order Details'!$E:$E,"Yes",'Order Details'!$I:$I,'Item Summary'!$B5,'Order Details'!$F:$F,'Item Summary'!K$4,'Order Details'!$C:$C,"PO Received")+SUMIFS('Order Details'!$Q:$Q,'Order Details'!$E:$E,"Yes",'Order Details'!$I:$I,'Item Summary'!$B5,'Order Details'!$F:$F,'Item Summary'!K$4,'Order Details'!$C:$C,"Proforma Invoice Sent")+SUMIFS('Order Details'!$Q:$Q,'Order Details'!$E:$E,"Yes",'Order Details'!$I:$I,'Item Summary'!$B5,'Order Details'!$F:$F,'Item Summary'!K$4,'Order Details'!$C:$C,"Downpayment Received")+SUMIFS('Order Details'!$Q:$Q,'Order Details'!$E:$E,"Yes",'Order Details'!$I:$I,'Item Summary'!$B5,'Order Details'!$F:$F,'Item Summary'!K$4,'Order Details'!$C:$C,"In Production") -> 0 | ... M5: =SUMIFS('Order Details'!$Q:$Q,'Order Details'!$E:$E,"Yes",'Order Details'!$I:$I,'Item Summary'!$B5,'Order Details'!$F:$F,'Item Summary'!M$4,'Order Details'!$C:$C,"PO Received")+SUMIFS('Order Details'!$Q:$Q,'Order Details'!$E:$E,"Yes",'Order Details'!$I:$I,'Item Summary'!$B5,'Order Details'!$F:$F,'Item Summary'!M$4,'Order Details'!$C:$C,"Proforma Invoice Sent")+SUMIFS('Order Details'!$Q:$Q,'Order Details'!$E:$E,"Yes",'Order Details'!$I:$I,'Item Summary'!$B5,'Order Details'!$F:$F,'Item Summary'!M$4,'Order Details'!$C:$C,"Downpayment Received")+SUMIFS('Order Details'!$Q:$Q,'Order Details'!$E:$E,"Yes",'Order Details'!$I:$I,'Item Summary'!$B5,'Order Details'!$F:$F,'Item Summary'!M$4,'Order Details'!$C:$C,"In Production") -> 0 | N5: =SUM(D5:M5) -> 0 | Q5: 704984 | R5: =VLOOKUP($Q5,'Pricing Table - eff 27-Jan-2026'!$A:$L,9,FALSE)&""" "&VLOOKUP($Q5,'Pricing Table - eff 27-Jan-2026'!$A:$L,12,FALSE) -> 84" GLOSSY BLACK | S5: =SUMIFS('Order Details'!$Q:$Q,'Order Details'!$E:$E,"Yes",'Order Details'!$I:$I,$Q5,'Order Details'!$F:$F,'Item Summary'!S$4)-D5 -> 0 | T5: =SUMIFS('Order Details'!$Q:$Q,'Order Details'!$E:$E,"Yes",'Order Details'!$I:$I,$Q5,'Order Details'!$F:$F,'Item Summary'!T$4)-E5 -> 1200 | U5: =SUMIFS('Order Details'!$Q:$Q,'Order Details'!$E:$E,"Yes",'Order Details'!$I:$I,$Q5,'Order Details'!$F:$F,'Item Summary'!U$4)-F5 -> 0 | V5: =SUMIFS('Order Details'!$Q:$Q,'Order Details'!$E:$E,"Yes",'Order Details'!$I:$I,$Q5,'Order Details'!$F:$F,'Item Summary'!V$4)-G5 -> 0 | W5: =SUMIFS('Order Details'!$Q:$Q,'Order Details'!$E:$E,"Yes",'Order Details'!$I:$I,$Q5,'Order Details'!$F:$F,'Item Summary'!W$4)-H5 -> 0 | X5: =SUMIFS('Order Details'!$Q:$Q,'Order Details'!$E:$E,"Yes",'Order Details'!$I:$I,$Q5,'Order Details'!$F:$F,'Item Summary'!X$4)-I5 -> 0 | Y5: =SUMIFS('Order Details'!$Q:$Q,'Order Details'!$E:$E,"Yes",'Order Details'!$I:$I,$Q5,'Order Details'!$F:$F,'Item Summary'!Y$4)-J5 -> 0 | Z5: =SUMIFS('Order Details'!$Q:$Q,'Order Details'!$E:$E,"Yes",'Order Details'!$I:$I,$Q5,'Order Details'!$F:$F,'Item Summary'!Z$4)-K5 -> 0 | ... AB5: =SUMIFS('Order Details'!$Q:$Q,'Order Details'!$E:$E,"Yes",'Order Details'!$I:$I,$Q5,'Order Details'!$F:$F,'Item Summary'!AB$4)-M5 -> 0 | AC5: =SUM(S5:AB5) -> 1200
B6: 694431 | C6: =VLOOKUP($B6,'Pricing Table - eff 27-Jan-2026'!$A:$L,9,FALSE)&""" "&VLOOKUP($B6,'Pricing Table - eff 27-Jan-2026'!$A:$L,12,FALSE) -> 90" GLOSSY BLACK | D6: =SUMIFS('Order Details'!$Q:$Q,'Order Details'!$E:$E,"Yes",'Order Details'!$I:$I,'Item Summary'!$B6,'Order Details'!$F:$F,'Item Summary'!D$4,'Order Details'!$C:$C,"PO Received")+SUMIFS('Order Details'!$Q:$Q,'Order Details'!$E:$E,"Yes",'Order Details'!$I:$I,'Item Summary'!$B6,'Order Details'!$F:$F,'Item Summary'!D$4,'Order Details'!$C:$C,"Proforma Invoice Sent")+SUMIFS('Order Details'!$Q:$Q,'Order Details'!$E:$E,"Yes",'Order Details'!$I:$I,'Item Summary'!$B6,'Order Details'!$F:$F,'Item Summary'!D$4,'Order Details'!$C:$C,"Downpayment Received")+SUMIFS('Order Details'!$Q:$Q,'Order Details'!$E:$E,"Yes",'Order Details'!$I:$I,'Item Summary'!$B6,'Order Details'!$F:$F,'Item Summary'!D$4,'Order Details'!$C:$C,"In Production") -> 0 | E6: =SUMIFS('Order Details'!$Q:$Q,'Order Details'!$E:$E,"Yes",'Order Details'!$I:$I,'Item Summary'!$B6,'Order Details'!$F:$F,'Item Summary'!E$4,'Order Details'!$C:$C,"PO Received")+SUMIFS('Order Details'!$Q:$Q,'Order Details'!$E:$E,"Yes",'Order Details'!$I:$I,'Item Summary'!$B6,'Order Details'!$F:$F,'Item Summary'!E$4,'Order Details'!$C:$C,"Proforma Invoice Sent")+SUMIFS('Order Details'!$Q:$Q,'Order Details'!$E:$E,"Yes",'Order Details'!$I:$I,'Item Summary'!$B6,'Order Details'!$F:$F,'Item Summary'!E$4,'Order Details'!$C:$C,"Downpayment Received")+SUMIFS('Order Details'!$Q:$Q,'Order Details'!$E:$E,"Yes",'Order Details'!$I:$I,'Item Summary'!$B6,'Order Details'!$F:$F,'Item Summary'!E$4,'Order Details'!$C:$C,"In Production") -> 0 | F6: =SUMIFS('Order Details'!$Q:$Q,'Order Details'!$E:$E,"Yes",'Order Details'!$I:$I,'Item Summary'!$B6,'Order Details'!$F:$F,'Item Summary'!F$4,'Order Details'!$C:$C,"PO Received")+SUMIFS('Order Details'!$Q:$Q,'Order Details'!$E:$E,"Yes",'Order Details'!$I:$I,'Item Summary'!$B6,'Order Details'!$F:$F,'Item Summary'!F$4,'Order Details'!$C:$C,"Proforma Invoice Sent")+SUMIFS('Order Details'!$Q:$Q,'Order Details'!$E:$E,"Yes",'Order Details'!$I:$I,'Item Summary'!$B6,'Order Details'!$F:$F,'Item Summary'!F$4,'Order Details'!$C:$C,"Downpayment Received")+SUMIFS('Order Details'!$Q:$Q,'Order Details'!$E:$E,"Yes",'Order Details'!$I:$I,'Item Summary'!$B6,'Order Details'!$F:$F,'Item Summary'!F$4,'Order Details'!$C:$C,"In Production") -> 0 | G6: =SUMIFS('Order Details'!$Q:$Q,'Order Details'!$E:$E,"Yes",'Order Details'!$I:$I,'Item Summary'!$B6,'Order Details'!$F:$F,'Item Summary'!G$4,'Order Details'!$C:$C,"PO Received")+SUMIFS('Order Details'!$Q:$Q,'Order Details'!$E:$E,"Yes",'Order Details'!$I:$I,'Item Summary'!$B6,'Order Details'!$F:$F,'Item Summary'!G$4,'Order Details'!$C:$C,"Proforma Invoice Sent")+SUMIFS('Order Details'!$Q:$Q,'Order Details'!$E:$E,"Yes",'Order Details'!$I:$I,'Item Summary'!$B6,'Order Details'!$F:$F,'Item Summary'!G$4,'Order Details'!$C:$C,"Downpayment Received")+SUMIFS('Order Details'!$Q:$Q,'Order Details'!$E:$E,"Yes",'Order Details'!$I:$I,'Item Summary'!$B6,'Order Details'!$F:$F,'Item Summary'!G$4,'Order Details'!$C:$C,"In Production") -> 0 | H6: =SUMIFS('Order Details'!$Q:$Q,'Order Details'!$E:$E,"Yes",'Order Details'!$I:$I,'Item Summary'!$B6,'Order Details'!$F:$F,'Item Summary'!H$4,'Order Details'!$C:$C,"PO Received")+SUMIFS('Order Details'!$Q:$Q,'Order Details'!$E:$E,"Yes",'Order Details'!$I:$I,'Item Summary'!$B6,'Order Details'!$F:$F,'Item Summary'!H$4,'Order Details'!$C:$C,"Proforma Invoice Sent")+SUMIFS('Order Details'!$Q:$Q,'Order Details'!$E:$E,"Yes",'Order Details'!$I:$I,'Item Summary'!$B6,'Order Details'!$F:$F,'Item Summary'!H$4,'Order Details'!$C:$C,"Downpayment Received")+SUMIFS('Order Details'!$Q:$Q,'Order Details'!$E:$E,"Yes",'Order Details'!$I:$I,'Item Summary'!$B6,'Order Details'!$F:$F,'Item Summary'!H$4,'Order Details'!$C:$C,"In Production") -> 0 | I6: =SUMIFS('Order Details'!$Q:$Q,'Order Details'!$E:$E,"Yes",'Order Details'!$I:$I,'Item Summary'!$B6,'Order Details'!$F:$F,'Item Summary'!I$4,'Order Details'!$C:$C,"PO Received")+SUMIFS('Order Details'!$Q:$Q,'Order Details'!$E:$E,"Yes",'Order Details'!$I:$I,'Item Summary'!$B6,'Order Details'!$F:$F,'Item Summary'!I$4,'Order Details'!$C:$C,"Proforma Invoice Sent")+SUMIFS('Order Details'!$Q:$Q,'Order Details'!$E:$E,"Yes",'Order Details'!$I:$I,'Item Summary'!$B6,'Order Details'!$F:$F,'Item Summary'!I$4,'Order Details'!$C:$C,"Downpayment Received")+SUMIFS('Order Details'!$Q:$Q,'Order Details'!$E:$E,"Yes",'Order Details'!$I:$I,'Item Summary'!$B6,'Order Details'!$F:$F,'Item Summary'!I$4,'Order Details'!$C:$C,"In Production") -> 0 | J6: =SUMIFS('Order Details'!$Q:$Q,'Order Details'!$E:$E,"Yes",'Order Details'!$I:$I,'Item Summary'!$B6,'Order Details'!$F:$F,'Item Summary'!J$4,'Order Details'!$C:$C,"PO Received")+SUMIFS('Order Details'!$Q:$Q,'Order Details'!$E:$E,"Yes",'Order Details'!$I:$I,'Item Summary'!$B6,'Order Details'!$F:$F,'Item Summary'!J$4,'Order Details'!$C:$C,"Proforma Invoice Sent")+SUMIFS('Order Details'!$Q:$Q,'Order Details'!$E:$E,"Yes",'Order Details'!$I:$I,'Item Summary'!$B6,'Order Details'!$F:$F,'Item Summary'!J$4,'Order Details'!$C:$C,"Downpayment Received")+SUMIFS('Order Details'!$Q:$Q,'Order Details'!$E:$E,"Yes",'Order Details'!$I:$I,'Item Summary'!$B6,'Order Details'!$F:$F,'Item Summary'!J$4,'Order Details'!$C:$C,"In Production") -> 0 | K6: =SUMIFS('Order Details'!$Q:$Q,'Order Details'!$E:$E,"Yes",'Order Details'!$I:$I,'Item Summary'!$B6,'Order Details'!$F:$F,'Item Summary'!K$4,'Order Details'!$C:$C,"PO Received")+SUMIFS('Order Details'!$Q:$Q,'Order Details'!$E:$E,"Yes",'Order Details'!$I:$I,'Item Summary'!$B6,'Order Details'!$F:$F,'Item Summary'!K$4,'Order Details'!$C:$C,"Proforma Invoice Sent")+SUMIFS('Order Details'!$Q:$Q,'Order Details'!$E:$E,"Yes",'Order Details'!$I:$I,'Item Summary'!$B6,'Order Details'!$F:$F,'Item Summary'!K$4,'Order Details'!$C:$C,"Downpayment Received")+SUMIFS('Order Details'!$Q:$Q,'Order Details'!$E:$E,"Yes",'Order Details'!$I:$I,'Item Summary'!$B6,'Order Details'!$F:$F,'Item Summary'!K$4,'Order Details'!$C:$C,"In Production") -> 0 | ... M6: =SUMIFS('Order Details'!$Q:$Q,'Order Details'!$E:$E,"Yes",'Order Details'!$I:$I,'Item Summary'!$B6,'Order Details'!$F:$F,'Item Summary'!M$4,'Order Details'!$C:$C,"PO Received")+SUMIFS('Order Details'!$Q:$Q,'Order Details'!$E:$E,"Yes",'Order Details'!$I:$I,'Item Summary'!$B6,'Order Details'!$F:$F,'Item Summary'!M$4,'Order Details'!$C:$C,"Proforma Invoice Sent")+SUMIFS('Order Details'!$Q:$Q,'Order Details'!$E:$E,"Yes",'Order Details'!$I:$I,'Item Summary'!$B6,'Order Details'!$F:$F,'Item Summary'!M$4,'Order Details'!$C:$C,"Downpayment Received")+SUMIFS('Order Details'!$Q:$Q,'Order Details'!$E:$E,"Yes",'Order Details'!$I:$I,'Item Summary'!$B6,'Order Details'!$F:$F,'Item Summary'!M$4,'Order Details'!$C:$C,"In Production") -> 0 | N6: =SUM(D6:M6) -> 0 | Q6: 694431 | R6: =VLOOKUP($Q6,'Pricing Table - eff 27-Jan-2026'!$A:$L,9,FALSE)&""" "&VLOOKUP($Q6,'Pricing Table - eff 27-Jan-2026'!$A:$L,12,FALSE) -> 90" GLOSSY BLACK | S6: =SUMIFS('Order Details'!$Q:$Q,'Order Details'!$E:$E,"Yes",'Order Details'!$I:$I,$Q6,'Order Details'!$F:$F,'Item Summary'!S$4)-D6 -> 0 | T6: =SUMIFS('Order Details'!$Q:$Q,'Order Details'!$E:$E,"Yes",'Order Details'!$I:$I,$Q6,'Order Details'!$F:$F,'Item Summary'!T$4)-E6 -> 0 | U6: =SUMIFS('Order Details'!$Q:$Q,'Order Details'!$E:$E,"Yes",'Order Details'!$I:$I,$Q6,'Order Details'!$F:$F,'Item Summary'!U$4)-F6 -> 0 | V6: =SUMIFS('Order Details'!$Q:$Q,'Order Details'!$E:$E,"Yes",'Order Details'!$I:$I,$Q6,'Order Details'!$F:$F,'Item Summary'!V$4)-G6 -> 400 | W6: =SUMIFS('Order Details'!$Q:$Q,'Order Details'!$E:$E,"Yes",'Order Details'!$I:$I,$Q6,'Order Details'!$F:$F,'Item Summary'!W$4)-H6 -> 0 | X6: =SUMIFS('Order Details'!$Q:$Q,'Order Details'!$E:$E,"Yes",'Order Details'!$I:$I,$Q6,'Order Details'!$F:$F,'Item Summary'!X$4)-I6 -> 0 | Y6: =SUMIFS('Order Details'!$Q:$Q,'Order Details'!$E:$E,"Yes",'Order Details'!$I:$I,$Q6,'Order Details'!$F:$F,'Item Summary'!Y$4)-J6 -> 0 | Z6: =SUMIFS('Order Details'!$Q:$Q,'Order Details'!$E:$E,"Yes",'Order Details'!$I:$I,$Q6,'Order Details'!$F:$F,'Item Summary'!Z$4)-K6 -> 0 | ... AB6: =SUMIFS('Order Details'!$Q:$Q,'Order Details'!$E:$E,"Yes",'Order Details'!$I:$I,$Q6,'Order Details'!$F:$F,'Item Summary'!AB$4)-M6 -> 0 | AC6: =SUM(S6:AB6) -> 400
B7: 709354 | C7: =VLOOKUP($B7,'Pricing Table - eff 27-Jan-2026'!$A:$L,9,FALSE)&""" "&VLOOKUP($B7,'Pricing Table - eff 27-Jan-2026'!$A:$L,12,FALSE) -> 90.5" GLOSSY BLACK | D7: =SUMIFS('Order Details'!$Q:$Q,'Order Details'!$E:$E,"Yes",'Order Details'!$I:$I,'Item Summary'!$B7,'Order Details'!$F:$F,'Item Summary'!D$4,'Order Details'!$C:$C,"PO Received")+SUMIFS('Order Details'!$Q:$Q,'Order Details'!$E:$E,"Yes",'Order Details'!$I:$I,'Item Summary'!$B7,'Order Details'!$F:$F,'Item Summary'!D$4,'Order Details'!$C:$C,"Proforma Invoice Sent")+SUMIFS('Order Details'!$Q:$Q,'Order Details'!$E:$E,"Yes",'Order Details'!$I:$I,'Item Summary'!$B7,'Order Details'!$F:$F,'Item Summary'!D$4,'Order Details'!$C:$C,"Downpayment Received")+SUMIFS('Order Details'!$Q:$Q,'Order Details'!$E:$E,"Yes",'Order Details'!$I:$I,'Item Summary'!$B7,'Order Details'!$F:$F,'Item Summary'!D$4,'Order Details'!$C:$C,"In Production") -> 0 | E7: =SUMIFS('Order Details'!$Q:$Q,'Order Details'!$E:$E,"Yes",'Order Details'!$I:$I,'Item Summary'!$B7,'Order Details'!$F:$F,'Item Summary'!E$4,'Order Details'!$C:$C,"PO Received")+SUMIFS('Order Details'!$Q:$Q,'Order Details'!$E:$E,"Yes",'Order Details'!$I:$I,'Item Summary'!$B7,'Order Details'!$F:$F,'Item Summary'!E$4,'Order Details'!$C:$C,"Proforma Invoice Sent")+SUMIFS('Order Details'!$Q:$Q,'Order Details'!$E:$E,"Yes",'Order Details'!$I:$I,'Item Summary'!$B7,'Order Details'!$F:$F,'Item Summary'!E$4,'Order Details'!$C:$C,"Downpayment Received")+SUMIFS('Order Details'!$Q:$Q,'Order Details'!$E:$E,"Yes",'Order Details'!$I:$I,'Item Summary'!$B7,'Order Details'!$F:$F,'Item Summary'!E$4,'Order Details'!$C:$C,"In Production") -> 1000 | F7: =SUMIFS('Order Details'!$Q:$Q,'Order Details'!$E:$E,"Yes",'Order Details'!$I:$I,'Item Summary'!$B7,'Order Details'!$F:$F,'Item Summary'!F$4,'Order Details'!$C:$C,"PO Received")+SUMIFS('Order Details'!$Q:$Q,'Order Details'!$E:$E,"Yes",'Order Details'!$I:$I,'Item Summary'!$B7,'Order Details'!$F:$F,'Item Summary'!F$4,'Order Details'!$C:$C,"Proforma Invoice Sent")+SUMIFS('Order Details'!$Q:$Q,'Order Details'!$E:$E,"Yes",'Order Details'!$I:$I,'Item Summary'!$B7,'Order Details'!$F:$F,'Item Summary'!F$4,'Order Details'!$C:$C,"Downpayment Received")+SUMIFS('Order Details'!$Q:$Q,'Order Details'!$E:$E,"Yes",'Order Details'!$I:$I,'Item Summary'!$B7,'Order Details'!$F:$F,'Item Summary'!F$4,'Order Details'!$C:$C,"In Production") -> 1400 | G7: =SUMIFS('Order Details'!$Q:$Q,'Order Details'!$E:$E,"Yes",'Order Details'!$I:$I,'Item Summary'!$B7,'Order Details'!$F:$F,'Item Summary'!G$4,'Order Details'!$C:$C,"PO Received")+SUMIFS('Order Details'!$Q:$Q,'Order Details'!$E:$E,"Yes",'Order Details'!$I:$I,'Item Summary'!$B7,'Order Details'!$F:$F,'Item Summary'!G$4,'Order Details'!$C:$C,"Proforma Invoice Sent")+SUMIFS('Order Details'!$Q:$Q,'Order Details'!$E:$E,"Yes",'Order Details'!$I:$I,'Item Summary'!$B7,'Order Details'!$F:$F,'Item Summary'!G$4,'Order Details'!$C:$C,"Downpayment Received")+SUMIFS('Order Details'!$Q:$Q,'Order Details'!$E:$E,"Yes",'Order Details'!$I:$I,'Item Summary'!$B7,'Order Details'!$F:$F,'Item Summary'!G$4,'Order Details'!$C:$C,"In Production") -> 1200 | H7: =SUMIFS('Order Details'!$Q:$Q,'Order Details'!$E:$E,"Yes",'Order Details'!$I:$I,'Item Summary'!$B7,'Order Details'!$F:$F,'Item Summary'!H$4,'Order Details'!$C:$C,"PO Received")+SUMIFS('Order Details'!$Q:$Q,'Order Details'!$E:$E,"Yes",'Order Details'!$I:$I,'Item Summary'!$B7,'Order Details'!$F:$F,'Item Summary'!H$4,'Order Details'!$C:$C,"Proforma Invoice Sent")+SUMIFS('Order Details'!$Q:$Q,'Order Details'!$E:$E,"Yes",'Order Details'!$I:$I,'Item Summary'!$B7,'Order Details'!$F:$F,'Item Summary'!H$4,'Order Details'!$C:$C,"Downpayment Received")+SUMIFS('Order Details'!$Q:$Q,'Order Details'!$E:$E,"Yes",'Order Details'!$I:$I,'Item Summary'!$B7,'Order Details'!$F:$F,'Item Summary'!H$4,'Order Details'!$C:$C,"In Production") -> 0 | I7: =SUMIFS('Order Details'!$Q:$Q,'Order Details'!$E:$E,"Yes",'Order Details'!$I:$I,'Item Summary'!$B7,'Order Details'!$F:$F,'Item Summary'!I$4,'Order Details'!$C:$C,"PO Received")+SUMIFS('Order Details'!$Q:$Q,'Order Details'!$E:$E,"Yes",'Order Details'!$I:$I,'Item Summary'!$B7,'Order Details'!$F:$F,'Item Summary'!I$4,'Order Details'!$C:$C,"Proforma Invoice Sent")+SUMIFS('Order Details'!$Q:$Q,'Order Details'!$E:$E,"Yes",'Order Details'!$I:$I,'Item Summary'!$B7,'Order Details'!$F:$F,'Item Summary'!I$4,'Order Details'!$C:$C,"Downpayment Received")+SUMIFS('Order Details'!$Q:$Q,'Order Details'!$E:$E,"Yes",'Order Details'!$I:$I,'Item Summary'!$B7,'Order Details'!$F:$F,'Item Summary'!I$4,'Order Details'!$C:$C,"In Production") -> 800 | J7: =SUMIFS('Order Details'!$Q:$Q,'Order Details'!$E:$E,"Yes",'Order Details'!$I:$I,'Item Summary'!$B7,'Order Details'!$F:$F,'Item Summary'!J$4,'Order Details'!$C:$C,"PO Received")+SUMIFS('Order Details'!$Q:$Q,'Order Details'!$E:$E,"Yes",'Order Details'!$I:$I,'Item Summary'!$B7,'Order Details'!$F:$F,'Item Summary'!J$4,'Order Details'!$C:$C,"Proforma Invoice Sent")+SUMIFS('Order Details'!$Q:$Q,'Order Details'!$E:$E,"Yes",'Order Details'!$I:$I,'Item Summary'!$B7,'Order Details'!$F:$F,'Item Summary'!J$4,'Order Details'!$C:$C,"Downpayment Received")+SUMIFS('Order Details'!$Q:$Q,'Order Details'!$E:$E,"Yes",'Order Details'!$I:$I,'Item Summary'!$B7,'Order Details'!$F:$F,'Item Summary'!J$4,'Order Details'!$C:$C,"In Production") -> 0 | K7: =SUMIFS('Order Details'!$Q:$Q,'Order Details'!$E:$E,"Yes",'Order Details'!$I:$I,'Item Summary'!$B7,'Order Details'!$F:$F,'Item Summary'!K$4,'Order Details'!$C:$C,"PO Received")+SUMIFS('Order Details'!$Q:$Q,'Order Details'!$E:$E,"Yes",'Order Details'!$I:$I,'Item Summary'!$B7,'Order Details'!$F:$F,'Item Summary'!K$4,'Order Details'!$C:$C,"Proforma Invoice Sent")+SUMIFS('Order Details'!$Q:$Q,'Order Details'!$E:$E,"Yes",'Order Details'!$I:$I,'Item Summary'!$B7,'Order Details'!$F:$F,'Item Summary'!K$4,'Order Details'!$C:$C,"Downpayment Received")+SUMIFS('Order Details'!$Q:$Q,'Order Details'!$E:$E,"Yes",'Order Details'!$I:$I,'Item Summary'!$B7,'Order Details'!$F:$F,'Item Summary'!K$4,'Order Details'!$C:$C,"In Production") -> 0 | ... M7: =SUMIFS('Order Details'!$Q:$Q,'Order Details'!$E:$E,"Yes",'Order Details'!$I:$I,'Item Summary'!$B7,'Order Details'!$F:$F,'Item Summary'!M$4,'Order Details'!$C:$C,"PO Received")+SUMIFS('Order Details'!$Q:$Q,'Order Details'!$E:$E,"Yes",'Order Details'!$I:$I,'Item Summary'!$B7,'Order Details'!$F:$F,'Item Summary'!M$4,'Order Details'!$C:$C,"Proforma Invoice Sent")+SUMIFS('Order Details'!$Q:$Q,'Order Details'!$E:$E,"Yes",'Order Details'!$I:$I,'Item Summary'!$B7,'Order Details'!$F:$F,'Item Summary'!M$4,'Order Details'!$C:$C,"Downpayment Received")+SUMIFS('Order Details'!$Q:$Q,'Order Details'!$E:$E,"Yes",'Order Details'!$I:$I,'Item Summary'!$B7,'Order Details'!$F:$F,'Item Summary'!M$4,'Order Details'!$C:$C,"In Production") -> 0 | N7: =SUM(D7:M7) -> 5200 | Q7: 709354 | R7: =VLOOKUP($Q7,'Pricing Table - eff 27-Jan-2026'!$A:$L,9,FALSE)&""" "&VLOOKUP($Q7,'Pricing Table - eff 27-Jan-2026'!$A:$L,12,FALSE) -> 90.5" GLOSSY BLACK | S7: =SUMIFS('Order Details'!$Q:$Q,'Order Details'!$E:$E,"Yes",'Order Details'!$I:$I,$Q7,'Order Details'!$F:$F,'Item Summary'!S$4)-D7 -> 0 | T7: =SUMIFS('Order Details'!$Q:$Q,'Order Details'!$E:$E,"Yes",'Order Details'!$I:$I,$Q7,'Order Details'!$F:$F,'Item Summary'!T$4)-E7 -> 2400 | U7: =SUMIFS('Order Details'!$Q:$Q,'Order Details'!$E:$E,"Yes",'Order Details'!$I:$I,$Q7,'Order Details'!$F:$F,'Item Summary'!U$4)-F7 -> 1800 | V7: =SUMIFS('Order Details'!$Q:$Q,'Order Details'!$E:$E,"Yes",'Order Details'!$I:$I,$Q7,'Order Details'!$F:$F,'Item Summary'!V$4)-G7 -> 1400 | W7: =SUMIFS('Order Details'!$Q:$Q,'Order Details'!$E:$E,"Yes",'Order Details'!$I:$I,$Q7,'Order Details'!$F:$F,'Item Summary'!W$4)-H7 -> 1600 | X7: =SUMIFS('Order Details'!$Q:$Q,'Order Details'!$E:$E,"Yes",'Order Details'!$I:$I,$Q7,'Order Details'!$F:$F,'Item Summary'!X$4)-I7 -> 0 | Y7: =SUMIFS('Order Details'!$Q:$Q,'Order Details'!$E:$E,"Yes",'Order Details'!$I:$I,$Q7,'Order Details'!$F:$F,'Item Summary'!Y$4)-J7 -> 0 | Z7: =SUMIFS('Order Details'!$Q:$Q,'Order Details'!$E:$E,"Yes",'Order Details'!$I:$I,$Q7,'Order Details'!$F:$F,'Item Summary'!Z$4)-K7 -> 0 | ... AB7: =SUMIFS('Order Details'!$Q:$Q,'Order Details'!$E:$E,"Yes",'Order Details'!$I:$I,$Q7,'Order Details'!$F:$F,'Item Summary'!AB$4)-M7 -> 0 | AC7: =SUM(S7:AB7) -> 7200
B8: 694432 | C8: =VLOOKUP($B8,'Pricing Table - eff 27-Jan-2026'!$A:$L,9,FALSE)&""" "&VLOOKUP($B8,'Pricing Table - eff 27-Jan-2026'!$A:$L,12,FALSE) -> 96" GLOSSY BLACK | D8: =SUMIFS('Order Details'!$Q:$Q,'Order Details'!$E:$E,"Yes",'Order Details'!$I:$I,'Item Summary'!$B8,'Order Details'!$F:$F,'Item Summary'!D$4,'Order Details'!$C:$C,"PO Received")+SUMIFS('Order Details'!$Q:$Q,'Order Details'!$E:$E,"Yes",'Order Details'!$I:$I,'Item Summary'!$B8,'Order Details'!$F:$F,'Item Summary'!D$4,'Order Details'!$C:$C,"Proforma Invoice Sent")+SUMIFS('Order Details'!$Q:$Q,'Order Details'!$E:$E,"Yes",'Order Details'!$I:$I,'Item Summary'!$B8,'Order Details'!$F:$F,'Item Summary'!D$4,'Order Details'!$C:$C,"Downpayment Received")+SUMIFS('Order Details'!$Q:$Q,'Order Details'!$E:$E,"Yes",'Order Details'!$I:$I,'Item Summary'!$B8,'Order Details'!$F:$F,'Item Summary'!D$4,'Order Details'!$C:$C,"In Production") -> 1400 | E8: =SUMIFS('Order Details'!$Q:$Q,'Order Details'!$E:$E,"Yes",'Order Details'!$I:$I,'Item Summary'!$B8,'Order Details'!$F:$F,'Item Summary'!E$4,'Order Details'!$C:$C,"PO Received")+SUMIFS('Order Details'!$Q:$Q,'Order Details'!$E:$E,"Yes",'Order Details'!$I:$I,'Item Summary'!$B8,'Order Details'!$F:$F,'Item Summary'!E$4,'Order Details'!$C:$C,"Proforma Invoice Sent")+SUMIFS('Order Details'!$Q:$Q,'Order Details'!$E:$E,"Yes",'Order Details'!$I:$I,'Item Summary'!$B8,'Order Details'!$F:$F,'Item Summary'!E$4,'Order Details'!$C:$C,"Downpayment Received")+SUMIFS('Order Details'!$Q:$Q,'Order Details'!$E:$E,"Yes",'Order Details'!$I:$I,'Item Summary'!$B8,'Order Details'!$F:$F,'Item Summary'!E$4,'Order Details'!$C:$C,"In Production") -> 1000 | F8: =SUMIFS('Order Details'!$Q:$Q,'Order Details'!$E:$E,"Yes",'Order Details'!$I:$I,'Item Summary'!$B8,'Order Details'!$F:$F,'Item Summary'!F$4,'Order Details'!$C:$C,"PO Received")+SUMIFS('Order Details'!$Q:$Q,'Order Details'!$E:$E,"Yes",'Order Details'!$I:$I,'Item Summary'!$B8,'Order Details'!$F:$F,'Item Summary'!F$4,'Order Details'!$C:$C,"Proforma Invoice Sent")+SUMIFS('Order Details'!$Q:$Q,'Order Details'!$E:$E,"Yes",'Order Details'!$I:$I,'Item Summary'!$B8,'Order Details'!$F:$F,'Item Summary'!F$4,'Order Details'!$C:$C,"Downpayment Received")+SUMIFS('Order Details'!$Q:$Q,'Order Details'!$E:$E,"Yes",'Order Details'!$I:$I,'Item Summary'!$B8,'Order Details'!$F:$F,'Item Summary'!F$4,'Order Details'!$C:$C,"In Production") -> 1400 | G8: =SUMIFS('Order Details'!$Q:$Q,'Order Details'!$E:$E,"Yes",'Order Details'!$I:$I,'Item Summary'!$B8,'Order Details'!$F:$F,'Item Summary'!G$4,'Order Details'!$C:$C,"PO Received")+SUMIFS('Order Details'!$Q:$Q,'Order Details'!$E:$E,"Yes",'Order Details'!$I:$I,'Item Summary'!$B8,'Order Details'!$F:$F,'Item Summary'!G$4,'Order Details'!$C:$C,"Proforma Invoice Sent")+SUMIFS('Order Details'!$Q:$Q,'Order Details'!$E:$E,"Yes",'Order Details'!$I:$I,'Item Summary'!$B8,'Order Details'!$F:$F,'Item Summary'!G$4,'Order Details'!$C:$C,"Downpayment Received")+SUMIFS('Order Details'!$Q:$Q,'Order Details'!$E:$E,"Yes",'Order Details'!$I:$I,'Item Summary'!$B8,'Order Details'!$F:$F,'Item Summary'!G$4,'Order Details'!$C:$C,"In Production") -> 2800 | H8: =SUMIFS('Order Details'!$Q:$Q,'Order Details'!$E:$E,"Yes",'Order Details'!$I:$I,'Item Summary'!$B8,'Order Details'!$F:$F,'Item Summary'!H$4,'Order Details'!$C:$C,"PO Received")+SUMIFS('Order Details'!$Q:$Q,'Order Details'!$E:$E,"Yes",'Order Details'!$I:$I,'Item Summary'!$B8,'Order Details'!$F:$F,'Item Summary'!H$4,'Order Details'!$C:$C,"Proforma Invoice Sent")+SUMIFS('Order Details'!$Q:$Q,'Order Details'!$E:$E,"Yes",'Order Details'!$I:$I,'Item Summary'!$B8,'Order Details'!$F:$F,'Item Summary'!H$4,'Order Details'!$C:$C,"Downpayment Received")+SUMIFS('Order Details'!$Q:$Q,'Order Details'!$E:$E,"Yes",'Order Details'!$I:$I,'Item Summary'!$B8,'Order Details'!$F:$F,'Item Summary'!H$4,'Order Details'!$C:$C,"In Production") -> 1400 | I8: =SUMIFS('Order Details'!$Q:$Q,'Order Details'!$E:$E,"Yes",'Order Details'!$I:$I,'Item Summary'!$B8,'Order Details'!$F:$F,'Item Summary'!I$4,'Order Details'!$C:$C,"PO Received")+SUMIFS('Order Details'!$Q:$Q,'Order Details'!$E:$E,"Yes",'Order Details'!$I:$I,'Item Summary'!$B8,'Order Details'!$F:$F,'Item Summary'!I$4,'Order Details'!$C:$C,"Proforma Invoice Sent")+SUMIFS('Order Details'!$Q:$Q,'Order Details'!$E:$E,"Yes",'Order Details'!$I:$I,'Item Summary'!$B8,'Order Details'!$F:$F,'Item Summary'!I$4,'Order Details'!$C:$C,"Downpayment Received")+SUMIFS('Order Details'!$Q:$Q,'Order Details'!$E:$E,"Yes",'Order Details'!$I:$I,'Item Summary'!$B8,'Order Details'!$F:$F,'Item Summary'!I$4,'Order Details'!$C:$C,"In Production") -> 7000 | J8: =SUMIFS('Order Details'!$Q:$Q,'Order Details'!$E:$E,"Yes",'Order Details'!$I:$I,'Item Summary'!$B8,'Order Details'!$F:$F,'Item Summary'!J$4,'Order Details'!$C:$C,"PO Received")+SUMIFS('Order Details'!$Q:$Q,'Order Details'!$E:$E,"Yes",'Order Details'!$I:$I,'Item Summary'!$B8,'Order Details'!$F:$F,'Item Summary'!J$4,'Order Details'!$C:$C,"Proforma Invoice Sent")+SUMIFS('Order Details'!$Q:$Q,'Order Details'!$E:$E,"Yes",'Order Details'!$I:$I,'Item Summary'!$B8,'Order Details'!$F:$F,'Item Summary'!J$4,'Order Details'!$C:$C,"Downpayment Received")+SUMIFS('Order Details'!$Q:$Q,'Order Details'!$E:$E,"Yes",'Order Details'!$I:$I,'Item Summary'!$B8,'Order Details'!$F:$F,'Item Summary'!J$4,'Order Details'!$C:$C,"In Production") -> 400 | K8: =SUMIFS('Order Details'!$Q:$Q,'Order Details'!$E:$E,"Yes",'Order Details'!$I:$I,'Item Summary'!$B8,'Order Details'!$F:$F,'Item Summary'!K$4,'Order Details'!$C:$C,"PO Received")+SUMIFS('Order Details'!$Q:$Q,'Order Details'!$E:$E,"Yes",'Order Details'!$I:$I,'Item Summary'!$B8,'Order Details'!$F:$F,'Item Summary'!K$4,'Order Details'!$C:$C,"Proforma Invoice Sent")+SUMIFS('Order Details'!$Q:$Q,'Order Details'!$E:$E,"Yes",'Order Details'!$I:$I,'Item Summary'!$B8,'Order Details'!$F:$F,'Item Summary'!K$4,'Order Details'!$C:$C,"Downpayment Received")+SUMIFS('Order Details'!$Q:$Q,'Order Details'!$E:$E,"Yes",'Order Details'!$I:$I,'Item Summary'!$B8,'Order Details'!$F:$F,'Item Summary'!K$4,'Order Details'!$C:$C,"In Production") -> 0 | ... M8: =SUMIFS('Order Details'!$Q:$Q,'Order Details'!$E:$E,"Yes",'Order Details'!$I:$I,'Item Summary'!$B8,'Order Details'!$F:$F,'Item Summary'!M$4,'Order Details'!$C:$C,"PO Received")+SUMIFS('Order Details'!$Q:$Q,'Order Details'!$E:$E,"Yes",'Order Details'!$I:$I,'Item Summary'!$B8,'Order Details'!$F:$F,'Item Summary'!M$4,'Order Details'!$C:$C,"Proforma Invoice Sent")+SUMIFS('Order Details'!$Q:$Q,'Order Details'!$E:$E,"Yes",'Order Details'!$I:$I,'Item Summary'!$B8,'Order Details'!$F:$F,'Item Summary'!M$4,'Order Details'!$C:$C,"Downpayment Received")+SUMIFS('Order Details'!$Q:$Q,'Order Details'!$E:$E,"Yes",'Order Details'!$I:$I,'Item Summary'!$B8,'Order Details'!$F:$F,'Item Summary'!M$4,'Order Details'!$C:$C,"In Production") -> 2800 | N8: =SUM(D8:M8) -> 19600 | Q8: 694432 | R8: =VLOOKUP($Q8,'Pricing Table - eff 27-Jan-2026'!$A:$L,9,FALSE)&""" "&VLOOKUP($Q8,'Pricing Table - eff 27-Jan-2026'!$A:$L,12,FALSE) -> 96" GLOSSY BLACK | S8: =SUMIFS('Order Details'!$Q:$Q,'Order Details'!$E:$E,"Yes",'Order Details'!$I:$I,$Q8,'Order Details'!$F:$F,'Item Summary'!S$4)-D8 -> 200 | T8: =SUMIFS('Order Details'!$Q:$Q,'Order Details'!$E:$E,"Yes",'Order Details'!$I:$I,$Q8,'Order Details'!$F:$F,'Item Summary'!T$4)-E8 -> 2800 | U8: =SUMIFS('Order Details'!$Q:$Q,'Order Details'!$E:$E,"Yes",'Order Details'!$I:$I,$Q8,'Order Details'!$F:$F,'Item Summary'!U$4)-F8 -> 1600 | V8: =SUMIFS('Order Details'!$Q:$Q,'Order Details'!$E:$E,"Yes",'Order Details'!$I:$I,$Q8,'Order Details'!$F:$F,'Item Summary'!V$4)-G8 -> 1400 | W8: =SUMIFS('Order Details'!$Q:$Q,'Order Details'!$E:$E,"Yes",'Order Details'!$I:$I,$Q8,'Order Details'!$F:$F,'Item Summary'!W$4)-H8 -> 5800 | X8: =SUMIFS('Order Details'!$Q:$Q,'Order Details'!$E:$E,"Yes",'Order Details'!$I:$I,$Q8,'Order Details'!$F:$F,'Item Summary'!X$4)-I8 -> 2400 | Y8: =SUMIFS('Order Details'!$Q:$Q,'Order Details'!$E:$E,"Yes",'Order Details'!$I:$I,$Q8,'Order Details'!$F:$F,'Item Summary'!Y$4)-J8 -> 800 | Z8: =SUMIFS('Order Details'!$Q:$Q,'Order Details'!$E:$E,"Yes",'Order Details'!$I:$I,$Q8,'Order Details'!$F:$F,'Item Summary'!Z$4)-K8 -> 5600 | ... AB8: =SUMIFS('Order Details'!$Q:$Q,'Order Details'!$E:$E,"Yes",'Order Details'!$I:$I,$Q8,'Order Details'!$F:$F,'Item Summary'!AB$4)-M8 -> 2800 | AC8: =SUM(S8:AB8) -> 23400
B9: 694433 | C9: =VLOOKUP($B9,'Pricing Table - eff 27-Jan-2026'!$A:$L,9,FALSE)&""" "&VLOOKUP($B9,'Pricing Table - eff 27-Jan-2026'!$A:$L,12,FALSE) -> 108" GLOSSY BLACK | D9: =SUMIFS('Order Details'!$Q:$Q,'Order Details'!$E:$E,"Yes",'Order Details'!$I:$I,'Item Summary'!$B9,'Order Details'!$F:$F,'Item Summary'!D$4,'Order Details'!$C:$C,"PO Received")+SUMIFS('Order Details'!$Q:$Q,'Order Details'!$E:$E,"Yes",'Order Details'!$I:$I,'Item Summary'!$B9,'Order Details'!$F:$F,'Item Summary'!D$4,'Order Details'!$C:$C,"Proforma Invoice Sent")+SUMIFS('Order Details'!$Q:$Q,'Order Details'!$E:$E,"Yes",'Order Details'!$I:$I,'Item Summary'!$B9,'Order Details'!$F:$F,'Item Summary'!D$4,'Order Details'!$C:$C,"Downpayment Received")+SUMIFS('Order Details'!$Q:$Q,'Order Details'!$E:$E,"Yes",'Order Details'!$I:$I,'Item Summary'!$B9,'Order Details'!$F:$F,'Item Summary'!D$4,'Order Details'!$C:$C,"In Production") -> 1000 | E9: =SUMIFS('Order Details'!$Q:$Q,'Order Details'!$E:$E,"Yes",'Order Details'!$I:$I,'Item Summary'!$B9,'Order Details'!$F:$F,'Item Summary'!E$4,'Order Details'!$C:$C,"PO Received")+SUMIFS('Order Details'!$Q:$Q,'Order Details'!$E:$E,"Yes",'Order Details'!$I:$I,'Item Summary'!$B9,'Order Details'!$F:$F,'Item Summary'!E$4,'Order Details'!$C:$C,"Proforma Invoice Sent")+SUMIFS('Order Details'!$Q:$Q,'Order Details'!$E:$E,"Yes",'Order Details'!$I:$I,'Item Summary'!$B9,'Order Details'!$F:$F,'Item Summary'!E$4,'Order Details'!$C:$C,"Downpayment Received")+SUMIFS('Order Details'!$Q:$Q,'Order Details'!$E:$E,"Yes",'Order Details'!$I:$I,'Item Summary'!$B9,'Order Details'!$F:$F,'Item Summary'!E$4,'Order Details'!$C:$C,"In Production") -> 0 | F9: =SUMIFS('Order Details'!$Q:$Q,'Order Details'!$E:$E,"Yes",'Order Details'!$I:$I,'Item Summary'!$B9,'Order Details'!$F:$F,'Item Summary'!F$4,'Order Details'!$C:$C,"PO Received")+SUMIFS('Order Details'!$Q:$Q,'Order Details'!$E:$E,"Yes",'Order Details'!$I:$I,'Item Summary'!$B9,'Order Details'!$F:$F,'Item Summary'!F$4,'Order Details'!$C:$C,"Proforma Invoice Sent")+SUMIFS('Order Details'!$Q:$Q,'Order Details'!$E:$E,"Yes",'Order Details'!$I:$I,'Item Summary'!$B9,'Order Details'!$F:$F,'Item Summary'!F$4,'Order Details'!$C:$C,"Downpayment Received")+SUMIFS('Order Details'!$Q:$Q,'Order Details'!$E:$E,"Yes",'Order Details'!$I:$I,'Item Summary'!$B9,'Order Details'!$F:$F,'Item Summary'!F$4,'Order Details'!$C:$C,"In Production") -> 2700 | G9: =SUMIFS('Order Details'!$Q:$Q,'Order Details'!$E:$E,"Yes",'Order Details'!$I:$I,'Item Summary'!$B9,'Order Details'!$F:$F,'Item Summary'!G$4,'Order Details'!$C:$C,"PO Received")+SUMIFS('Order Details'!$Q:$Q,'Order Details'!$E:$E,"Yes",'Order Details'!$I:$I,'Item Summary'!$B9,'Order Details'!$F:$F,'Item Summary'!G$4,'Order Details'!$C:$C,"Proforma Invoice Sent")+SUMIFS('Order Details'!$Q:$Q,'Order Details'!$E:$E,"Yes",'Order Details'!$I:$I,'Item Summary'!$B9,'Order Details'!$F:$F,'Item Summary'!G$4,'Order Details'!$C:$C,"Downpayment Received")+SUMIFS('Order Details'!$Q:$Q,'Order Details'!$E:$E,"Yes",'Order Details'!$I:$I,'Item Summary'!$B9,'Order Details'!$F:$F,'Item Summary'!G$4,'Order Details'!$C:$C,"In Production") -> 1200 | H9: =SUMIFS('Order Details'!$Q:$Q,'Order Details'!$E:$E,"Yes",'Order Details'!$I:$I,'Item Summary'!$B9,'Order Details'!$F:$F,'Item Summary'!H$4,'Order Details'!$C:$C,"PO Received")+SUMIFS('Order Details'!$Q:$Q,'Order Details'!$E:$E,"Yes",'Order Details'!$I:$I,'Item Summary'!$B9,'Order Details'!$F:$F,'Item Summary'!H$4,'Order Details'!$C:$C,"Proforma Invoice Sent")+SUMIFS('Order Details'!$Q:$Q,'Order Details'!$E:$E,"Yes",'Order Details'!$I:$I,'Item Summary'!$B9,'Order Details'!$F:$F,'Item Summary'!H$4,'Order Details'!$C:$C,"Downpayment Received")+SUMIFS('Order Details'!$Q:$Q,'Order Details'!$E:$E,"Yes",'Order Details'!$I:$I,'Item Summary'!$B9,'Order Details'!$F:$F,'Item Summary'!H$4,'Order Details'!$C:$C,"In Production") -> 400 | I9: =SUMIFS('Order Details'!$Q:$Q,'Order Details'!$E:$E,"Yes",'Order Details'!$I:$I,'Item Summary'!$B9,'Order Details'!$F:$F,'Item Summary'!I$4,'Order Details'!$C:$C,"PO Received")+SUMIFS('Order Details'!$Q:$Q,'Order Details'!$E:$E,"Yes",'Order Details'!$I:$I,'Item Summary'!$B9,'Order Details'!$F:$F,'Item Summary'!I$4,'Order Details'!$C:$C,"Proforma Invoice Sent")+SUMIFS('Order Details'!$Q:$Q,'Order Details'!$E:$E,"Yes",'Order Details'!$I:$I,'Item Summary'!$B9,'Order Details'!$F:$F,'Item Summary'!I$4,'Order Details'!$C:$C,"Downpayment Received")+SUMIFS('Order Details'!$Q:$Q,'Order Details'!$E:$E,"Yes",'Order Details'!$I:$I,'Item Summary'!$B9,'Order Details'!$F:$F,'Item Summary'!I$4,'Order Details'!$C:$C,"In Production") -> 2800 | J9: =SUMIFS('Order Details'!$Q:$Q,'Order Details'!$E:$E,"Yes",'Order Details'!$I:$I,'Item Summary'!$B9,'Order Details'!$F:$F,'Item Summary'!J$4,'Order Details'!$C:$C,"PO Received")+SUMIFS('Order Details'!$Q:$Q,'Order Details'!$E:$E,"Yes",'Order Details'!$I:$I,'Item Summary'!$B9,'Order Details'!$F:$F,'Item Summary'!J$4,'Order Details'!$C:$C,"Proforma Invoice Sent")+SUMIFS('Order Details'!$Q:$Q,'Order Details'!$E:$E,"Yes",'Order Details'!$I:$I,'Item Summary'!$B9,'Order Details'!$F:$F,'Item Summary'!J$4,'Order Details'!$C:$C,"Downpayment Received")+SUMIFS('Order Details'!$Q:$Q,'Order Details'!$E:$E,"Yes",'Order Details'!$I:$I,'Item Summary'!$B9,'Order Details'!$F:$F,'Item Summary'!J$4,'Order Details'!$C:$C,"In Production") -> 1400 | K9: =SUMIFS('Order Details'!$Q:$Q,'Order Details'!$E:$E,"Yes",'Order Details'!$I:$I,'Item Summary'!$B9,'Order Details'!$F:$F,'Item Summary'!K$4,'Order Details'!$C:$C,"PO Received")+SUMIFS('Order Details'!$Q:$Q,'Order Details'!$E:$E,"Yes",'Order Details'!$I:$I,'Item Summary'!$B9,'Order Details'!$F:$F,'Item Summary'!K$4,'Order Details'!$C:$C,"Proforma Invoice Sent")+SUMIFS('Order Details'!$Q:$Q,'Order Details'!$E:$E,"Yes",'Order Details'!$I:$I,'Item Summary'!$B9,'Order Details'!$F:$F,'Item Summary'!K$4,'Order Details'!$C:$C,"Downpayment Received")+SUMIFS('Order Details'!$Q:$Q,'Order Details'!$E:$E,"Yes",'Order Details'!$I:$I,'Item Summary'!$B9,'Order Details'!$F:$F,'Item Summary'!K$4,'Order Details'!$C:$C,"In Production") -> 0 | ... M9: =SUMIFS('Order Details'!$Q:$Q,'Order Details'!$E:$E,"Yes",'Order Details'!$I:$I,'Item Summary'!$B9,'Order Details'!$F:$F,'Item Summary'!M$4,'Order Details'!$C:$C,"PO Received")+SUMIFS('Order Details'!$Q:$Q,'Order Details'!$E:$E,"Yes",'Order Details'!$I:$I,'Item Summary'!$B9,'Order Details'!$F:$F,'Item Summary'!M$4,'Order Details'!$C:$C,"Proforma Invoice Sent")+SUMIFS('Order Details'!$Q:$Q,'Order Details'!$E:$E,"Yes",'Order Details'!$I:$I,'Item Summary'!$B9,'Order Details'!$F:$F,'Item Summary'!M$4,'Order Details'!$C:$C,"Downpayment Received")+SUMIFS('Order Details'!$Q:$Q,'Order Details'!$E:$E,"Yes",'Order Details'!$I:$I,'Item Summary'!$B9,'Order Details'!$F:$F,'Item Summary'!M$4,'Order Details'!$C:$C,"In Production") -> 0 | N9: =SUM(D9:M9) -> 9900 | Q9: 694433 | R9: =VLOOKUP($Q9,'Pricing Table - eff 27-Jan-2026'!$A:$L,9,FALSE)&""" "&VLOOKUP($Q9,'Pricing Table - eff 27-Jan-2026'!$A:$L,12,FALSE) -> 108" GLOSSY BLACK | S9: =SUMIFS('Order Details'!$Q:$Q,'Order Details'!$E:$E,"Yes",'Order Details'!$I:$I,$Q9,'Order Details'!$F:$F,'Item Summary'!S$4)-D9 -> 400 | T9: =SUMIFS('Order Details'!$Q:$Q,'Order Details'!$E:$E,"Yes",'Order Details'!$I:$I,$Q9,'Order Details'!$F:$F,'Item Summary'!T$4)-E9 -> 800 | U9: =SUMIFS('Order Details'!$Q:$Q,'Order Details'!$E:$E,"Yes",'Order Details'!$I:$I,$Q9,'Order Details'!$F:$F,'Item Summary'!U$4)-F9 -> 3600 | V9: =SUMIFS('Order Details'!$Q:$Q,'Order Details'!$E:$E,"Yes",'Order Details'!$I:$I,$Q9,'Order Details'!$F:$F,'Item Summary'!V$4)-G9 -> 1400 | W9: =SUMIFS('Order Details'!$Q:$Q,'Order Details'!$E:$E,"Yes",'Order Details'!$I:$I,$Q9,'Order Details'!$F:$F,'Item Summary'!W$4)-H9 -> 1800 | X9: =SUMIFS('Order Details'!$Q:$Q,'Order Details'!$E:$E,"Yes",'Order Details'!$I:$I,$Q9,'Order Details'!$F:$F,'Item Summary'!X$4)-I9 -> 0 | Y9: =SUMIFS('Order Details'!$Q:$Q,'Order Details'!$E:$E,"Yes",'Order Details'!$I:$I,$Q9,'Order Details'!$F:$F,'Item Summary'!Y$4)-J9 -> 1400 | Z9: =SUMIFS('Order Details'!$Q:$Q,'Order Details'!$E:$E,"Yes",'Order Details'!$I:$I,$Q9,'Order Details'!$F:$F,'Item Summary'!Z$4)-K9 -> 2400 | ... AB9: =SUMIFS('Order Details'!$Q:$Q,'Order Details'!$E:$E,"Yes",'Order Details'!$I:$I,$Q9,'Order Details'!$F:$F,'Item Summary'!AB$4)-M9 -> 2400 | AC9: =SUM(S9:AB9) -> 14200
B10: 694434 | C10: =VLOOKUP($B10,'Pricing Table - eff 27-Jan-2026'!$A:$L,9,FALSE)&""" "&VLOOKUP($B10,'Pricing Table - eff 27-Jan-2026'!$A:$L,12,FALSE) -> 144" GLOSSY BLACK | D10: =SUMIFS('Order Details'!$Q:$Q,'Order Details'!$E:$E,"Yes",'Order Details'!$I:$I,'Item Summary'!$B10,'Order Details'!$F:$F,'Item Summary'!D$4,'Order Details'!$C:$C,"PO Received")+SUMIFS('Order Details'!$Q:$Q,'Order Details'!$E:$E,"Yes",'Order Details'!$I:$I,'Item Summary'!$B10,'Order Details'!$F:$F,'Item Summary'!D$4,'Order Details'!$C:$C,"Proforma Invoice Sent")+SUMIFS('Order Details'!$Q:$Q,'Order Details'!$E:$E,"Yes",'Order Details'!$I:$I,'Item Summary'!$B10,'Order Details'!$F:$F,'Item Summary'!D$4,'Order Details'!$C:$C,"Downpayment Received")+SUMIFS('Order Details'!$Q:$Q,'Order Details'!$E:$E,"Yes",'Order Details'!$I:$I,'Item Summary'!$B10,'Order Details'!$F:$F,'Item Summary'!D$4,'Order Details'!$C:$C,"In Production") -> 0 | E10: =SUMIFS('Order Details'!$Q:$Q,'Order Details'!$E:$E,"Yes",'Order Details'!$I:$I,'Item Summary'!$B10,'Order Details'!$F:$F,'Item Summary'!E$4,'Order Details'!$C:$C,"PO Received")+SUMIFS('Order Details'!$Q:$Q,'Order Details'!$E:$E,"Yes",'Order Details'!$I:$I,'Item Summary'!$B10,'Order Details'!$F:$F,'Item Summary'!E$4,'Order Details'!$C:$C,"Proforma Invoice Sent")+SUMIFS('Order Details'!$Q:$Q,'Order Details'!$E:$E,"Yes",'Order Details'!$I:$I,'Item Summary'!$B10,'Order Details'!$F:$F,'Item Summary'!E$4,'Order Details'!$C:$C,"Downpayment Received")+SUMIFS('Order Details'!$Q:$Q,'Order Details'!$E:$E,"Yes",'Order Details'!$I:$I,'Item Summary'!$B10,'Order Details'!$F:$F,'Item Summary'!E$4,'Order Details'!$C:$C,"In Production") -> 0 | F10: =SUMIFS('Order Details'!$Q:$Q,'Order Details'!$E:$E,"Yes",'Order Details'!$I:$I,'Item Summary'!$B10,'Order Details'!$F:$F,'Item Summary'!F$4,'Order Details'!$C:$C,"PO Received")+SUMIFS('Order Details'!$Q:$Q,'Order Details'!$E:$E,"Yes",'Order Details'!$I:$I,'Item Summary'!$B10,'Order Details'!$F:$F,'Item Summary'!F$4,'Order Details'!$C:$C,"Proforma Invoice Sent")+SUMIFS('Order Details'!$Q:$Q,'Order Details'!$E:$E,"Yes",'Order Details'!$I:$I,'Item Summary'!$B10,'Order Details'!$F:$F,'Item Summary'!F$4,'Order Details'!$C:$C,"Downpayment Received")+SUMIFS('Order Details'!$Q:$Q,'Order Details'!$E:$E,"Yes",'Order Details'!$I:$I,'Item Summary'!$B10,'Order Details'!$F:$F,'Item Summary'!F$4,'Order Details'!$C:$C,"In Production") -> 1800 | G10: =SUMIFS('Order Details'!$Q:$Q,'Order Details'!$E:$E,"Yes",'Order Details'!$I:$I,'Item Summary'!$B10,'Order Details'!$F:$F,'Item Summary'!G$4,'Order Details'!$C:$C,"PO Received")+SUMIFS('Order Details'!$Q:$Q,'Order Details'!$E:$E,"Yes",'Order Details'!$I:$I,'Item Summary'!$B10,'Order Details'!$F:$F,'Item Summary'!G$4,'Order Details'!$C:$C,"Proforma Invoice Sent")+SUMIFS('Order Details'!$Q:$Q,'Order Details'!$E:$E,"Yes",'Order Details'!$I:$I,'Item Summary'!$B10,'Order Details'!$F:$F,'Item Summary'!G$4,'Order Details'!$C:$C,"Downpayment Received")+SUMIFS('Order Details'!$Q:$Q,'Order Details'!$E:$E,"Yes",'Order Details'!$I:$I,'Item Summary'!$B10,'Order Details'!$F:$F,'Item Summary'!G$4,'Order Details'!$C:$C,"In Production") -> 0 | H10: =SUMIFS('Order Details'!$Q:$Q,'Order Details'!$E:$E,"Yes",'Order Details'!$I:$I,'Item Summary'!$B10,'Order Details'!$F:$F,'Item Summary'!H$4,'Order Details'!$C:$C,"PO Received")+SUMIFS('Order Details'!$Q:$Q,'Order Details'!$E:$E,"Yes",'Order Details'!$I:$I,'Item Summary'!$B10,'Order Details'!$F:$F,'Item Summary'!H$4,'Order Details'!$C:$C,"Proforma Invoice Sent")+SUMIFS('Order Details'!$Q:$Q,'Order Details'!$E:$E,"Yes",'Order Details'!$I:$I,'Item Summary'!$B10,'Order Details'!$F:$F,'Item Summary'!H$4,'Order Details'!$C:$C,"Downpayment Received")+SUMIFS('Order Details'!$Q:$Q,'Order Details'!$E:$E,"Yes",'Order Details'!$I:$I,'Item Summary'!$B10,'Order Details'!$F:$F,'Item Summary'!H$4,'Order Details'!$C:$C,"In Production") -> 0 | I10: =SUMIFS('Order Details'!$Q:$Q,'Order Details'!$E:$E,"Yes",'Order Details'!$I:$I,'Item Summary'!$B10,'Order Details'!$F:$F,'Item Summary'!I$4,'Order Details'!$C:$C,"PO Received")+SUMIFS('Order Details'!$Q:$Q,'Order Details'!$E:$E,"Yes",'Order Details'!$I:$I,'Item Summary'!$B10,'Order Details'!$F:$F,'Item Summary'!I$4,'Order Details'!$C:$C,"Proforma Invoice Sent")+SUMIFS('Order Details'!$Q:$Q,'Order Details'!$E:$E,"Yes",'Order Details'!$I:$I,'Item Summary'!$B10,'Order Details'!$F:$F,'Item Summary'!I$4,'Order Details'!$C:$C,"Downpayment Received")+SUMIFS('Order Details'!$Q:$Q,'Order Details'!$E:$E,"Yes",'Order Details'!$I:$I,'Item Summary'!$B10,'Order Details'!$F:$F,'Item Summary'!I$4,'Order Details'!$C:$C,"In Production") -> 0 | J10: =SUMIFS('Order Details'!$Q:$Q,'Order Details'!$E:$E,"Yes",'Order Details'!$I:$I,'Item Summary'!$B10,'Order Details'!$F:$F,'Item Summary'!J$4,'Order Details'!$C:$C,"PO Received")+SUMIFS('Order Details'!$Q:$Q,'Order Details'!$E:$E,"Yes",'Order Details'!$I:$I,'Item Summary'!$B10,'Order Details'!$F:$F,'Item Summary'!J$4,'Order Details'!$C:$C,"Proforma Invoice Sent")+SUMIFS('Order Details'!$Q:$Q,'Order Details'!$E:$E,"Yes",'Order Details'!$I:$I,'Item Summary'!$B10,'Order Details'!$F:$F,'Item Summary'!J$4,'Order Details'!$C:$C,"Downpayment Received")+SUMIFS('Order Details'!$Q:$Q,'Order Details'!$E:$E,"Yes",'Order Details'!$I:$I,'Item Summary'!$B10,'Order Details'!$F:$F,'Item Summary'!J$4,'Order Details'!$C:$C,"In Production") -> 0 | K10: =SUMIFS('Order Details'!$Q:$Q,'Order Details'!$E:$E,"Yes",'Order Details'!$I:$I,'Item Summary'!$B10,'Order Details'!$F:$F,'Item Summary'!K$4,'Order Details'!$C:$C,"PO Received")+SUMIFS('Order Details'!$Q:$Q,'Order Details'!$E:$E,"Yes",'Order Details'!$I:$I,'Item Summary'!$B10,'Order Details'!$F:$F,'Item Summary'!K$4,'Order Details'!$C:$C,"Proforma Invoice Sent")+SUMIFS('Order Details'!$Q:$Q,'Order Details'!$E:$E,"Yes",'Order Details'!$I:$I,'Item Summary'!$B10,'Order Details'!$F:$F,'Item Summary'!K$4,'Order Details'!$C:$C,"Downpayment Received")+SUMIFS('Order Details'!$Q:$Q,'Order Details'!$E:$E,"Yes",'Order Details'!$I:$I,'Item Summary'!$B10,'Order Details'!$F:$F,'Item Summary'!K$4,'Order Details'!$C:$C,"In Production") -> 0 | ... M10: =SUMIFS('Order Details'!$Q:$Q,'Order Details'!$E:$E,"Yes",'Order Details'!$I:$I,'Item Summary'!$B10,'Order Details'!$F:$F,'Item Summary'!M$4,'Order Details'!$C:$C,"PO Received")+SUMIFS('Order Details'!$Q:$Q,'Order Details'!$E:$E,"Yes",'Order Details'!$I:$I,'Item Summary'!$B10,'Order Details'!$F:$F,'Item Summary'!M$4,'Order Details'!$C:$C,"Proforma Invoice Sent")+SUMIFS('Order Details'!$Q:$Q,'Order Details'!$E:$E,"Yes",'Order Details'!$I:$I,'Item Summary'!$B10,'Order Details'!$F:$F,'Item Summary'!M$4,'Order Details'!$C:$C,"Downpayment Received")+SUMIFS('Order Details'!$Q:$Q,'Order Details'!$E:$E,"Yes",'Order Details'!$I:$I,'Item Summary'!$B10,'Order Details'!$F:$F,'Item Summary'!M$4,'Order Details'!$C:$C,"In Production") -> 0 | N10: =SUM(D10:M10) -> 1800 | Q10: 694434 | R10: =VLOOKUP($Q10,'Pricing Table - eff 27-Jan-2026'!$A:$L,9,FALSE)&""" "&VLOOKUP($Q10,'Pricing Table - eff 27-Jan-2026'!$A:$L,12,FALSE) -> 144" GLOSSY BLACK | S10: =SUMIFS('Order Details'!$Q:$Q,'Order Details'!$E:$E,"Yes",'Order Details'!$I:$I,$Q10,'Order Details'!$F:$F,'Item Summary'!S$4)-D10 -> 0 | T10: =SUMIFS('Order Details'!$Q:$Q,'Order Details'!$E:$E,"Yes",'Order Details'!$I:$I,$Q10,'Order Details'!$F:$F,'Item Summary'!T$4)-E10 -> 200 | U10: =SUMIFS('Order Details'!$Q:$Q,'Order Details'!$E:$E,"Yes",'Order Details'!$I:$I,$Q10,'Order Details'!$F:$F,'Item Summary'!U$4)-F10 -> 1600 | V10: =SUMIFS('Order Details'!$Q:$Q,'Order Details'!$E:$E,"Yes",'Order Details'!$I:$I,$Q10,'Order Details'!$F:$F,'Item Summary'!V$4)-G10 -> 0 | W10: =SUMIFS('Order Details'!$Q:$Q,'Order Details'!$E:$E,"Yes",'Order Details'!$I:$I,$Q10,'Order Details'!$F:$F,'Item Summary'!W$4)-H10 -> 800 | X10: =SUMIFS('Order Details'!$Q:$Q,'Order Details'!$E:$E,"Yes",'Order Details'!$I:$I,$Q10,'Order Details'!$F:$F,'Item Summary'!X$4)-I10 -> 0 | Y10: =SUMIFS('Order Details'!$Q:$Q,'Order Details'!$E:$E,"Yes",'Order Details'!$I:$I,$Q10,'Order Details'!$F:$F,'Item Summary'!Y$4)-J10 -> 0 | Z10: =SUMIFS('Order Details'!$Q:$Q,'Order Details'!$E:$E,"Yes",'Order Details'!$I:$I,$Q10,'Order Details'!$F:$F,'Item Summary'!Z$4)-K10 -> 1000 | ... AB10: =SUMIFS('Order Details'!$Q:$Q,'Order Details'!$E:$E,"Yes",'Order Details'!$I:$I,$Q10,'Order Details'!$F:$F,'Item Summary'!AB$4)-M10 -> 1000 | AC10: =SUM(S10:AB10) -> 4600
B11: 704985 | C11: =VLOOKUP($B11,'Pricing Table - eff 27-Jan-2026'!$A:$L,9,FALSE)&""" "&VLOOKUP($B11,'Pricing Table - eff 27-Jan-2026'!$A:$L,12,FALSE) -> 84" GLOSSY WHITE | D11: =SUMIFS('Order Details'!$Q:$Q,'Order Details'!$E:$E,"Yes",'Order Details'!$I:$I,'Item Summary'!$B11,'Order Details'!$F:$F,'Item Summary'!D$4,'Order Details'!$C:$C,"PO Received")+SUMIFS('Order Details'!$Q:$Q,'Order Details'!$E:$E,"Yes",'Order Details'!$I:$I,'Item Summary'!$B11,'Order Details'!$F:$F,'Item Summary'!D$4,'Order Details'!$C:$C,"Proforma Invoice Sent")+SUMIFS('Order Details'!$Q:$Q,'Order Details'!$E:$E,"Yes",'Order Details'!$I:$I,'Item Summary'!$B11,'Order Details'!$F:$F,'Item Summary'!D$4,'Order Details'!$C:$C,"Downpayment Received")+SUMIFS('Order Details'!$Q:$Q,'Order Details'!$E:$E,"Yes",'Order Details'!$I:$I,'Item Summary'!$B11,'Order Details'!$F:$F,'Item Summary'!D$4,'Order Details'!$C:$C,"In Production") -> 0 | E11: =SUMIFS('Order Details'!$Q:$Q,'Order Details'!$E:$E,"Yes",'Order Details'!$I:$I,'Item Summary'!$B11,'Order Details'!$F:$F,'Item Summary'!E$4,'Order Details'!$C:$C,"PO Received")+SUMIFS('Order Details'!$Q:$Q,'Order Details'!$E:$E,"Yes",'Order Details'!$I:$I,'Item Summary'!$B11,'Order Details'!$F:$F,'Item Summary'!E$4,'Order Details'!$C:$C,"Proforma Invoice Sent")+SUMIFS('Order Details'!$Q:$Q,'Order Details'!$E:$E,"Yes",'Order Details'!$I:$I,'Item Summary'!$B11,'Order Details'!$F:$F,'Item Summary'!E$4,'Order Details'!$C:$C,"Downpayment Received")+SUMIFS('Order Details'!$Q:$Q,'Order Details'!$E:$E,"Yes",'Order Details'!$I:$I,'Item Summary'!$B11,'Order Details'!$F:$F,'Item Summary'!E$4,'Order Details'!$C:$C,"In Production") -> 600 | F11: =SUMIFS('Order Details'!$Q:$Q,'Order Details'!$E:$E,"Yes",'Order Details'!$I:$I,'Item Summary'!$B11,'Order Details'!$F:$F,'Item Summary'!F$4,'Order Details'!$C:$C,"PO Received")+SUMIFS('Order Details'!$Q:$Q,'Order Details'!$E:$E,"Yes",'Order Details'!$I:$I,'Item Summary'!$B11,'Order Details'!$F:$F,'Item Summary'!F$4,'Order Details'!$C:$C,"Proforma Invoice Sent")+SUMIFS('Order Details'!$Q:$Q,'Order Details'!$E:$E,"Yes",'Order Details'!$I:$I,'Item Summary'!$B11,'Order Details'!$F:$F,'Item Summary'!F$4,'Order Details'!$C:$C,"Downpayment Received")+SUMIFS('Order Details'!$Q:$Q,'Order Details'!$E:$E,"Yes",'Order Details'!$I:$I,'Item Summary'!$B11,'Order Details'!$F:$F,'Item Summary'!F$4,'Order Details'!$C:$C,"In Production") -> 0 | G11: =SUMIFS('Order Details'!$Q:$Q,'Order Details'!$E:$E,"Yes",'Order Details'!$I:$I,'Item Summary'!$B11,'Order Details'!$F:$F,'Item Summary'!G$4,'Order Details'!$C:$C,"PO Received")+SUMIFS('Order Details'!$Q:$Q,'Order Details'!$E:$E,"Yes",'Order Details'!$I:$I,'Item Summary'!$B11,'Order Details'!$F:$F,'Item Summary'!G$4,'Order Details'!$C:$C,"Proforma Invoice Sent")+SUMIFS('Order Details'!$Q:$Q,'Order Details'!$E:$E,"Yes",'Order Details'!$I:$I,'Item Summary'!$B11,'Order Details'!$F:$F,'Item Summary'!G$4,'Order Details'!$C:$C,"Downpayment Received")+SUMIFS('Order Details'!$Q:$Q,'Order Details'!$E:$E,"Yes",'Order Details'!$I:$I,'Item Summary'!$B11,'Order Details'!$F:$F,'Item Summary'!G$4,'Order Details'!$C:$C,"In Production") -> 0 | H11: =SUMIFS('Order Details'!$Q:$Q,'Order Details'!$E:$E,"Yes",'Order Details'!$I:$I,'Item Summary'!$B11,'Order Details'!$F:$F,'Item Summary'!H$4,'Order Details'!$C:$C,"PO Received")+SUMIFS('Order Details'!$Q:$Q,'Order Details'!$E:$E,"Yes",'Order Details'!$I:$I,'Item Summary'!$B11,'Order Details'!$F:$F,'Item Summary'!H$4,'Order Details'!$C:$C,"Proforma Invoice Sent")+SUMIFS('Order Details'!$Q:$Q,'Order Details'!$E:$E,"Yes",'Order Details'!$I:$I,'Item Summary'!$B11,'Order Details'!$F:$F,'Item Summary'!H$4,'Order Details'!$C:$C,"Downpayment Received")+SUMIFS('Order Details'!$Q:$Q,'Order Details'!$E:$E,"Yes",'Order Details'!$I:$I,'Item Summary'!$B11,'Order Details'!$F:$F,'Item Summary'!H$4,'Order Details'!$C:$C,"In Production") -> 0 | I11: =SUMIFS('Order Details'!$Q:$Q,'Order Details'!$E:$E,"Yes",'Order Details'!$I:$I,'Item Summary'!$B11,'Order Details'!$F:$F,'Item Summary'!I$4,'Order Details'!$C:$C,"PO Received")+SUMIFS('Order Details'!$Q:$Q,'Order Details'!$E:$E,"Yes",'Order Details'!$I:$I,'Item Summary'!$B11,'Order Details'!$F:$F,'Item Summary'!I$4,'Order Details'!$C:$C,"Proforma Invoice Sent")+SUMIFS('Order Details'!$Q:$Q,'Order Details'!$E:$E,"Yes",'Order Details'!$I:$I,'Item Summary'!$B11,'Order Details'!$F:$F,'Item Summary'!I$4,'Order Details'!$C:$C,"Downpayment Received")+SUMIFS('Order Details'!$Q:$Q,'Order Details'!$E:$E,"Yes",'Order Details'!$I:$I,'Item Summary'!$B11,'Order Details'!$F:$F,'Item Summary'!I$4,'Order Details'!$C:$C,"In Production") -> 0 | J11: =SUMIFS('Order Details'!$Q:$Q,'Order Details'!$E:$E,"Yes",'Order Details'!$I:$I,'Item Summary'!$B11,'Order Details'!$F:$F,'Item Summary'!J$4,'Order Details'!$C:$C,"PO Received")+SUMIFS('Order Details'!$Q:$Q,'Order Details'!$E:$E,"Yes",'Order Details'!$I:$I,'Item Summary'!$B11,'Order Details'!$F:$F,'Item Summary'!J$4,'Order Details'!$C:$C,"Proforma Invoice Sent")+SUMIFS('Order Details'!$Q:$Q,'Order Details'!$E:$E,"Yes",'Order Details'!$I:$I,'Item Summary'!$B11,'Order Details'!$F:$F,'Item Summary'!J$4,'Order Details'!$C:$C,"Downpayment Received")+SUMIFS('Order Details'!$Q:$Q,'Order Details'!$E:$E,"Yes",'Order Details'!$I:$I,'Item Summary'!$B11,'Order Details'!$F:$F,'Item Summary'!J$4,'Order Details'!$C:$C,"In Production") -> 0 | K11: =SUMIFS('Order Details'!$Q:$Q,'Order Details'!$E:$E,"Yes",'Order Details'!$I:$I,'Item Summary'!$B11,'Order Details'!$F:$F,'Item Summary'!K$4,'Order Details'!$C:$C,"PO Received")+SUMIFS('Order Details'!$Q:$Q,'Order Details'!$E:$E,"Yes",'Order Details'!$I:$I,'Item Summary'!$B11,'Order Details'!$F:$F,'Item Summary'!K$4,'Order Details'!$C:$C,"Proforma Invoice Sent")+SUMIFS('Order Details'!$Q:$Q,'Order Details'!$E:$E,"Yes",'Order Details'!$I:$I,'Item Summary'!$B11,'Order Details'!$F:$F,'Item Summary'!K$4,'Order Details'!$C:$C,"Downpayment Received")+SUMIFS('Order Details'!$Q:$Q,'Order Details'!$E:$E,"Yes",'Order Details'!$I:$I,'Item Summary'!$B11,'Order Details'!$F:$F,'Item Summary'!K$4,'Order Details'!$C:$C,"In Production") -> 0 | ... M11: =SUMIFS('Order Details'!$Q:$Q,'Order Details'!$E:$E,"Yes",'Order Details'!$I:$I,'Item Summary'!$B11,'Order Details'!$F:$F,'Item Summary'!M$4,'Order Details'!$C:$C,"PO Received")+SUMIFS('Order Details'!$Q:$Q,'Order Details'!$E:$E,"Yes",'Order Details'!$I:$I,'Item Summary'!$B11,'Order Details'!$F:$F,'Item Summary'!M$4,'Order Details'!$C:$C,"Proforma Invoice Sent")+SUMIFS('Order Details'!$Q:$Q,'Order Details'!$E:$E,"Yes",'Order Details'!$I:$I,'Item Summary'!$B11,'Order Details'!$F:$F,'Item Summary'!M$4,'Order Details'!$C:$C,"Downpayment Received")+SUMIFS('Order Details'!$Q:$Q,'Order Details'!$E:$E,"Yes",'Order Details'!$I:$I,'Item Summary'!$B11,'Order Details'!$F:$F,'Item Summary'!M$4,'Order Details'!$C:$C,"In Production") -> 0 | N11: =SUM(D11:M11) -> 600 | Q11: 704985 | R11: =VLOOKUP($Q11,'Pricing Table - eff 27-Jan-2026'!$A:$L,9,FALSE)&""" "&VLOOKUP($Q11,'Pricing Table - eff 27-Jan-2026'!$A:$L,12,FALSE) -> 84" GLOSSY WHITE | S11: =SUMIFS('Order Details'!$Q:$Q,'Order Details'!$E:$E,"Yes",'Order Details'!$I:$I,$Q11,'Order Details'!$F:$F,'Item Summary'!S$4)-D11 -> 0 | T11: =SUMIFS('Order Details'!$Q:$Q,'Order Details'!$E:$E,"Yes",'Order Details'!$I:$I,$Q11,'Order Details'!$F:$F,'Item Summary'!T$4)-E11 -> 1200 | U11: =SUMIFS('Order Details'!$Q:$Q,'Order Details'!$E:$E,"Yes",'Order Details'!$I:$I,$Q11,'Order Details'!$F:$F,'Item Summary'!U$4)-F11 -> 0 | V11: =SUMIFS('Order Details'!$Q:$Q,'Order Details'!$E:$E,"Yes",'Order Details'!$I:$I,$Q11,'Order Details'!$F:$F,'Item Summary'!V$4)-G11 -> 0 | W11: =SUMIFS('Order Details'!$Q:$Q,'Order Details'!$E:$E,"Yes",'Order Details'!$I:$I,$Q11,'Order Details'!$F:$F,'Item Summary'!W$4)-H11 -> 0 | X11: =SUMIFS('Order Details'!$Q:$Q,'Order Details'!$E:$E,"Yes",'Order Details'!$I:$I,$Q11,'Order Details'!$F:$F,'Item Summary'!X$4)-I11 -> 0 | Y11: =SUMIFS('Order Details'!$Q:$Q,'Order Details'!$E:$E,"Yes",'Order Details'!$I:$I,$Q11,'Order Details'!$F:$F,'Item Summary'!Y$4)-J11 -> 0 | Z11: =SUMIFS('Order Details'!$Q:$Q,'Order Details'!$E:$E,"Yes",'Order Details'!$I:$I,$Q11,'Order Details'!$F:$F,'Item Summary'!Z$4)-K11 -> 0 | ... AB11: =SUMIFS('Order Details'!$Q:$Q,'Order Details'!$E:$E,"Yes",'Order Details'!$I:$I,$Q11,'Order Details'!$F:$F,'Item Summary'!AB$4)-M11 -> 0 | AC11: =SUM(S11:AB11) -> 1200
B12: 694435 | C12: =VLOOKUP($B12,'Pricing Table - eff 27-Jan-2026'!$A:$L,9,FALSE)&""" "&VLOOKUP($B12,'Pricing Table - eff 27-Jan-2026'!$A:$L,12,FALSE) -> 90" GLOSSY WHITE | D12: =SUMIFS('Order Details'!$Q:$Q,'Order Details'!$E:$E,"Yes",'Order Details'!$I:$I,'Item Summary'!$B12,'Order Details'!$F:$F,'Item Summary'!D$4,'Order Details'!$C:$C,"PO Received")+SUMIFS('Order Details'!$Q:$Q,'Order Details'!$E:$E,"Yes",'Order Details'!$I:$I,'Item Summary'!$B12,'Order Details'!$F:$F,'Item Summary'!D$4,'Order Details'!$C:$C,"Proforma Invoice Sent")+SUMIFS('Order Details'!$Q:$Q,'Order Details'!$E:$E,"Yes",'Order Details'!$I:$I,'Item Summary'!$B12,'Order Details'!$F:$F,'Item Summary'!D$4,'Order Details'!$C:$C,"Downpayment Received")+SUMIFS('Order Details'!$Q:$Q,'Order Details'!$E:$E,"Yes",'Order Details'!$I:$I,'Item Summary'!$B12,'Order Details'!$F:$F,'Item Summary'!D$4,'Order Details'!$C:$C,"In Production") -> 0 | E12: =SUMIFS('Order Details'!$Q:$Q,'Order Details'!$E:$E,"Yes",'Order Details'!$I:$I,'Item Summary'!$B12,'Order Details'!$F:$F,'Item Summary'!E$4,'Order Details'!$C:$C,"PO Received")+SUMIFS('Order Details'!$Q:$Q,'Order Details'!$E:$E,"Yes",'Order Details'!$I:$I,'Item Summary'!$B12,'Order Details'!$F:$F,'Item Summary'!E$4,'Order Details'!$C:$C,"Proforma Invoice Sent")+SUMIFS('Order Details'!$Q:$Q,'Order Details'!$E:$E,"Yes",'Order Details'!$I:$I,'Item Summary'!$B12,'Order Details'!$F:$F,'Item Summary'!E$4,'Order Details'!$C:$C,"Downpayment Received")+SUMIFS('Order Details'!$Q:$Q,'Order Details'!$E:$E,"Yes",'Order Details'!$I:$I,'Item Summary'!$B12,'Order Details'!$F:$F,'Item Summary'!E$4,'Order Details'!$C:$C,"In Production") -> 0 | F12: =SUMIFS('Order Details'!$Q:$Q,'Order Details'!$E:$E,"Yes",'Order Details'!$I:$I,'Item Summary'!$B12,'Order Details'!$F:$F,'Item Summary'!F$4,'Order Details'!$C:$C,"PO Received")+SUMIFS('Order Details'!$Q:$Q,'Order Details'!$E:$E,"Yes",'Order Details'!$I:$I,'Item Summary'!$B12,'Order Details'!$F:$F,'Item Summary'!F$4,'Order Details'!$C:$C,"Proforma Invoice Sent")+SUMIFS('Order Details'!$Q:$Q,'Order Details'!$E:$E,"Yes",'Order Details'!$I:$I,'Item Summary'!$B12,'Order Details'!$F:$F,'Item Summary'!F$4,'Order Details'!$C:$C,"Downpayment Received")+SUMIFS('Order Details'!$Q:$Q,'Order Details'!$E:$E,"Yes",'Order Details'!$I:$I,'Item Summary'!$B12,'Order Details'!$F:$F,'Item Summary'!F$4,'Order Details'!$C:$C,"In Production") -> 0 | G12: =SUMIFS('Order Details'!$Q:$Q,'Order Details'!$E:$E,"Yes",'Order Details'!$I:$I,'Item Summary'!$B12,'Order Details'!$F:$F,'Item Summary'!G$4,'Order Details'!$C:$C,"PO Received")+SUMIFS('Order Details'!$Q:$Q,'Order Details'!$E:$E,"Yes",'Order Details'!$I:$I,'Item Summary'!$B12,'Order Details'!$F:$F,'Item Summary'!G$4,'Order Details'!$C:$C,"Proforma Invoice Sent")+SUMIFS('Order Details'!$Q:$Q,'Order Details'!$E:$E,"Yes",'Order Details'!$I:$I,'Item Summary'!$B12,'Order Details'!$F:$F,'Item Summary'!G$4,'Order Details'!$C:$C,"Downpayment Received")+SUMIFS('Order Details'!$Q:$Q,'Order Details'!$E:$E,"Yes",'Order Details'!$I:$I,'Item Summary'!$B12,'Order Details'!$F:$F,'Item Summary'!G$4,'Order Details'!$C:$C,"In Production") -> 0 | H12: =SUMIFS('Order Details'!$Q:$Q,'Order Details'!$E:$E,"Yes",'Order Details'!$I:$I,'Item Summary'!$B12,'Order Details'!$F:$F,'Item Summary'!H$4,'Order Details'!$C:$C,"PO Received")+SUMIFS('Order Details'!$Q:$Q,'Order Details'!$E:$E,"Yes",'Order Details'!$I:$I,'Item Summary'!$B12,'Order Details'!$F:$F,'Item Summary'!H$4,'Order Details'!$C:$C,"Proforma Invoice Sent")+SUMIFS('Order Details'!$Q:$Q,'Order Details'!$E:$E,"Yes",'Order Details'!$I:$I,'Item Summary'!$B12,'Order Details'!$F:$F,'Item Summary'!H$4,'Order Details'!$C:$C,"Downpayment Received")+SUMIFS('Order Details'!$Q:$Q,'Order Details'!$E:$E,"Yes",'Order Details'!$I:$I,'Item Summary'!$B12,'Order Details'!$F:$F,'Item Summary'!H$4,'Order Details'!$C:$C,"In Production") -> 0 | I12: =SUMIFS('Order Details'!$Q:$Q,'Order Details'!$E:$E,"Yes",'Order Details'!$I:$I,'Item Summary'!$B12,'Order Details'!$F:$F,'Item Summary'!I$4,'Order Details'!$C:$C,"PO Received")+SUMIFS('Order Details'!$Q:$Q,'Order Details'!$E:$E,"Yes",'Order Details'!$I:$I,'Item Summary'!$B12,'Order Details'!$F:$F,'Item Summary'!I$4,'Order Details'!$C:$C,"Proforma Invoice Sent")+SUMIFS('Order Details'!$Q:$Q,'Order Details'!$E:$E,"Yes",'Order Details'!$I:$I,'Item Summary'!$B12,'Order Details'!$F:$F,'Item Summary'!I$4,'Order Details'!$C:$C,"Downpayment Received")+SUMIFS('Order Details'!$Q:$Q,'Order Details'!$E:$E,"Yes",'Order Details'!$I:$I,'Item Summary'!$B12,'Order Details'!$F:$F,'Item Summary'!I$4,'Order Details'!$C:$C,"In Production") -> 0 | J12: =SUMIFS('Order Details'!$Q:$Q,'Order Details'!$E:$E,"Yes",'Order Details'!$I:$I,'Item Summary'!$B12,'Order Details'!$F:$F,'Item Summary'!J$4,'Order Details'!$C:$C,"PO Received")+SUMIFS('Order Details'!$Q:$Q,'Order Details'!$E:$E,"Yes",'Order Details'!$I:$I,'Item Summary'!$B12,'Order Details'!$F:$F,'Item Summary'!J$4,'Order Details'!$C:$C,"Proforma Invoice Sent")+SUMIFS('Order Details'!$Q:$Q,'Order Details'!$E:$E,"Yes",'Order Details'!$I:$I,'Item Summary'!$B12,'Order Details'!$F:$F,'Item Summary'!J$4,'Order Details'!$C:$C,"Downpayment Received")+SUMIFS('Order Details'!$Q:$Q,'Order Details'!$E:$E,"Yes",'Order Details'!$I:$I,'Item Summary'!$B12,'Order Details'!$F:$F,'Item Summary'!J$4,'Order Details'!$C:$C,"In Production") -> 0 | K12: =SUMIFS('Order Details'!$Q:$Q,'Order Details'!$E:$E,"Yes",'Order Details'!$I:$I,'Item Summary'!$B12,'Order Details'!$F:$F,'Item Summary'!K$4,'Order Details'!$C:$C,"PO Received")+SUMIFS('Order Details'!$Q:$Q,'Order Details'!$E:$E,"Yes",'Order Details'!$I:$I,'Item Summary'!$B12,'Order Details'!$F:$F,'Item Summary'!K$4,'Order Details'!$C:$C,"Proforma Invoice Sent")+SUMIFS('Order Details'!$Q:$Q,'Order Details'!$E:$E,"Yes",'Order Details'!$I:$I,'Item Summary'!$B12,'Order Details'!$F:$F,'Item Summary'!K$4,'Order Details'!$C:$C,"Downpayment Received")+SUMIFS('Order Details'!$Q:$Q,'Order Details'!$E:$E,"Yes",'Order Details'!$I:$I,'Item Summary'!$B12,'Order Details'!$F:$F,'Item Summary'!K$4,'Order Details'!$C:$C,"In Production") -> 0 | ... M12: =SUMIFS('Order Details'!$Q:$Q,'Order Details'!$E:$E,"Yes",'Order Details'!$I:$I,'Item Summary'!$B12,'Order Details'!$F:$F,'Item Summary'!M$4,'Order Details'!$C:$C,"PO Received")+SUMIFS('Order Details'!$Q:$Q,'Order Details'!$E:$E,"Yes",'Order Details'!$I:$I,'Item Summary'!$B12,'Order Details'!$F:$F,'Item Summary'!M$4,'Order Details'!$C:$C,"Proforma Invoice Sent")+SUMIFS('Order Details'!$Q:$Q,'Order Details'!$E:$E,"Yes",'Order Details'!$I:$I,'Item Summary'!$B12,'Order Details'!$F:$F,'Item Summary'!M$4,'Order Details'!$C:$C,"Downpayment Received")+SUMIFS('Order Details'!$Q:$Q,'Order Details'!$E:$E,"Yes",'Order Details'!$I:$I,'Item Summary'!$B12,'Order Details'!$F:$F,'Item Summary'!M$4,'Order Details'!$C:$C,"In Production") -> 0 | N12: =SUM(D12:M12) -> 0 | Q12: 694435 | R12: =VLOOKUP($Q12,'Pricing Table - eff 27-Jan-2026'!$A:$L,9,FALSE)&""" "&VLOOKUP($Q12,'Pricing Table - eff 27-Jan-2026'!$A:$L,12,FALSE) -> 90" GLOSSY WHITE | S12: =SUMIFS('Order Details'!$Q:$Q,'Order Details'!$E:$E,"Yes",'Order Details'!$I:$I,$Q12,'Order Details'!$F:$F,'Item Summary'!S$4)-D12 -> 0 | T12: =SUMIFS('Order Details'!$Q:$Q,'Order Details'!$E:$E,"Yes",'Order Details'!$I:$I,$Q12,'Order Details'!$F:$F,'Item Summary'!T$4)-E12 -> 0 | U12: =SUMIFS('Order Details'!$Q:$Q,'Order Details'!$E:$E,"Yes",'Order Details'!$I:$I,$Q12,'Order Details'!$F:$F,'Item Summary'!U$4)-F12 -> 0 | V12: =SUMIFS('Order Details'!$Q:$Q,'Order Details'!$E:$E,"Yes",'Order Details'!$I:$I,$Q12,'Order Details'!$F:$F,'Item Summary'!V$4)-G12 -> 600 | W12: =SUMIFS('Order Details'!$Q:$Q,'Order Details'!$E:$E,"Yes",'Order Details'!$I:$I,$Q12,'Order Details'!$F:$F,'Item Summary'!W$4)-H12 -> 0 | X12: =SUMIFS('Order Details'!$Q:$Q,'Order Details'!$E:$E,"Yes",'Order Details'!$I:$I,$Q12,'Order Details'!$F:$F,'Item Summary'!X$4)-I12 -> 0 | Y12: =SUMIFS('Order Details'!$Q:$Q,'Order Details'!$E:$E,"Yes",'Order Details'!$I:$I,$Q12,'Order Details'!$F:$F,'Item Summary'!Y$4)-J12 -> 0 | Z12: =SUMIFS('Order Details'!$Q:$Q,'Order Details'!$E:$E,"Yes",'Order Details'!$I:$I,$Q12,'Order Details'!$F:$F,'Item Summary'!Z$4)-K12 -> 0 | ... AB12: =SUMIFS('Order Details'!$Q:$Q,'Order Details'!$E:$E,"Yes",'Order Details'!$I:$I,$Q12,'Order Details'!$F:$F,'Item Summary'!AB$4)-M12 -> 0 | AC12: =SUM(S12:AB12) -> 600
B13: 709355 | C13: =VLOOKUP($B13,'Pricing Table - eff 27-Jan-2026'!$A:$L,9,FALSE)&""" "&VLOOKUP($B13,'Pricing Table - eff 27-Jan-2026'!$A:$L,12,FALSE) -> 90.5" GLOSSY WHITE | D13: =SUMIFS('Order Details'!$Q:$Q,'Order Details'!$E:$E,"Yes",'Order Details'!$I:$I,'Item Summary'!$B13,'Order Details'!$F:$F,'Item Summary'!D$4,'Order Details'!$C:$C,"PO Received")+SUMIFS('Order Details'!$Q:$Q,'Order Details'!$E:$E,"Yes",'Order Details'!$I:$I,'Item Summary'!$B13,'Order Details'!$F:$F,'Item Summary'!D$4,'Order Details'!$C:$C,"Proforma Invoice Sent")+SUMIFS('Order Details'!$Q:$Q,'Order Details'!$E:$E,"Yes",'Order Details'!$I:$I,'Item Summary'!$B13,'Order Details'!$F:$F,'Item Summary'!D$4,'Order Details'!$C:$C,"Downpayment Received")+SUMIFS('Order Details'!$Q:$Q,'Order Details'!$E:$E,"Yes",'Order Details'!$I:$I,'Item Summary'!$B13,'Order Details'!$F:$F,'Item Summary'!D$4,'Order Details'!$C:$C,"In Production") -> 0 | E13: =SUMIFS('Order Details'!$Q:$Q,'Order Details'!$E:$E,"Yes",'Order Details'!$I:$I,'Item Summary'!$B13,'Order Details'!$F:$F,'Item Summary'!E$4,'Order Details'!$C:$C,"PO Received")+SUMIFS('Order Details'!$Q:$Q,'Order Details'!$E:$E,"Yes",'Order Details'!$I:$I,'Item Summary'!$B13,'Order Details'!$F:$F,'Item Summary'!E$4,'Order Details'!$C:$C,"Proforma Invoice Sent")+SUMIFS('Order Details'!$Q:$Q,'Order Details'!$E:$E,"Yes",'Order Details'!$I:$I,'Item Summary'!$B13,'Order Details'!$F:$F,'Item Summary'!E$4,'Order Details'!$C:$C,"Downpayment Received")+SUMIFS('Order Details'!$Q:$Q,'Order Details'!$E:$E,"Yes",'Order Details'!$I:$I,'Item Summary'!$B13,'Order Details'!$F:$F,'Item Summary'!E$4,'Order Details'!$C:$C,"In Production") -> 1200 | F13: =SUMIFS('Order Details'!$Q:$Q,'Order Details'!$E:$E,"Yes",'Order Details'!$I:$I,'Item Summary'!$B13,'Order Details'!$F:$F,'Item Summary'!F$4,'Order Details'!$C:$C,"PO Received")+SUMIFS('Order Details'!$Q:$Q,'Order Details'!$E:$E,"Yes",'Order Details'!$I:$I,'Item Summary'!$B13,'Order Details'!$F:$F,'Item Summary'!F$4,'Order Details'!$C:$C,"Proforma Invoice Sent")+SUMIFS('Order Details'!$Q:$Q,'Order Details'!$E:$E,"Yes",'Order Details'!$I:$I,'Item Summary'!$B13,'Order Details'!$F:$F,'Item Summary'!F$4,'Order Details'!$C:$C,"Downpayment Received")+SUMIFS('Order Details'!$Q:$Q,'Order Details'!$E:$E,"Yes",'Order Details'!$I:$I,'Item Summary'!$B13,'Order Details'!$F:$F,'Item Summary'!F$4,'Order Details'!$C:$C,"In Production") -> 1200 | G13: =SUMIFS('Order Details'!$Q:$Q,'Order Details'!$E:$E,"Yes",'Order Details'!$I:$I,'Item Summary'!$B13,'Order Details'!$F:$F,'Item Summary'!G$4,'Order Details'!$C:$C,"PO Received")+SUMIFS('Order Details'!$Q:$Q,'Order Details'!$E:$E,"Yes",'Order Details'!$I:$I,'Item Summary'!$B13,'Order Details'!$F:$F,'Item Summary'!G$4,'Order Details'!$C:$C,"Proforma Invoice Sent")+SUMIFS('Order Details'!$Q:$Q,'Order Details'!$E:$E,"Yes",'Order Details'!$I:$I,'Item Summary'!$B13,'Order Details'!$F:$F,'Item Summary'!G$4,'Order Details'!$C:$C,"Downpayment Received")+SUMIFS('Order Details'!$Q:$Q,'Order Details'!$E:$E,"Yes",'Order Details'!$I:$I,'Item Summary'!$B13,'Order Details'!$F:$F,'Item Summary'!G$4,'Order Details'!$C:$C,"In Production") -> 2000 | H13: =SUMIFS('Order Details'!$Q:$Q,'Order Details'!$E:$E,"Yes",'Order Details'!$I:$I,'Item Summary'!$B13,'Order Details'!$F:$F,'Item Summary'!H$4,'Order Details'!$C:$C,"PO Received")+SUMIFS('Order Details'!$Q:$Q,'Order Details'!$E:$E,"Yes",'Order Details'!$I:$I,'Item Summary'!$B13,'Order Details'!$F:$F,'Item Summary'!H$4,'Order Details'!$C:$C,"Proforma Invoice Sent")+SUMIFS('Order Details'!$Q:$Q,'Order Details'!$E:$E,"Yes",'Order Details'!$I:$I,'Item Summary'!$B13,'Order Details'!$F:$F,'Item Summary'!H$4,'Order Details'!$C:$C,"Downpayment Received")+SUMIFS('Order Details'!$Q:$Q,'Order Details'!$E:$E,"Yes",'Order Details'!$I:$I,'Item Summary'!$B13,'Order Details'!$F:$F,'Item Summary'!H$4,'Order Details'!$C:$C,"In Production") -> 1800 | I13: =SUMIFS('Order Details'!$Q:$Q,'Order Details'!$E:$E,"Yes",'Order Details'!$I:$I,'Item Summary'!$B13,'Order Details'!$F:$F,'Item Summary'!I$4,'Order Details'!$C:$C,"PO Received")+SUMIFS('Order Details'!$Q:$Q,'Order Details'!$E:$E,"Yes",'Order Details'!$I:$I,'Item Summary'!$B13,'Order Details'!$F:$F,'Item Summary'!I$4,'Order Details'!$C:$C,"Proforma Invoice Sent")+SUMIFS('Order Details'!$Q:$Q,'Order Details'!$E:$E,"Yes",'Order Details'!$I:$I,'Item Summary'!$B13,'Order Details'!$F:$F,'Item Summary'!I$4,'Order Details'!$C:$C,"Downpayment Received")+SUMIFS('Order Details'!$Q:$Q,'Order Details'!$E:$E,"Yes",'Order Details'!$I:$I,'Item Summary'!$B13,'Order Details'!$F:$F,'Item Summary'!I$4,'Order Details'!$C:$C,"In Production") -> 800 | J13: =SUMIFS('Order Details'!$Q:$Q,'Order Details'!$E:$E,"Yes",'Order Details'!$I:$I,'Item Summary'!$B13,'Order Details'!$F:$F,'Item Summary'!J$4,'Order Details'!$C:$C,"PO Received")+SUMIFS('Order Details'!$Q:$Q,'Order Details'!$E:$E,"Yes",'Order Details'!$I:$I,'Item Summary'!$B13,'Order Details'!$F:$F,'Item Summary'!J$4,'Order Details'!$C:$C,"Proforma Invoice Sent")+SUMIFS('Order Details'!$Q:$Q,'Order Details'!$E:$E,"Yes",'Order Details'!$I:$I,'Item Summary'!$B13,'Order Details'!$F:$F,'Item Summary'!J$4,'Order Details'!$C:$C,"Downpayment Received")+SUMIFS('Order Details'!$Q:$Q,'Order Details'!$E:$E,"Yes",'Order Details'!$I:$I,'Item Summary'!$B13,'Order Details'!$F:$F,'Item Summary'!J$4,'Order Details'!$C:$C,"In Production") -> 0 | K13: =SUMIFS('Order Details'!$Q:$Q,'Order Details'!$E:$E,"Yes",'Order Details'!$I:$I,'Item Summary'!$B13,'Order Details'!$F:$F,'Item Summary'!K$4,'Order Details'!$C:$C,"PO Received")+SUMIFS('Order Details'!$Q:$Q,'Order Details'!$E:$E,"Yes",'Order Details'!$I:$I,'Item Summary'!$B13,'Order Details'!$F:$F,'Item Summary'!K$4,'Order Details'!$C:$C,"Proforma Invoice Sent")+SUMIFS('Order Details'!$Q:$Q,'Order Details'!$E:$E,"Yes",'Order Details'!$I:$I,'Item Summary'!$B13,'Order Details'!$F:$F,'Item Summary'!K$4,'Order Details'!$C:$C,"Downpayment Received")+SUMIFS('Order Details'!$Q:$Q,'Order Details'!$E:$E,"Yes",'Order Details'!$I:$I,'Item Summary'!$B13,'Order Details'!$F:$F,'Item Summary'!K$4,'Order Details'!$C:$C,"In Production") -> 0 | ... M13: =SUMIFS('Order Details'!$Q:$Q,'Order Details'!$E:$E,"Yes",'Order Details'!$I:$I,'Item Summary'!$B13,'Order Details'!$F:$F,'Item Summary'!M$4,'Order Details'!$C:$C,"PO Received")+SUMIFS('Order Details'!$Q:$Q,'Order Details'!$E:$E,"Yes",'Order Details'!$I:$I,'Item Summary'!$B13,'Order Details'!$F:$F,'Item Summary'!M$4,'Order Details'!$C:$C,"Proforma Invoice Sent")+SUMIFS('Order Details'!$Q:$Q,'Order Details'!$E:$E,"Yes",'Order Details'!$I:$I,'Item Summary'!$B13,'Order Details'!$F:$F,'Item Summary'!M$4,'Order Details'!$C:$C,"Downpayment Received")+SUMIFS('Order Details'!$Q:$Q,'Order Details'!$E:$E,"Yes",'Order Details'!$I:$I,'Item Summary'!$B13,'Order Details'!$F:$F,'Item Summary'!M$4,'Order Details'!$C:$C,"In Production") -> 0 | N13: =SUM(D13:M13) -> 9800 | Q13: 709355 | R13: =VLOOKUP($Q13,'Pricing Table - eff 27-Jan-2026'!$A:$L,9,FALSE)&""" "&VLOOKUP($Q13,'Pricing Table - eff 27-Jan-2026'!$A:$L,12,FALSE) -> 90.5" GLOSSY WHITE | S13: =SUMIFS('Order Details'!$Q:$Q,'Order Details'!$E:$E,"Yes",'Order Details'!$I:$I,$Q13,'Order Details'!$F:$F,'Item Summary'!S$4)-D13 -> 0 | T13: =SUMIFS('Order Details'!$Q:$Q,'Order Details'!$E:$E,"Yes",'Order Details'!$I:$I,$Q13,'Order Details'!$F:$F,'Item Summary'!T$4)-E13 -> 2400 | U13: =SUMIFS('Order Details'!$Q:$Q,'Order Details'!$E:$E,"Yes",'Order Details'!$I:$I,$Q13,'Order Details'!$F:$F,'Item Summary'!U$4)-F13 -> 1600 | V13: =SUMIFS('Order Details'!$Q:$Q,'Order Details'!$E:$E,"Yes",'Order Details'!$I:$I,$Q13,'Order Details'!$F:$F,'Item Summary'!V$4)-G13 -> 2400 | W13: =SUMIFS('Order Details'!$Q:$Q,'Order Details'!$E:$E,"Yes",'Order Details'!$I:$I,$Q13,'Order Details'!$F:$F,'Item Summary'!W$4)-H13 -> 2000 | X13: =SUMIFS('Order Details'!$Q:$Q,'Order Details'!$E:$E,"Yes",'Order Details'!$I:$I,$Q13,'Order Details'!$F:$F,'Item Summary'!X$4)-I13 -> 0 | Y13: =SUMIFS('Order Details'!$Q:$Q,'Order Details'!$E:$E,"Yes",'Order Details'!$I:$I,$Q13,'Order Details'!$F:$F,'Item Summary'!Y$4)-J13 -> 0 | Z13: =SUMIFS('Order Details'!$Q:$Q,'Order Details'!$E:$E,"Yes",'Order Details'!$I:$I,$Q13,'Order Details'!$F:$F,'Item Summary'!Z$4)-K13 -> 0 | ... AB13: =SUMIFS('Order Details'!$Q:$Q,'Order Details'!$E:$E,"Yes",'Order Details'!$I:$I,$Q13,'Order Details'!$F:$F,'Item Summary'!AB$4)-M13 -> 0 | AC13: =SUM(S13:AB13) -> 8400
B14: 694436 | C14: =VLOOKUP($B14,'Pricing Table - eff 27-Jan-2026'!$A:$L,9,FALSE)&""" "&VLOOKUP($B14,'Pricing Table - eff 27-Jan-2026'!$A:$L,12,FALSE) -> 96" GLOSSY WHITE | D14: =SUMIFS('Order Details'!$Q:$Q,'Order Details'!$E:$E,"Yes",'Order Details'!$I:$I,'Item Summary'!$B14,'Order Details'!$F:$F,'Item Summary'!D$4,'Order Details'!$C:$C,"PO Received")+SUMIFS('Order Details'!$Q:$Q,'Order Details'!$E:$E,"Yes",'Order Details'!$I:$I,'Item Summary'!$B14,'Order Details'!$F:$F,'Item Summary'!D$4,'Order Details'!$C:$C,"Proforma Invoice Sent")+SUMIFS('Order Details'!$Q:$Q,'Order Details'!$E:$E,"Yes",'Order Details'!$I:$I,'Item Summary'!$B14,'Order Details'!$F:$F,'Item Summary'!D$4,'Order Details'!$C:$C,"Downpayment Received")+SUMIFS('Order Details'!$Q:$Q,'Order Details'!$E:$E,"Yes",'Order Details'!$I:$I,'Item Summary'!$B14,'Order Details'!$F:$F,'Item Summary'!D$4,'Order Details'!$C:$C,"In Production") -> 1400 | E14: =SUMIFS('Order Details'!$Q:$Q,'Order Details'!$E:$E,"Yes",'Order Details'!$I:$I,'Item Summary'!$B14,'Order Details'!$F:$F,'Item Summary'!E$4,'Order Details'!$C:$C,"PO Received")+SUMIFS('Order Details'!$Q:$Q,'Order Details'!$E:$E,"Yes",'Order Details'!$I:$I,'Item Summary'!$B14,'Order Details'!$F:$F,'Item Summary'!E$4,'Order Details'!$C:$C,"Proforma Invoice Sent")+SUMIFS('Order Details'!$Q:$Q,'Order Details'!$E:$E,"Yes",'Order Details'!$I:$I,'Item Summary'!$B14,'Order Details'!$F:$F,'Item Summary'!E$4,'Order Details'!$C:$C,"Downpayment Received")+SUMIFS('Order Details'!$Q:$Q,'Order Details'!$E:$E,"Yes",'Order Details'!$I:$I,'Item Summary'!$B14,'Order Details'!$F:$F,'Item Summary'!E$4,'Order Details'!$C:$C,"In Production") -> 600 | F14: =SUMIFS('Order Details'!$Q:$Q,'Order Details'!$E:$E,"Yes",'Order Details'!$I:$I,'Item Summary'!$B14,'Order Details'!$F:$F,'Item Summary'!F$4,'Order Details'!$C:$C,"PO Received")+SUMIFS('Order Details'!$Q:$Q,'Order Details'!$E:$E,"Yes",'Order Details'!$I:$I,'Item Summary'!$B14,'Order Details'!$F:$F,'Item Summary'!F$4,'Order Details'!$C:$C,"Proforma Invoice Sent")+SUMIFS('Order Details'!$Q:$Q,'Order Details'!$E:$E,"Yes",'Order Details'!$I:$I,'Item Summary'!$B14,'Order Details'!$F:$F,'Item Summary'!F$4,'Order Details'!$C:$C,"Downpayment Received")+SUMIFS('Order Details'!$Q:$Q,'Order Details'!$E:$E,"Yes",'Order Details'!$I:$I,'Item Summary'!$B14,'Order Details'!$F:$F,'Item Summary'!F$4,'Order Details'!$C:$C,"In Production") -> 3200 | G14: =SUMIFS('Order Details'!$Q:$Q,'Order Details'!$E:$E,"Yes",'Order Details'!$I:$I,'Item Summary'!$B14,'Order Details'!$F:$F,'Item Summary'!G$4,'Order Details'!$C:$C,"PO Received")+SUMIFS('Order Details'!$Q:$Q,'Order Details'!$E:$E,"Yes",'Order Details'!$I:$I,'Item Summary'!$B14,'Order Details'!$F:$F,'Item Summary'!G$4,'Order Details'!$C:$C,"Proforma Invoice Sent")+SUMIFS('Order Details'!$Q:$Q,'Order Details'!$E:$E,"Yes",'Order Details'!$I:$I,'Item Summary'!$B14,'Order Details'!$F:$F,'Item Summary'!G$4,'Order Details'!$C:$C,"Downpayment Received")+SUMIFS('Order Details'!$Q:$Q,'Order Details'!$E:$E,"Yes",'Order Details'!$I:$I,'Item Summary'!$B14,'Order Details'!$F:$F,'Item Summary'!G$4,'Order Details'!$C:$C,"In Production") -> 4800 | H14: =SUMIFS('Order Details'!$Q:$Q,'Order Details'!$E:$E,"Yes",'Order Details'!$I:$I,'Item Summary'!$B14,'Order Details'!$F:$F,'Item Summary'!H$4,'Order Details'!$C:$C,"PO Received")+SUMIFS('Order Details'!$Q:$Q,'Order Details'!$E:$E,"Yes",'Order Details'!$I:$I,'Item Summary'!$B14,'Order Details'!$F:$F,'Item Summary'!H$4,'Order Details'!$C:$C,"Proforma Invoice Sent")+SUMIFS('Order Details'!$Q:$Q,'Order Details'!$E:$E,"Yes",'Order Details'!$I:$I,'Item Summary'!$B14,'Order Details'!$F:$F,'Item Summary'!H$4,'Order Details'!$C:$C,"Downpayment Received")+SUMIFS('Order Details'!$Q:$Q,'Order Details'!$E:$E,"Yes",'Order Details'!$I:$I,'Item Summary'!$B14,'Order Details'!$F:$F,'Item Summary'!H$4,'Order Details'!$C:$C,"In Production") -> 4400 | I14: =SUMIFS('Order Details'!$Q:$Q,'Order Details'!$E:$E,"Yes",'Order Details'!$I:$I,'Item Summary'!$B14,'Order Details'!$F:$F,'Item Summary'!I$4,'Order Details'!$C:$C,"PO Received")+SUMIFS('Order Details'!$Q:$Q,'Order Details'!$E:$E,"Yes",'Order Details'!$I:$I,'Item Summary'!$B14,'Order Details'!$F:$F,'Item Summary'!I$4,'Order Details'!$C:$C,"Proforma Invoice Sent")+SUMIFS('Order Details'!$Q:$Q,'Order Details'!$E:$E,"Yes",'Order Details'!$I:$I,'Item Summary'!$B14,'Order Details'!$F:$F,'Item Summary'!I$4,'Order Details'!$C:$C,"Downpayment Received")+SUMIFS('Order Details'!$Q:$Q,'Order Details'!$E:$E,"Yes",'Order Details'!$I:$I,'Item Summary'!$B14,'Order Details'!$F:$F,'Item Summary'!I$4,'Order Details'!$C:$C,"In Production") -> 7400 | J14: =SUMIFS('Order Details'!$Q:$Q,'Order Details'!$E:$E,"Yes",'Order Details'!$I:$I,'Item Summary'!$B14,'Order Details'!$F:$F,'Item Summary'!J$4,'Order Details'!$C:$C,"PO Received")+SUMIFS('Order Details'!$Q:$Q,'Order Details'!$E:$E,"Yes",'Order Details'!$I:$I,'Item Summary'!$B14,'Order Details'!$F:$F,'Item Summary'!J$4,'Order Details'!$C:$C,"Proforma Invoice Sent")+SUMIFS('Order Details'!$Q:$Q,'Order Details'!$E:$E,"Yes",'Order Details'!$I:$I,'Item Summary'!$B14,'Order Details'!$F:$F,'Item Summary'!J$4,'Order Details'!$C:$C,"Downpayment Received")+SUMIFS('Order Details'!$Q:$Q,'Order Details'!$E:$E,"Yes",'Order Details'!$I:$I,'Item Summary'!$B14,'Order Details'!$F:$F,'Item Summary'!J$4,'Order Details'!$C:$C,"In Production") -> 8600 | K14: =SUMIFS('Order Details'!$Q:$Q,'Order Details'!$E:$E,"Yes",'Order Details'!$I:$I,'Item Summary'!$B14,'Order Details'!$F:$F,'Item Summary'!K$4,'Order Details'!$C:$C,"PO Received")+SUMIFS('Order Details'!$Q:$Q,'Order Details'!$E:$E,"Yes",'Order Details'!$I:$I,'Item Summary'!$B14,'Order Details'!$F:$F,'Item Summary'!K$4,'Order Details'!$C:$C,"Proforma Invoice Sent")+SUMIFS('Order Details'!$Q:$Q,'Order Details'!$E:$E,"Yes",'Order Details'!$I:$I,'Item Summary'!$B14,'Order Details'!$F:$F,'Item Summary'!K$4,'Order Details'!$C:$C,"Downpayment Received")+SUMIFS('Order Details'!$Q:$Q,'Order Details'!$E:$E,"Yes",'Order Details'!$I:$I,'Item Summary'!$B14,'Order Details'!$F:$F,'Item Summary'!K$4,'Order Details'!$C:$C,"In Production") -> 0 | ... M14: =SUMIFS('Order Details'!$Q:$Q,'Order Details'!$E:$E,"Yes",'Order Details'!$I:$I,'Item Summary'!$B14,'Order Details'!$F:$F,'Item Summary'!M$4,'Order Details'!$C:$C,"PO Received")+SUMIFS('Order Details'!$Q:$Q,'Order Details'!$E:$E,"Yes",'Order Details'!$I:$I,'Item Summary'!$B14,'Order Details'!$F:$F,'Item Summary'!M$4,'Order Details'!$C:$C,"Proforma Invoice Sent")+SUMIFS('Order Details'!$Q:$Q,'Order Details'!$E:$E,"Yes",'Order Details'!$I:$I,'Item Summary'!$B14,'Order Details'!$F:$F,'Item Summary'!M$4,'Order Details'!$C:$C,"Downpayment Received")+SUMIFS('Order Details'!$Q:$Q,'Order Details'!$E:$E,"Yes",'Order Details'!$I:$I,'Item Summary'!$B14,'Order Details'!$F:$F,'Item Summary'!M$4,'Order Details'!$C:$C,"In Production") -> 2800 | N14: =SUM(D14:M14) -> 38200 | Q14: 694436 | R14: =VLOOKUP($Q14,'Pricing Table - eff 27-Jan-2026'!$A:$L,9,FALSE)&""" "&VLOOKUP($Q14,'Pricing Table - eff 27-Jan-2026'!$A:$L,12,FALSE) -> 96" GLOSSY WHITE | S14: =SUMIFS('Order Details'!$Q:$Q,'Order Details'!$E:$E,"Yes",'Order Details'!$I:$I,$Q14,'Order Details'!$F:$F,'Item Summary'!S$4)-D14 -> 800 | T14: =SUMIFS('Order Details'!$Q:$Q,'Order Details'!$E:$E,"Yes",'Order Details'!$I:$I,$Q14,'Order Details'!$F:$F,'Item Summary'!T$4)-E14 -> 2800 | U14: =SUMIFS('Order Details'!$Q:$Q,'Order Details'!$E:$E,"Yes",'Order Details'!$I:$I,$Q14,'Order Details'!$F:$F,'Item Summary'!U$4)-F14 -> 1400 | V14: =SUMIFS('Order Details'!$Q:$Q,'Order Details'!$E:$E,"Yes",'Order Details'!$I:$I,$Q14,'Order Details'!$F:$F,'Item Summary'!V$4)-G14 -> 4000 | W14: =SUMIFS('Order Details'!$Q:$Q,'Order Details'!$E:$E,"Yes",'Order Details'!$I:$I,$Q14,'Order Details'!$F:$F,'Item Summary'!W$4)-H14 -> 6600 | X14: =SUMIFS('Order Details'!$Q:$Q,'Order Details'!$E:$E,"Yes",'Order Details'!$I:$I,$Q14,'Order Details'!$F:$F,'Item Summary'!X$4)-I14 -> 800 | Y14: =SUMIFS('Order Details'!$Q:$Q,'Order Details'!$E:$E,"Yes",'Order Details'!$I:$I,$Q14,'Order Details'!$F:$F,'Item Summary'!Y$4)-J14 -> 400 | Z14: =SUMIFS('Order Details'!$Q:$Q,'Order Details'!$E:$E,"Yes",'Order Details'!$I:$I,$Q14,'Order Details'!$F:$F,'Item Summary'!Z$4)-K14 -> 5600 | ... AB14: =SUMIFS('Order Details'!$Q:$Q,'Order Details'!$E:$E,"Yes",'Order Details'!$I:$I,$Q14,'Order Details'!$F:$F,'Item Summary'!AB$4)-M14 -> 2800 | AC14: =SUM(S14:AB14) -> 25200
B15: 694437 | C15: =VLOOKUP($B15,'Pricing Table - eff 27-Jan-2026'!$A:$L,9,FALSE)&""" "&VLOOKUP($B15,'Pricing Table - eff 27-Jan-2026'!$A:$L,12,FALSE) -> 108" GLOSSY WHITE | D15: =SUMIFS('Order Details'!$Q:$Q,'Order Details'!$E:$E,"Yes",'Order Details'!$I:$I,'Item Summary'!$B15,'Order Details'!$F:$F,'Item Summary'!D$4,'Order Details'!$C:$C,"PO Received")+SUMIFS('Order Details'!$Q:$Q,'Order Details'!$E:$E,"Yes",'Order Details'!$I:$I,'Item Summary'!$B15,'Order Details'!$F:$F,'Item Summary'!D$4,'Order Details'!$C:$C,"Proforma Invoice Sent")+SUMIFS('Order Details'!$Q:$Q,'Order Details'!$E:$E,"Yes",'Order Details'!$I:$I,'Item Summary'!$B15,'Order Details'!$F:$F,'Item Summary'!D$4,'Order Details'!$C:$C,"Downpayment Received")+SUMIFS('Order Details'!$Q:$Q,'Order Details'!$E:$E,"Yes",'Order Details'!$I:$I,'Item Summary'!$B15,'Order Details'!$F:$F,'Item Summary'!D$4,'Order Details'!$C:$C,"In Production") -> 1000 | E15: =SUMIFS('Order Details'!$Q:$Q,'Order Details'!$E:$E,"Yes",'Order Details'!$I:$I,'Item Summary'!$B15,'Order Details'!$F:$F,'Item Summary'!E$4,'Order Details'!$C:$C,"PO Received")+SUMIFS('Order Details'!$Q:$Q,'Order Details'!$E:$E,"Yes",'Order Details'!$I:$I,'Item Summary'!$B15,'Order Details'!$F:$F,'Item Summary'!E$4,'Order Details'!$C:$C,"Proforma Invoice Sent")+SUMIFS('Order Details'!$Q:$Q,'Order Details'!$E:$E,"Yes",'Order Details'!$I:$I,'Item Summary'!$B15,'Order Details'!$F:$F,'Item Summary'!E$4,'Order Details'!$C:$C,"Downpayment Received")+SUMIFS('Order Details'!$Q:$Q,'Order Details'!$E:$E,"Yes",'Order Details'!$I:$I,'Item Summary'!$B15,'Order Details'!$F:$F,'Item Summary'!E$4,'Order Details'!$C:$C,"In Production") -> 0 | F15: =SUMIFS('Order Details'!$Q:$Q,'Order Details'!$E:$E,"Yes",'Order Details'!$I:$I,'Item Summary'!$B15,'Order Details'!$F:$F,'Item Summary'!F$4,'Order Details'!$C:$C,"PO Received")+SUMIFS('Order Details'!$Q:$Q,'Order Details'!$E:$E,"Yes",'Order Details'!$I:$I,'Item Summary'!$B15,'Order Details'!$F:$F,'Item Summary'!F$4,'Order Details'!$C:$C,"Proforma Invoice Sent")+SUMIFS('Order Details'!$Q:$Q,'Order Details'!$E:$E,"Yes",'Order Details'!$I:$I,'Item Summary'!$B15,'Order Details'!$F:$F,'Item Summary'!F$4,'Order Details'!$C:$C,"Downpayment Received")+SUMIFS('Order Details'!$Q:$Q,'Order Details'!$E:$E,"Yes",'Order Details'!$I:$I,'Item Summary'!$B15,'Order Details'!$F:$F,'Item Summary'!F$4,'Order Details'!$C:$C,"In Production") -> 3300 | G15: =SUMIFS('Order Details'!$Q:$Q,'Order Details'!$E:$E,"Yes",'Order Details'!$I:$I,'Item Summary'!$B15,'Order Details'!$F:$F,'Item Summary'!G$4,'Order Details'!$C:$C,"PO Received")+SUMIFS('Order Details'!$Q:$Q,'Order Details'!$E:$E,"Yes",'Order Details'!$I:$I,'Item Summary'!$B15,'Order Details'!$F:$F,'Item Summary'!G$4,'Order Details'!$C:$C,"Proforma Invoice Sent")+SUMIFS('Order Details'!$Q:$Q,'Order Details'!$E:$E,"Yes",'Order Details'!$I:$I,'Item Summary'!$B15,'Order Details'!$F:$F,'Item Summary'!G$4,'Order Details'!$C:$C,"Downpayment Received")+SUMIFS('Order Details'!$Q:$Q,'Order Details'!$E:$E,"Yes",'Order Details'!$I:$I,'Item Summary'!$B15,'Order Details'!$F:$F,'Item Summary'!G$4,'Order Details'!$C:$C,"In Production") -> 1200 | H15: =SUMIFS('Order Details'!$Q:$Q,'Order Details'!$E:$E,"Yes",'Order Details'!$I:$I,'Item Summary'!$B15,'Order Details'!$F:$F,'Item Summary'!H$4,'Order Details'!$C:$C,"PO Received")+SUMIFS('Order Details'!$Q:$Q,'Order Details'!$E:$E,"Yes",'Order Details'!$I:$I,'Item Summary'!$B15,'Order Details'!$F:$F,'Item Summary'!H$4,'Order Details'!$C:$C,"Proforma Invoice Sent")+SUMIFS('Order Details'!$Q:$Q,'Order Details'!$E:$E,"Yes",'Order Details'!$I:$I,'Item Summary'!$B15,'Order Details'!$F:$F,'Item Summary'!H$4,'Order Details'!$C:$C,"Downpayment Received")+SUMIFS('Order Details'!$Q:$Q,'Order Details'!$E:$E,"Yes",'Order Details'!$I:$I,'Item Summary'!$B15,'Order Details'!$F:$F,'Item Summary'!H$4,'Order Details'!$C:$C,"In Production") -> 3000 | I15: =SUMIFS('Order Details'!$Q:$Q,'Order Details'!$E:$E,"Yes",'Order Details'!$I:$I,'Item Summary'!$B15,'Order Details'!$F:$F,'Item Summary'!I$4,'Order Details'!$C:$C,"PO Received")+SUMIFS('Order Details'!$Q:$Q,'Order Details'!$E:$E,"Yes",'Order Details'!$I:$I,'Item Summary'!$B15,'Order Details'!$F:$F,'Item Summary'!I$4,'Order Details'!$C:$C,"Proforma Invoice Sent")+SUMIFS('Order Details'!$Q:$Q,'Order Details'!$E:$E,"Yes",'Order Details'!$I:$I,'Item Summary'!$B15,'Order Details'!$F:$F,'Item Summary'!I$4,'Order Details'!$C:$C,"Downpayment Received")+SUMIFS('Order Details'!$Q:$Q,'Order Details'!$E:$E,"Yes",'Order Details'!$I:$I,'Item Summary'!$B15,'Order Details'!$F:$F,'Item Summary'!I$4,'Order Details'!$C:$C,"In Production") -> 2800 | J15: =SUMIFS('Order Details'!$Q:$Q,'Order Details'!$E:$E,"Yes",'Order Details'!$I:$I,'Item Summary'!$B15,'Order Details'!$F:$F,'Item Summary'!J$4,'Order Details'!$C:$C,"PO Received")+SUMIFS('Order Details'!$Q:$Q,'Order Details'!$E:$E,"Yes",'Order Details'!$I:$I,'Item Summary'!$B15,'Order Details'!$F:$F,'Item Summary'!J$4,'Order Details'!$C:$C,"Proforma Invoice Sent")+SUMIFS('Order Details'!$Q:$Q,'Order Details'!$E:$E,"Yes",'Order Details'!$I:$I,'Item Summary'!$B15,'Order Details'!$F:$F,'Item Summary'!J$4,'Order Details'!$C:$C,"Downpayment Received")+SUMIFS('Order Details'!$Q:$Q,'Order Details'!$E:$E,"Yes",'Order Details'!$I:$I,'Item Summary'!$B15,'Order Details'!$F:$F,'Item Summary'!J$4,'Order Details'!$C:$C,"In Production") -> 1400 | K15: =SUMIFS('Order Details'!$Q:$Q,'Order Details'!$E:$E,"Yes",'Order Details'!$I:$I,'Item Summary'!$B15,'Order Details'!$F:$F,'Item Summary'!K$4,'Order Details'!$C:$C,"PO Received")+SUMIFS('Order Details'!$Q:$Q,'Order Details'!$E:$E,"Yes",'Order Details'!$I:$I,'Item Summary'!$B15,'Order Details'!$F:$F,'Item Summary'!K$4,'Order Details'!$C:$C,"Proforma Invoice Sent")+SUMIFS('Order Details'!$Q:$Q,'Order Details'!$E:$E,"Yes",'Order Details'!$I:$I,'Item Summary'!$B15,'Order Details'!$F:$F,'Item Summary'!K$4,'Order Details'!$C:$C,"Downpayment Received")+SUMIFS('Order Details'!$Q:$Q,'Order Details'!$E:$E,"Yes",'Order Details'!$I:$I,'Item Summary'!$B15,'Order Details'!$F:$F,'Item Summary'!K$4,'Order Details'!$C:$C,"In Production") -> 0 | ... M15: =SUMIFS('Order Details'!$Q:$Q,'Order Details'!$E:$E,"Yes",'Order Details'!$I:$I,'Item Summary'!$B15,'Order Details'!$F:$F,'Item Summary'!M$4,'Order Details'!$C:$C,"PO Received")+SUMIFS('Order Details'!$Q:$Q,'Order Details'!$E:$E,"Yes",'Order Details'!$I:$I,'Item Summary'!$B15,'Order Details'!$F:$F,'Item Summary'!M$4,'Order Details'!$C:$C,"Proforma Invoice Sent")+SUMIFS('Order Details'!$Q:$Q,'Order Details'!$E:$E,"Yes",'Order Details'!$I:$I,'Item Summary'!$B15,'Order Details'!$F:$F,'Item Summary'!M$4,'Order Details'!$C:$C,"Downpayment Received")+SUMIFS('Order Details'!$Q:$Q,'Order Details'!$E:$E,"Yes",'Order Details'!$I:$I,'Item Summary'!$B15,'Order Details'!$F:$F,'Item Summary'!M$4,'Order Details'!$C:$C,"In Production") -> 0 | N15: =SUM(D15:M15) -> 15500 | Q15: 694437 | R15: =VLOOKUP($Q15,'Pricing Table - eff 27-Jan-2026'!$A:$L,9,FALSE)&""" "&VLOOKUP($Q15,'Pricing Table - eff 27-Jan-2026'!$A:$L,12,FALSE) -> 108" GLOSSY WHITE | S15: =SUMIFS('Order Details'!$Q:$Q,'Order Details'!$E:$E,"Yes",'Order Details'!$I:$I,$Q15,'Order Details'!$F:$F,'Item Summary'!S$4)-D15 -> 400 | T15: =SUMIFS('Order Details'!$Q:$Q,'Order Details'!$E:$E,"Yes",'Order Details'!$I:$I,$Q15,'Order Details'!$F:$F,'Item Summary'!T$4)-E15 -> 800 | U15: =SUMIFS('Order Details'!$Q:$Q,'Order Details'!$E:$E,"Yes",'Order Details'!$I:$I,$Q15,'Order Details'!$F:$F,'Item Summary'!U$4)-F15 -> 3150 | V15: =SUMIFS('Order Details'!$Q:$Q,'Order Details'!$E:$E,"Yes",'Order Details'!$I:$I,$Q15,'Order Details'!$F:$F,'Item Summary'!V$4)-G15 -> 3200 | W15: =SUMIFS('Order Details'!$Q:$Q,'Order Details'!$E:$E,"Yes",'Order Details'!$I:$I,$Q15,'Order Details'!$F:$F,'Item Summary'!W$4)-H15 -> 2400 | X15: =SUMIFS('Order Details'!$Q:$Q,'Order Details'!$E:$E,"Yes",'Order Details'!$I:$I,$Q15,'Order Details'!$F:$F,'Item Summary'!X$4)-I15 -> 0 | Y15: =SUMIFS('Order Details'!$Q:$Q,'Order Details'!$E:$E,"Yes",'Order Details'!$I:$I,$Q15,'Order Details'!$F:$F,'Item Summary'!Y$4)-J15 -> 1600 | Z15: =SUMIFS('Order Details'!$Q:$Q,'Order Details'!$E:$E,"Yes",'Order Details'!$I:$I,$Q15,'Order Details'!$F:$F,'Item Summary'!Z$4)-K15 -> 2400 | ... AB15: =SUMIFS('Order Details'!$Q:$Q,'Order Details'!$E:$E,"Yes",'Order Details'!$I:$I,$Q15,'Order Details'!$F:$F,'Item Summary'!AB$4)-M15 -> 2400 | AC15: =SUM(S15:AB15) -> 16350
B16: 694438 | C16: =VLOOKUP($B16,'Pricing Table - eff 27-Jan-2026'!$A:$L,9,FALSE)&""" "&VLOOKUP($B16,'Pricing Table - eff 27-Jan-2026'!$A:$L,12,FALSE) -> 144" GLOSSY WHITE | D16: =SUMIFS('Order Details'!$Q:$Q,'Order Details'!$E:$E,"Yes",'Order Details'!$I:$I,'Item Summary'!$B16,'Order Details'!$F:$F,'Item Summary'!D$4,'Order Details'!$C:$C,"PO Received")+SUMIFS('Order Details'!$Q:$Q,'Order Details'!$E:$E,"Yes",'Order Details'!$I:$I,'Item Summary'!$B16,'Order Details'!$F:$F,'Item Summary'!D$4,'Order Details'!$C:$C,"Proforma Invoice Sent")+SUMIFS('Order Details'!$Q:$Q,'Order Details'!$E:$E,"Yes",'Order Details'!$I:$I,'Item Summary'!$B16,'Order Details'!$F:$F,'Item Summary'!D$4,'Order Details'!$C:$C,"Downpayment Received")+SUMIFS('Order Details'!$Q:$Q,'Order Details'!$E:$E,"Yes",'Order Details'!$I:$I,'Item Summary'!$B16,'Order Details'!$F:$F,'Item Summary'!D$4,'Order Details'!$C:$C,"In Production") -> 0 | E16: =SUMIFS('Order Details'!$Q:$Q,'Order Details'!$E:$E,"Yes",'Order Details'!$I:$I,'Item Summary'!$B16,'Order Details'!$F:$F,'Item Summary'!E$4,'Order Details'!$C:$C,"PO Received")+SUMIFS('Order Details'!$Q:$Q,'Order Details'!$E:$E,"Yes",'Order Details'!$I:$I,'Item Summary'!$B16,'Order Details'!$F:$F,'Item Summary'!E$4,'Order Details'!$C:$C,"Proforma Invoice Sent")+SUMIFS('Order Details'!$Q:$Q,'Order Details'!$E:$E,"Yes",'Order Details'!$I:$I,'Item Summary'!$B16,'Order Details'!$F:$F,'Item Summary'!E$4,'Order Details'!$C:$C,"Downpayment Received")+SUMIFS('Order Details'!$Q:$Q,'Order Details'!$E:$E,"Yes",'Order Details'!$I:$I,'Item Summary'!$B16,'Order Details'!$F:$F,'Item Summary'!E$4,'Order Details'!$C:$C,"In Production") -> 0 | F16: =SUMIFS('Order Details'!$Q:$Q,'Order Details'!$E:$E,"Yes",'Order Details'!$I:$I,'Item Summary'!$B16,'Order Details'!$F:$F,'Item Summary'!F$4,'Order Details'!$C:$C,"PO Received")+SUMIFS('Order Details'!$Q:$Q,'Order Details'!$E:$E,"Yes",'Order Details'!$I:$I,'Item Summary'!$B16,'Order Details'!$F:$F,'Item Summary'!F$4,'Order Details'!$C:$C,"Proforma Invoice Sent")+SUMIFS('Order Details'!$Q:$Q,'Order Details'!$E:$E,"Yes",'Order Details'!$I:$I,'Item Summary'!$B16,'Order Details'!$F:$F,'Item Summary'!F$4,'Order Details'!$C:$C,"Downpayment Received")+SUMIFS('Order Details'!$Q:$Q,'Order Details'!$E:$E,"Yes",'Order Details'!$I:$I,'Item Summary'!$B16,'Order Details'!$F:$F,'Item Summary'!F$4,'Order Details'!$C:$C,"In Production") -> 600 | G16: =SUMIFS('Order Details'!$Q:$Q,'Order Details'!$E:$E,"Yes",'Order Details'!$I:$I,'Item Summary'!$B16,'Order Details'!$F:$F,'Item Summary'!G$4,'Order Details'!$C:$C,"PO Received")+SUMIFS('Order Details'!$Q:$Q,'Order Details'!$E:$E,"Yes",'Order Details'!$I:$I,'Item Summary'!$B16,'Order Details'!$F:$F,'Item Summary'!G$4,'Order Details'!$C:$C,"Proforma Invoice Sent")+SUMIFS('Order Details'!$Q:$Q,'Order Details'!$E:$E,"Yes",'Order Details'!$I:$I,'Item Summary'!$B16,'Order Details'!$F:$F,'Item Summary'!G$4,'Order Details'!$C:$C,"Downpayment Received")+SUMIFS('Order Details'!$Q:$Q,'Order Details'!$E:$E,"Yes",'Order Details'!$I:$I,'Item Summary'!$B16,'Order Details'!$F:$F,'Item Summary'!G$4,'Order Details'!$C:$C,"In Production") -> 0 | H16: =SUMIFS('Order Details'!$Q:$Q,'Order Details'!$E:$E,"Yes",'Order Details'!$I:$I,'Item Summary'!$B16,'Order Details'!$F:$F,'Item Summary'!H$4,'Order Details'!$C:$C,"PO Received")+SUMIFS('Order Details'!$Q:$Q,'Order Details'!$E:$E,"Yes",'Order Details'!$I:$I,'Item Summary'!$B16,'Order Details'!$F:$F,'Item Summary'!H$4,'Order Details'!$C:$C,"Proforma Invoice Sent")+SUMIFS('Order Details'!$Q:$Q,'Order Details'!$E:$E,"Yes",'Order Details'!$I:$I,'Item Summary'!$B16,'Order Details'!$F:$F,'Item Summary'!H$4,'Order Details'!$C:$C,"Downpayment Received")+SUMIFS('Order Details'!$Q:$Q,'Order Details'!$E:$E,"Yes",'Order Details'!$I:$I,'Item Summary'!$B16,'Order Details'!$F:$F,'Item Summary'!H$4,'Order Details'!$C:$C,"In Production") -> 1400 | I16: =SUMIFS('Order Details'!$Q:$Q,'Order Details'!$E:$E,"Yes",'Order Details'!$I:$I,'Item Summary'!$B16,'Order Details'!$F:$F,'Item Summary'!I$4,'Order Details'!$C:$C,"PO Received")+SUMIFS('Order Details'!$Q:$Q,'Order Details'!$E:$E,"Yes",'Order Details'!$I:$I,'Item Summary'!$B16,'Order Details'!$F:$F,'Item Summary'!I$4,'Order Details'!$C:$C,"Proforma Invoice Sent")+SUMIFS('Order Details'!$Q:$Q,'Order Details'!$E:$E,"Yes",'Order Details'!$I:$I,'Item Summary'!$B16,'Order Details'!$F:$F,'Item Summary'!I$4,'Order Details'!$C:$C,"Downpayment Received")+SUMIFS('Order Details'!$Q:$Q,'Order Details'!$E:$E,"Yes",'Order Details'!$I:$I,'Item Summary'!$B16,'Order Details'!$F:$F,'Item Summary'!I$4,'Order Details'!$C:$C,"In Production") -> 0 | J16: =SUMIFS('Order Details'!$Q:$Q,'Order Details'!$E:$E,"Yes",'Order Details'!$I:$I,'Item Summary'!$B16,'Order Details'!$F:$F,'Item Summary'!J$4,'Order Details'!$C:$C,"PO Received")+SUMIFS('Order Details'!$Q:$Q,'Order Details'!$E:$E,"Yes",'Order Details'!$I:$I,'Item Summary'!$B16,'Order Details'!$F:$F,'Item Summary'!J$4,'Order Details'!$C:$C,"Proforma Invoice Sent")+SUMIFS('Order Details'!$Q:$Q,'Order Details'!$E:$E,"Yes",'Order Details'!$I:$I,'Item Summary'!$B16,'Order Details'!$F:$F,'Item Summary'!J$4,'Order Details'!$C:$C,"Downpayment Received")+SUMIFS('Order Details'!$Q:$Q,'Order Details'!$E:$E,"Yes",'Order Details'!$I:$I,'Item Summary'!$B16,'Order Details'!$F:$F,'Item Summary'!J$4,'Order Details'!$C:$C,"In Production") -> 0 | K16: =SUMIFS('Order Details'!$Q:$Q,'Order Details'!$E:$E,"Yes",'Order Details'!$I:$I,'Item Summary'!$B16,'Order Details'!$F:$F,'Item Summary'!K$4,'Order Details'!$C:$C,"PO Received")+SUMIFS('Order Details'!$Q:$Q,'Order Details'!$E:$E,"Yes",'Order Details'!$I:$I,'Item Summary'!$B16,'Order Details'!$F:$F,'Item Summary'!K$4,'Order Details'!$C:$C,"Proforma Invoice Sent")+SUMIFS('Order Details'!$Q:$Q,'Order Details'!$E:$E,"Yes",'Order Details'!$I:$I,'Item Summary'!$B16,'Order Details'!$F:$F,'Item Summary'!K$4,'Order Details'!$C:$C,"Downpayment Received")+SUMIFS('Order Details'!$Q:$Q,'Order Details'!$E:$E,"Yes",'Order Details'!$I:$I,'Item Summary'!$B16,'Order Details'!$F:$F,'Item Summary'!K$4,'Order Details'!$C:$C,"In Production") -> 0 | ... M16: =SUMIFS('Order Details'!$Q:$Q,'Order Details'!$E:$E,"Yes",'Order Details'!$I:$I,'Item Summary'!$B16,'Order Details'!$F:$F,'Item Summary'!M$4,'Order Details'!$C:$C,"PO Received")+SUMIFS('Order Details'!$Q:$Q,'Order Details'!$E:$E,"Yes",'Order Details'!$I:$I,'Item Summary'!$B16,'Order Details'!$F:$F,'Item Summary'!M$4,'Order Details'!$C:$C,"Proforma Invoice Sent")+SUMIFS('Order Details'!$Q:$Q,'Order Details'!$E:$E,"Yes",'Order Details'!$I:$I,'Item Summary'!$B16,'Order Details'!$F:$F,'Item Summary'!M$4,'Order Details'!$C:$C,"Downpayment Received")+SUMIFS('Order Details'!$Q:$Q,'Order Details'!$E:$E,"Yes",'Order Details'!$I:$I,'Item Summary'!$B16,'Order Details'!$F:$F,'Item Summary'!M$4,'Order Details'!$C:$C,"In Production") -> 0 | N16: =SUM(D16:M16) -> 2000 | Q16: 694438 | R16: =VLOOKUP($Q16,'Pricing Table - eff 27-Jan-2026'!$A:$L,9,FALSE)&""" "&VLOOKUP($Q16,'Pricing Table - eff 27-Jan-2026'!$A:$L,12,FALSE) -> 144" GLOSSY WHITE | S16: =SUMIFS('Order Details'!$Q:$Q,'Order Details'!$E:$E,"Yes",'Order Details'!$I:$I,$Q16,'Order Details'!$F:$F,'Item Summary'!S$4)-D16 -> 0 | T16: =SUMIFS('Order Details'!$Q:$Q,'Order Details'!$E:$E,"Yes",'Order Details'!$I:$I,$Q16,'Order Details'!$F:$F,'Item Summary'!T$4)-E16 -> 200 | U16: =SUMIFS('Order Details'!$Q:$Q,'Order Details'!$E:$E,"Yes",'Order Details'!$I:$I,$Q16,'Order Details'!$F:$F,'Item Summary'!U$4)-F16 -> 1000 | V16: =SUMIFS('Order Details'!$Q:$Q,'Order Details'!$E:$E,"Yes",'Order Details'!$I:$I,$Q16,'Order Details'!$F:$F,'Item Summary'!V$4)-G16 -> 0 | W16: =SUMIFS('Order Details'!$Q:$Q,'Order Details'!$E:$E,"Yes",'Order Details'!$I:$I,$Q16,'Order Details'!$F:$F,'Item Summary'!W$4)-H16 -> 800 | X16: =SUMIFS('Order Details'!$Q:$Q,'Order Details'!$E:$E,"Yes",'Order Details'!$I:$I,$Q16,'Order Details'!$F:$F,'Item Summary'!X$4)-I16 -> 0 | Y16: =SUMIFS('Order Details'!$Q:$Q,'Order Details'!$E:$E,"Yes",'Order Details'!$I:$I,$Q16,'Order Details'!$F:$F,'Item Summary'!Y$4)-J16 -> 0 | Z16: =SUMIFS('Order Details'!$Q:$Q,'Order Details'!$E:$E,"Yes",'Order Details'!$I:$I,$Q16,'Order Details'!$F:$F,'Item Summary'!Z$4)-K16 -> 1000 | ... AB16: =SUMIFS('Order Details'!$Q:$Q,'Order Details'!$E:$E,"Yes",'Order Details'!$I:$I,$Q16,'Order Details'!$F:$F,'Item Summary'!AB$4)-M16 -> 1000 | AC16: =SUM(S16:AB16) -> 4000
... B59: 697410 | C59: =VLOOKUP($B59,'Pricing Table - eff 27-Jan-2026'!$A:$L,9,FALSE)&""" "&VLOOKUP($B59,'Pricing Table - eff 27-Jan-2026'!$A:$L,12,FALSE) -> 144" SAND SAHARA | D59: =SUMIFS('Order Details'!$Q:$Q,'Order Details'!$E:$E,"Yes",'Order Details'!$I:$I,'Item Summary'!$B59,'Order Details'!$F:$F,'Item Summary'!D$4,'Order Details'!$C:$C,"PO Received")+SUMIFS('Order Details'!$Q:$Q,'Order Details'!$E:$E,"Yes",'Order Details'!$I:$I,'Item Summary'!$B59,'Order Details'!$F:$F,'Item Summary'!D$4,'Order Details'!$C:$C,"Proforma Invoice Sent")+SUMIFS('Order Details'!$Q:$Q,'Order Details'!$E:$E,"Yes",'Order Details'!$I:$I,'Item Summary'!$B59,'Order Details'!$F:$F,'Item Summary'!D$4,'Order Details'!$C:$C,"Downpayment Received")+SUMIFS('Order Details'!$Q:$Q,'Order Details'!$E:$E,"Yes",'Order Details'!$I:$I,'Item Summary'!$B59,'Order Details'!$F:$F,'Item Summary'!D$4,'Order Details'!$C:$C,"In Production") -> 0 | E59: =SUMIFS('Order Details'!$Q:$Q,'Order Details'!$E:$E,"Yes",'Order Details'!$I:$I,'Item Summary'!$B59,'Order Details'!$F:$F,'Item Summary'!E$4,'Order Details'!$C:$C,"PO Received")+SUMIFS('Order Details'!$Q:$Q,'Order Details'!$E:$E,"Yes",'Order Details'!$I:$I,'Item Summary'!$B59,'Order Details'!$F:$F,'Item Summary'!E$4,'Order Details'!$C:$C,"Proforma Invoice Sent")+SUMIFS('Order Details'!$Q:$Q,'Order Details'!$E:$E,"Yes",'Order Details'!$I:$I,'Item Summary'!$B59,'Order Details'!$F:$F,'Item Summary'!E$4,'Order Details'!$C:$C,"Downpayment Received")+SUMIFS('Order Details'!$Q:$Q,'Order Details'!$E:$E,"Yes",'Order Details'!$I:$I,'Item Summary'!$B59,'Order Details'!$F:$F,'Item Summary'!E$4,'Order Details'!$C:$C,"In Production") -> 0 | F59: =SUMIFS('Order Details'!$Q:$Q,'Order Details'!$E:$E,"Yes",'Order Details'!$I:$I,'Item Summary'!$B59,'Order Details'!$F:$F,'Item Summary'!F$4,'Order Details'!$C:$C,"PO Received")+SUMIFS('Order Details'!$Q:$Q,'Order Details'!$E:$E,"Yes",'Order Details'!$I:$I,'Item Summary'!$B59,'Order Details'!$F:$F,'Item Summary'!F$4,'Order Details'!$C:$C,"Proforma Invoice Sent")+SUMIFS('Order Details'!$Q:$Q,'Order Details'!$E:$E,"Yes",'Order Details'!$I:$I,'Item Summary'!$B59,'Order Details'!$F:$F,'Item Summary'!F$4,'Order Details'!$C:$C,"Downpayment Received")+SUMIFS('Order Details'!$Q:$Q,'Order Details'!$E:$E,"Yes",'Order Details'!$I:$I,'Item Summary'!$B59,'Order Details'!$F:$F,'Item Summary'!F$4,'Order Details'!$C:$C,"In Production") -> 0 | G59: =SUMIFS('Order Details'!$Q:$Q,'Order Details'!$E:$E,"Yes",'Order Details'!$I:$I,'Item Summary'!$B59,'Order Details'!$F:$F,'Item Summary'!G$4,'Order Details'!$C:$C,"PO Received")+SUMIFS('Order Details'!$Q:$Q,'Order Details'!$E:$E,"Yes",'Order Details'!$I:$I,'Item Summary'!$B59,'Order Details'!$F:$F,'Item Summary'!G$4,'Order Details'!$C:$C,"Proforma Invoice Sent")+SUMIFS('Order Details'!$Q:$Q,'Order Details'!$E:$E,"Yes",'Order Details'!$I:$I,'Item Summary'!$B59,'Order Details'!$F:$F,'Item Summary'!G$4,'Order Details'!$C:$C,"Downpayment Received")+SUMIFS('Order Details'!$Q:$Q,'Order Details'!$E:$E,"Yes",'Order Details'!$I:$I,'Item Summary'!$B59,'Order Details'!$F:$F,'Item Summary'!G$4,'Order Details'!$C:$C,"In Production") -> 0 | H59: =SUMIFS('Order Details'!$Q:$Q,'Order Details'!$E:$E,"Yes",'Order Details'!$I:$I,'Item Summary'!$B59,'Order Details'!$F:$F,'Item Summary'!H$4,'Order Details'!$C:$C,"PO Received")+SUMIFS('Order Details'!$Q:$Q,'Order Details'!$E:$E,"Yes",'Order Details'!$I:$I,'Item Summary'!$B59,'Order Details'!$F:$F,'Item Summary'!H$4,'Order Details'!$C:$C,"Proforma Invoice Sent")+SUMIFS('Order Details'!$Q:$Q,'Order Details'!$E:$E,"Yes",'Order Details'!$I:$I,'Item Summary'!$B59,'Order Details'!$F:$F,'Item Summary'!H$4,'Order Details'!$C:$C,"Downpayment Received")+SUMIFS('Order Details'!$Q:$Q,'Order Details'!$E:$E,"Yes",'Order Details'!$I:$I,'Item Summary'!$B59,'Order Details'!$F:$F,'Item Summary'!H$4,'Order Details'!$C:$C,"In Production") -> 0 | I59: =SUMIFS('Order Details'!$Q:$Q,'Order Details'!$E:$E,"Yes",'Order Details'!$I:$I,'Item Summary'!$B59,'Order Details'!$F:$F,'Item Summary'!I$4,'Order Details'!$C:$C,"PO Received")+SUMIFS('Order Details'!$Q:$Q,'Order Details'!$E:$E,"Yes",'Order Details'!$I:$I,'Item Summary'!$B59,'Order Details'!$F:$F,'Item Summary'!I$4,'Order Details'!$C:$C,"Proforma Invoice Sent")+SUMIFS('Order Details'!$Q:$Q,'Order Details'!$E:$E,"Yes",'Order Details'!$I:$I,'Item Summary'!$B59,'Order Details'!$F:$F,'Item Summary'!I$4,'Order Details'!$C:$C,"Downpayment Received")+SUMIFS('Order Details'!$Q:$Q,'Order Details'!$E:$E,"Yes",'Order Details'!$I:$I,'Item Summary'!$B59,'Order Details'!$F:$F,'Item Summary'!I$4,'Order Details'!$C:$C,"In Production") -> 0 | J59: =SUMIFS('Order Details'!$Q:$Q,'Order Details'!$E:$E,"Yes",'Order Details'!$I:$I,'Item Summary'!$B59,'Order Details'!$F:$F,'Item Summary'!J$4,'Order Details'!$C:$C,"PO Received")+SUMIFS('Order Details'!$Q:$Q,'Order Details'!$E:$E,"Yes",'Order Details'!$I:$I,'Item Summary'!$B59,'Order Details'!$F:$F,'Item Summary'!J$4,'Order Details'!$C:$C,"Proforma Invoice Sent")+SUMIFS('Order Details'!$Q:$Q,'Order Details'!$E:$E,"Yes",'Order Details'!$I:$I,'Item Summary'!$B59,'Order Details'!$F:$F,'Item Summary'!J$4,'Order Details'!$C:$C,"Downpayment Received")+SUMIFS('Order Details'!$Q:$Q,'Order Details'!$E:$E,"Yes",'Order Details'!$I:$I,'Item Summary'!$B59,'Order Details'!$F:$F,'Item Summary'!J$4,'Order Details'!$C:$C,"In Production") -> 0 | K59: =SUMIFS('Order Details'!$Q:$Q,'Order Details'!$E:$E,"Yes",'Order Details'!$I:$I,'Item Summary'!$B59,'Order Details'!$F:$F,'Item Summary'!K$4,'Order Details'!$C:$C,"PO Received")+SUMIFS('Order Details'!$Q:$Q,'Order Details'!$E:$E,"Yes",'Order Details'!$I:$I,'Item Summary'!$B59,'Order Details'!$F:$F,'Item Summary'!K$4,'Order Details'!$C:$C,"Proforma Invoice Sent")+SUMIFS('Order Details'!$Q:$Q,'Order Details'!$E:$E,"Yes",'Order Details'!$I:$I,'Item Summary'!$B59,'Order Details'!$F:$F,'Item Summary'!K$4,'Order Details'!$C:$C,"Downpayment Received")+SUMIFS('Order Details'!$Q:$Q,'Order Details'!$E:$E,"Yes",'Order Details'!$I:$I,'Item Summary'!$B59,'Order Details'!$F:$F,'Item Summary'!K$4,'Order Details'!$C:$C,"In Production") -> 0 | ... M59: =SUMIFS('Order Details'!$Q:$Q,'Order Details'!$E:$E,"Yes",'Order Details'!$I:$I,'Item Summary'!$B59,'Order Details'!$F:$F,'Item Summary'!M$4,'Order Details'!$C:$C,"PO Received")+SUMIFS('Order Details'!$Q:$Q,'Order Details'!$E:$E,"Yes",'Order Details'!$I:$I,'Item Summary'!$B59,'Order Details'!$F:$F,'Item Summary'!M$4,'Order Details'!$C:$C,"Proforma Invoice Sent")+SUMIFS('Order Details'!$Q:$Q,'Order Details'!$E:$E,"Yes",'Order Details'!$I:$I,'Item Summary'!$B59,'Order Details'!$F:$F,'Item Summary'!M$4,'Order Details'!$C:$C,"Downpayment Received")+SUMIFS('Order Details'!$Q:$Q,'Order Details'!$E:$E,"Yes",'Order Details'!$I:$I,'Item Summary'!$B59,'Order Details'!$F:$F,'Item Summary'!M$4,'Order Details'!$C:$C,"In Production") -> 0 | N59: =SUM(D59:M59) -> 0 | Q59: 697410 | R59: =VLOOKUP($Q59,'Pricing Table - eff 27-Jan-2026'!$A:$L,9,FALSE)&""" "&VLOOKUP($Q59,'Pricing Table - eff 27-Jan-2026'!$A:$L,12,FALSE) -> 144" SAND SAHARA | S59: =SUMIFS('Order Details'!$Q:$Q,'Order Details'!$E:$E,"Yes",'Order Details'!$I:$I,$Q59,'Order Details'!$F:$F,'Item Summary'!S$4)-D59 -> 0 | T59: =SUMIFS('Order Details'!$Q:$Q,'Order Details'!$E:$E,"Yes",'Order Details'!$I:$I,$Q59,'Order Details'!$F:$F,'Item Summary'!T$4)-E59 -> 0 | U59: =SUMIFS('Order Details'!$Q:$Q,'Order Details'!$E:$E,"Yes",'Order Details'!$I:$I,$Q59,'Order Details'!$F:$F,'Item Summary'!U$4)-F59 -> 0 | V59: =SUMIFS('Order Details'!$Q:$Q,'Order Details'!$E:$E,"Yes",'Order Details'!$I:$I,$Q59,'Order Details'!$F:$F,'Item Summary'!V$4)-G59 -> 0 | W59: =SUMIFS('Order Details'!$Q:$Q,'Order Details'!$E:$E,"Yes",'Order Details'!$I:$I,$Q59,'Order Details'!$F:$F,'Item Summary'!W$4)-H59 -> 0 | X59: =SUMIFS('Order Details'!$Q:$Q,'Order Details'!$E:$E,"Yes",'Order Details'!$I:$I,$Q59,'Order Details'!$F:$F,'Item Summary'!X$4)-I59 -> 0 | Y59: =SUMIFS('Order Details'!$Q:$Q,'Order Details'!$E:$E,"Yes",'Order Details'!$I:$I,$Q59,'Order Details'!$F:$F,'Item Summary'!Y$4)-J59 -> 0 | Z59: =SUMIFS('Order Details'!$Q:$Q,'Order Details'!$E:$E,"Yes",'Order Details'!$I:$I,$Q59,'Order Details'!$F:$F,'Item Summary'!Z$4)-K59 -> 0 | ... AB59: =SUMIFS('Order Details'!$Q:$Q,'Order Details'!$E:$E,"Yes",'Order Details'!$I:$I,$Q59,'Order Details'!$F:$F,'Item Summary'!AB$4)-M59 -> 0 | AC59: =SUM(S59:AB59) -> 0
B60: SSM90 | C60: =VLOOKUP($B60,'Pricing Table - eff 27-Jan-2026'!$A:$L,9,FALSE)&""" "&VLOOKUP($B60,'Pricing Table - eff 27-Jan-2026'!$A:$L,12,FALSE) -> 90" SAND SAHARA MATTE | D60: =SUMIFS('Order Details'!$Q:$Q,'Order Details'!$E:$E,"Yes",'Order Details'!$I:$I,'Item Summary'!$B60,'Order Details'!$F:$F,'Item Summary'!D$4,'Order Details'!$C:$C,"PO Received")+SUMIFS('Order Details'!$Q:$Q,'Order Details'!$E:$E,"Yes",'Order Details'!$I:$I,'Item Summary'!$B60,'Order Details'!$F:$F,'Item Summary'!D$4,'Order Details'!$C:$C,"Proforma Invoice Sent")+SUMIFS('Order Details'!$Q:$Q,'Order Details'!$E:$E,"Yes",'Order Details'!$I:$I,'Item Summary'!$B60,'Order Details'!$F:$F,'Item Summary'!D$4,'Order Details'!$C:$C,"Downpayment Received")+SUMIFS('Order Details'!$Q:$Q,'Order Details'!$E:$E,"Yes",'Order Details'!$I:$I,'Item Summary'!$B60,'Order Details'!$F:$F,'Item Summary'!D$4,'Order Details'!$C:$C,"In Production") -> 0 | E60: =SUMIFS('Order Details'!$Q:$Q,'Order Details'!$E:$E,"Yes",'Order Details'!$I:$I,'Item Summary'!$B60,'Order Details'!$F:$F,'Item Summary'!E$4,'Order Details'!$C:$C,"PO Received")+SUMIFS('Order Details'!$Q:$Q,'Order Details'!$E:$E,"Yes",'Order Details'!$I:$I,'Item Summary'!$B60,'Order Details'!$F:$F,'Item Summary'!E$4,'Order Details'!$C:$C,"Proforma Invoice Sent")+SUMIFS('Order Details'!$Q:$Q,'Order Details'!$E:$E,"Yes",'Order Details'!$I:$I,'Item Summary'!$B60,'Order Details'!$F:$F,'Item Summary'!E$4,'Order Details'!$C:$C,"Downpayment Received")+SUMIFS('Order Details'!$Q:$Q,'Order Details'!$E:$E,"Yes",'Order Details'!$I:$I,'Item Summary'!$B60,'Order Details'!$F:$F,'Item Summary'!E$4,'Order Details'!$C:$C,"In Production") -> 0 | F60: =SUMIFS('Order Details'!$Q:$Q,'Order Details'!$E:$E,"Yes",'Order Details'!$I:$I,'Item Summary'!$B60,'Order Details'!$F:$F,'Item Summary'!F$4,'Order Details'!$C:$C,"PO Received")+SUMIFS('Order Details'!$Q:$Q,'Order Details'!$E:$E,"Yes",'Order Details'!$I:$I,'Item Summary'!$B60,'Order Details'!$F:$F,'Item Summary'!F$4,'Order Details'!$C:$C,"Proforma Invoice Sent")+SUMIFS('Order Details'!$Q:$Q,'Order Details'!$E:$E,"Yes",'Order Details'!$I:$I,'Item Summary'!$B60,'Order Details'!$F:$F,'Item Summary'!F$4,'Order Details'!$C:$C,"Downpayment Received")+SUMIFS('Order Details'!$Q:$Q,'Order Details'!$E:$E,"Yes",'Order Details'!$I:$I,'Item Summary'!$B60,'Order Details'!$F:$F,'Item Summary'!F$4,'Order Details'!$C:$C,"In Production") -> 0 | G60: =SUMIFS('Order Details'!$Q:$Q,'Order Details'!$E:$E,"Yes",'Order Details'!$I:$I,'Item Summary'!$B60,'Order Details'!$F:$F,'Item Summary'!G$4,'Order Details'!$C:$C,"PO Received")+SUMIFS('Order Details'!$Q:$Q,'Order Details'!$E:$E,"Yes",'Order Details'!$I:$I,'Item Summary'!$B60,'Order Details'!$F:$F,'Item Summary'!G$4,'Order Details'!$C:$C,"Proforma Invoice Sent")+SUMIFS('Order Details'!$Q:$Q,'Order Details'!$E:$E,"Yes",'Order Details'!$I:$I,'Item Summary'!$B60,'Order Details'!$F:$F,'Item Summary'!G$4,'Order Details'!$C:$C,"Downpayment Received")+SUMIFS('Order Details'!$Q:$Q,'Order Details'!$E:$E,"Yes",'Order Details'!$I:$I,'Item Summary'!$B60,'Order Details'!$F:$F,'Item Summary'!G$4,'Order Details'!$C:$C,"In Production") -> 0 | H60: =SUMIFS('Order Details'!$Q:$Q,'Order Details'!$E:$E,"Yes",'Order Details'!$I:$I,'Item Summary'!$B60,'Order Details'!$F:$F,'Item Summary'!H$4,'Order Details'!$C:$C,"PO Received")+SUMIFS('Order Details'!$Q:$Q,'Order Details'!$E:$E,"Yes",'Order Details'!$I:$I,'Item Summary'!$B60,'Order Details'!$F:$F,'Item Summary'!H$4,'Order Details'!$C:$C,"Proforma Invoice Sent")+SUMIFS('Order Details'!$Q:$Q,'Order Details'!$E:$E,"Yes",'Order Details'!$I:$I,'Item Summary'!$B60,'Order Details'!$F:$F,'Item Summary'!H$4,'Order Details'!$C:$C,"Downpayment Received")+SUMIFS('Order Details'!$Q:$Q,'Order Details'!$E:$E,"Yes",'Order Details'!$I:$I,'Item Summary'!$B60,'Order Details'!$F:$F,'Item Summary'!H$4,'Order Details'!$C:$C,"In Production") -> 0 | I60: =SUMIFS('Order Details'!$Q:$Q,'Order Details'!$E:$E,"Yes",'Order Details'!$I:$I,'Item Summary'!$B60,'Order Details'!$F:$F,'Item Summary'!I$4,'Order Details'!$C:$C,"PO Received")+SUMIFS('Order Details'!$Q:$Q,'Order Details'!$E:$E,"Yes",'Order Details'!$I:$I,'Item Summary'!$B60,'Order Details'!$F:$F,'Item Summary'!I$4,'Order Details'!$C:$C,"Proforma Invoice Sent")+SUMIFS('Order Details'!$Q:$Q,'Order Details'!$E:$E,"Yes",'Order Details'!$I:$I,'Item Summary'!$B60,'Order Details'!$F:$F,'Item Summary'!I$4,'Order Details'!$C:$C,"Downpayment Received")+SUMIFS('Order Details'!$Q:$Q,'Order Details'!$E:$E,"Yes",'Order Details'!$I:$I,'Item Summary'!$B60,'Order Details'!$F:$F,'Item Summary'!I$4,'Order Details'!$C:$C,"In Production") -> 0 | J60: =SUMIFS('Order Details'!$Q:$Q,'Order Details'!$E:$E,"Yes",'Order Details'!$I:$I,'Item Summary'!$B60,'Order Details'!$F:$F,'Item Summary'!J$4,'Order Details'!$C:$C,"PO Received")+SUMIFS('Order Details'!$Q:$Q,'Order Details'!$E:$E,"Yes",'Order Details'!$I:$I,'Item Summary'!$B60,'Order Details'!$F:$F,'Item Summary'!J$4,'Order Details'!$C:$C,"Proforma Invoice Sent")+SUMIFS('Order Details'!$Q:$Q,'Order Details'!$E:$E,"Yes",'Order Details'!$I:$I,'Item Summary'!$B60,'Order Details'!$F:$F,'Item Summary'!J$4,'Order Details'!$C:$C,"Downpayment Received")+SUMIFS('Order Details'!$Q:$Q,'Order Details'!$E:$E,"Yes",'Order Details'!$I:$I,'Item Summary'!$B60,'Order Details'!$F:$F,'Item Summary'!J$4,'Order Details'!$C:$C,"In Production") -> 0 | K60: =SUMIFS('Order Details'!$Q:$Q,'Order Details'!$E:$E,"Yes",'Order Details'!$I:$I,'Item Summary'!$B60,'Order Details'!$F:$F,'Item Summary'!K$4,'Order Details'!$C:$C,"PO Received")+SUMIFS('Order Details'!$Q:$Q,'Order Details'!$E:$E,"Yes",'Order Details'!$I:$I,'Item Summary'!$B60,'Order Details'!$F:$F,'Item Summary'!K$4,'Order Details'!$C:$C,"Proforma Invoice Sent")+SUMIFS('Order Details'!$Q:$Q,'Order Details'!$E:$E,"Yes",'Order Details'!$I:$I,'Item Summary'!$B60,'Order Details'!$F:$F,'Item Summary'!K$4,'Order Details'!$C:$C,"Downpayment Received")+SUMIFS('Order Details'!$Q:$Q,'Order Details'!$E:$E,"Yes",'Order Details'!$I:$I,'Item Summary'!$B60,'Order Details'!$F:$F,'Item Summary'!K$4,'Order Details'!$C:$C,"In Production") -> 0 | ... M60: =SUMIFS('Order Details'!$Q:$Q,'Order Details'!$E:$E,"Yes",'Order Details'!$I:$I,'Item Summary'!$B60,'Order Details'!$F:$F,'Item Summary'!M$4,'Order Details'!$C:$C,"PO Received")+SUMIFS('Order Details'!$Q:$Q,'Order Details'!$E:$E,"Yes",'Order Details'!$I:$I,'Item Summary'!$B60,'Order Details'!$F:$F,'Item Summary'!M$4,'Order Details'!$C:$C,"Proforma Invoice Sent")+SUMIFS('Order Details'!$Q:$Q,'Order Details'!$E:$E,"Yes",'Order Details'!$I:$I,'Item Summary'!$B60,'Order Details'!$F:$F,'Item Summary'!M$4,'Order Details'!$C:$C,"Downpayment Received")+SUMIFS('Order Details'!$Q:$Q,'Order Details'!$E:$E,"Yes",'Order Details'!$I:$I,'Item Summary'!$B60,'Order Details'!$F:$F,'Item Summary'!M$4,'Order Details'!$C:$C,"In Production") -> 0 | N60: =SUM(D60:M60) -> 0 | Q60: SSM90 | R60: =VLOOKUP($Q60,'Pricing Table - eff 27-Jan-2026'!$A:$L,9,FALSE)&""" "&VLOOKUP($Q60,'Pricing Table - eff 27-Jan-2026'!$A:$L,12,FALSE) -> 90" SAND SAHARA MATTE | S60: =SUMIFS('Order Details'!$Q:$Q,'Order Details'!$E:$E,"Yes",'Order Details'!$I:$I,$Q60,'Order Details'!$F:$F,'Item Summary'!S$4)-D60 -> 0 | T60: =SUMIFS('Order Details'!$Q:$Q,'Order Details'!$E:$E,"Yes",'Order Details'!$I:$I,$Q60,'Order Details'!$F:$F,'Item Summary'!T$4)-E60 -> 0 | U60: =SUMIFS('Order Details'!$Q:$Q,'Order Details'!$E:$E,"Yes",'Order Details'!$I:$I,$Q60,'Order Details'!$F:$F,'Item Summary'!U$4)-F60 -> 0 | V60: =SUMIFS('Order Details'!$Q:$Q,'Order Details'!$E:$E,"Yes",'Order Details'!$I:$I,$Q60,'Order Details'!$F:$F,'Item Summary'!V$4)-G60 -> 0 | W60: =SUMIFS('Order Details'!$Q:$Q,'Order Details'!$E:$E,"Yes",'Order Details'!$I:$I,$Q60,'Order Details'!$F:$F,'Item Summary'!W$4)-H60 -> 0 | X60: =SUMIFS('Order Details'!$Q:$Q,'Order Details'!$E:$E,"Yes",'Order Details'!$I:$I,$Q60,'Order Details'!$F:$F,'Item Summary'!X$4)-I60 -> 0 | Y60: =SUMIFS('Order Details'!$Q:$Q,'Order Details'!$E:$E,"Yes",'Order Details'!$I:$I,$Q60,'Order Details'!$F:$F,'Item Summary'!Y$4)-J60 -> 0 | Z60: =SUMIFS('Order Details'!$Q:$Q,'Order Details'!$E:$E,"Yes",'Order Details'!$I:$I,$Q60,'Order Details'!$F:$F,'Item Summary'!Z$4)-K60 -> 0 | ... AB60: =SUMIFS('Order Details'!$Q:$Q,'Order Details'!$E:$E,"Yes",'Order Details'!$I:$I,$Q60,'Order Details'!$F:$F,'Item Summary'!AB$4)-M60 -> 0 | AC60: =SUM(S60:AB60) -> 0
B61: 721547 | C61: =VLOOKUP($B61,'Pricing Table - eff 27-Jan-2026'!$A:$L,9,FALSE)&""" "&VLOOKUP($B61,'Pricing Table - eff 27-Jan-2026'!$A:$L,12,FALSE) -> 90.5" SAND SAHARA MATTE | D61: =SUMIFS('Order Details'!$Q:$Q,'Order Details'!$E:$E,"Yes",'Order Details'!$I:$I,'Item Summary'!$B61,'Order Details'!$F:$F,'Item Summary'!D$4,'Order Details'!$C:$C,"PO Received")+SUMIFS('Order Details'!$Q:$Q,'Order Details'!$E:$E,"Yes",'Order Details'!$I:$I,'Item Summary'!$B61,'Order Details'!$F:$F,'Item Summary'!D$4,'Order Details'!$C:$C,"Proforma Invoice Sent")+SUMIFS('Order Details'!$Q:$Q,'Order Details'!$E:$E,"Yes",'Order Details'!$I:$I,'Item Summary'!$B61,'Order Details'!$F:$F,'Item Summary'!D$4,'Order Details'!$C:$C,"Downpayment Received")+SUMIFS('Order Details'!$Q:$Q,'Order Details'!$E:$E,"Yes",'Order Details'!$I:$I,'Item Summary'!$B61,'Order Details'!$F:$F,'Item Summary'!D$4,'Order Details'!$C:$C,"In Production") -> 0 | E61: =SUMIFS('Order Details'!$Q:$Q,'Order Details'!$E:$E,"Yes",'Order Details'!$I:$I,'Item Summary'!$B61,'Order Details'!$F:$F,'Item Summary'!E$4,'Order Details'!$C:$C,"PO Received")+SUMIFS('Order Details'!$Q:$Q,'Order Details'!$E:$E,"Yes",'Order Details'!$I:$I,'Item Summary'!$B61,'Order Details'!$F:$F,'Item Summary'!E$4,'Order Details'!$C:$C,"Proforma Invoice Sent")+SUMIFS('Order Details'!$Q:$Q,'Order Details'!$E:$E,"Yes",'Order Details'!$I:$I,'Item Summary'!$B61,'Order Details'!$F:$F,'Item Summary'!E$4,'Order Details'!$C:$C,"Downpayment Received")+SUMIFS('Order Details'!$Q:$Q,'Order Details'!$E:$E,"Yes",'Order Details'!$I:$I,'Item Summary'!$B61,'Order Details'!$F:$F,'Item Summary'!E$4,'Order Details'!$C:$C,"In Production") -> 0 | F61: =SUMIFS('Order Details'!$Q:$Q,'Order Details'!$E:$E,"Yes",'Order Details'!$I:$I,'Item Summary'!$B61,'Order Details'!$F:$F,'Item Summary'!F$4,'Order Details'!$C:$C,"PO Received")+SUMIFS('Order Details'!$Q:$Q,'Order Details'!$E:$E,"Yes",'Order Details'!$I:$I,'Item Summary'!$B61,'Order Details'!$F:$F,'Item Summary'!F$4,'Order Details'!$C:$C,"Proforma Invoice Sent")+SUMIFS('Order Details'!$Q:$Q,'Order Details'!$E:$E,"Yes",'Order Details'!$I:$I,'Item Summary'!$B61,'Order Details'!$F:$F,'Item Summary'!F$4,'Order Details'!$C:$C,"Downpayment Received")+SUMIFS('Order Details'!$Q:$Q,'Order Details'!$E:$E,"Yes",'Order Details'!$I:$I,'Item Summary'!$B61,'Order Details'!$F:$F,'Item Summary'!F$4,'Order Details'!$C:$C,"In Production") -> 0 | G61: =SUMIFS('Order Details'!$Q:$Q,'Order Details'!$E:$E,"Yes",'Order Details'!$I:$I,'Item Summary'!$B61,'Order Details'!$F:$F,'Item Summary'!G$4,'Order Details'!$C:$C,"PO Received")+SUMIFS('Order Details'!$Q:$Q,'Order Details'!$E:$E,"Yes",'Order Details'!$I:$I,'Item Summary'!$B61,'Order Details'!$F:$F,'Item Summary'!G$4,'Order Details'!$C:$C,"Proforma Invoice Sent")+SUMIFS('Order Details'!$Q:$Q,'Order Details'!$E:$E,"Yes",'Order Details'!$I:$I,'Item Summary'!$B61,'Order Details'!$F:$F,'Item Summary'!G$4,'Order Details'!$C:$C,"Downpayment Received")+SUMIFS('Order Details'!$Q:$Q,'Order Details'!$E:$E,"Yes",'Order Details'!$I:$I,'Item Summary'!$B61,'Order Details'!$F:$F,'Item Summary'!G$4,'Order Details'!$C:$C,"In Production") -> 800 | H61: =SUMIFS('Order Details'!$Q:$Q,'Order Details'!$E:$E,"Yes",'Order Details'!$I:$I,'Item Summary'!$B61,'Order Details'!$F:$F,'Item Summary'!H$4,'Order Details'!$C:$C,"PO Received")+SUMIFS('Order Details'!$Q:$Q,'Order Details'!$E:$E,"Yes",'Order Details'!$I:$I,'Item Summary'!$B61,'Order Details'!$F:$F,'Item Summary'!H$4,'Order Details'!$C:$C,"Proforma Invoice Sent")+SUMIFS('Order Details'!$Q:$Q,'Order Details'!$E:$E,"Yes",'Order Details'!$I:$I,'Item Summary'!$B61,'Order Details'!$F:$F,'Item Summary'!H$4,'Order Details'!$C:$C,"Downpayment Received")+SUMIFS('Order Details'!$Q:$Q,'Order Details'!$E:$E,"Yes",'Order Details'!$I:$I,'Item Summary'!$B61,'Order Details'!$F:$F,'Item Summary'!H$4,'Order Details'!$C:$C,"In Production") -> 0 | I61: =SUMIFS('Order Details'!$Q:$Q,'Order Details'!$E:$E,"Yes",'Order Details'!$I:$I,'Item Summary'!$B61,'Order Details'!$F:$F,'Item Summary'!I$4,'Order Details'!$C:$C,"PO Received")+SUMIFS('Order Details'!$Q:$Q,'Order Details'!$E:$E,"Yes",'Order Details'!$I:$I,'Item Summary'!$B61,'Order Details'!$F:$F,'Item Summary'!I$4,'Order Details'!$C:$C,"Proforma Invoice Sent")+SUMIFS('Order Details'!$Q:$Q,'Order Details'!$E:$E,"Yes",'Order Details'!$I:$I,'Item Summary'!$B61,'Order Details'!$F:$F,'Item Summary'!I$4,'Order Details'!$C:$C,"Downpayment Received")+SUMIFS('Order Details'!$Q:$Q,'Order Details'!$E:$E,"Yes",'Order Details'!$I:$I,'Item Summary'!$B61,'Order Details'!$F:$F,'Item Summary'!I$4,'Order Details'!$C:$C,"In Production") -> 0 | J61: =SUMIFS('Order Details'!$Q:$Q,'Order Details'!$E:$E,"Yes",'Order Details'!$I:$I,'Item Summary'!$B61,'Order Details'!$F:$F,'Item Summary'!J$4,'Order Details'!$C:$C,"PO Received")+SUMIFS('Order Details'!$Q:$Q,'Order Details'!$E:$E,"Yes",'Order Details'!$I:$I,'Item Summary'!$B61,'Order Details'!$F:$F,'Item Summary'!J$4,'Order Details'!$C:$C,"Proforma Invoice Sent")+SUMIFS('Order Details'!$Q:$Q,'Order Details'!$E:$E,"Yes",'Order Details'!$I:$I,'Item Summary'!$B61,'Order Details'!$F:$F,'Item Summary'!J$4,'Order Details'!$C:$C,"Downpayment Received")+SUMIFS('Order Details'!$Q:$Q,'Order Details'!$E:$E,"Yes",'Order Details'!$I:$I,'Item Summary'!$B61,'Order Details'!$F:$F,'Item Summary'!J$4,'Order Details'!$C:$C,"In Production") -> 0 | K61: =SUMIFS('Order Details'!$Q:$Q,'Order Details'!$E:$E,"Yes",'Order Details'!$I:$I,'Item Summary'!$B61,'Order Details'!$F:$F,'Item Summary'!K$4,'Order Details'!$C:$C,"PO Received")+SUMIFS('Order Details'!$Q:$Q,'Order Details'!$E:$E,"Yes",'Order Details'!$I:$I,'Item Summary'!$B61,'Order Details'!$F:$F,'Item Summary'!K$4,'Order Details'!$C:$C,"Proforma Invoice Sent")+SUMIFS('Order Details'!$Q:$Q,'Order Details'!$E:$E,"Yes",'Order Details'!$I:$I,'Item Summary'!$B61,'Order Details'!$F:$F,'Item Summary'!K$4,'Order Details'!$C:$C,"Downpayment Received")+SUMIFS('Order Details'!$Q:$Q,'Order Details'!$E:$E,"Yes",'Order Details'!$I:$I,'Item Summary'!$B61,'Order Details'!$F:$F,'Item Summary'!K$4,'Order Details'!$C:$C,"In Production") -> 0 | ... M61: =SUMIFS('Order Details'!$Q:$Q,'Order Details'!$E:$E,"Yes",'Order Details'!$I:$I,'Item Summary'!$B61,'Order Details'!$F:$F,'Item Summary'!M$4,'Order Details'!$C:$C,"PO Received")+SUMIFS('Order Details'!$Q:$Q,'Order Details'!$E:$E,"Yes",'Order Details'!$I:$I,'Item Summary'!$B61,'Order Details'!$F:$F,'Item Summary'!M$4,'Order Details'!$C:$C,"Proforma Invoice Sent")+SUMIFS('Order Details'!$Q:$Q,'Order Details'!$E:$E,"Yes",'Order Details'!$I:$I,'Item Summary'!$B61,'Order Details'!$F:$F,'Item Summary'!M$4,'Order Details'!$C:$C,"Downpayment Received")+SUMIFS('Order Details'!$Q:$Q,'Order Details'!$E:$E,"Yes",'Order Details'!$I:$I,'Item Summary'!$B61,'Order Details'!$F:$F,'Item Summary'!M$4,'Order Details'!$C:$C,"In Production") -> 0 | N61: =SUM(D61:M61) -> 800 | Q61: 721547 | R61: =VLOOKUP($Q61,'Pricing Table - eff 27-Jan-2026'!$A:$L,9,FALSE)&""" "&VLOOKUP($Q61,'Pricing Table - eff 27-Jan-2026'!$A:$L,12,FALSE) -> 90.5" SAND SAHARA MATTE | S61: =SUMIFS('Order Details'!$Q:$Q,'Order Details'!$E:$E,"Yes",'Order Details'!$I:$I,$Q61,'Order Details'!$F:$F,'Item Summary'!S$4)-D61 -> 0 | T61: =SUMIFS('Order Details'!$Q:$Q,'Order Details'!$E:$E,"Yes",'Order Details'!$I:$I,$Q61,'Order Details'!$F:$F,'Item Summary'!T$4)-E61 -> 0 | U61: =SUMIFS('Order Details'!$Q:$Q,'Order Details'!$E:$E,"Yes",'Order Details'!$I:$I,$Q61,'Order Details'!$F:$F,'Item Summary'!U$4)-F61 -> 0 | V61: =SUMIFS('Order Details'!$Q:$Q,'Order Details'!$E:$E,"Yes",'Order Details'!$I:$I,$Q61,'Order Details'!$F:$F,'Item Summary'!V$4)-G61 -> 0 | W61: =SUMIFS('Order Details'!$Q:$Q,'Order Details'!$E:$E,"Yes",'Order Details'!$I:$I,$Q61,'Order Details'!$F:$F,'Item Summary'!W$4)-H61 -> 0 | X61: =SUMIFS('Order Details'!$Q:$Q,'Order Details'!$E:$E,"Yes",'Order Details'!$I:$I,$Q61,'Order Details'!$F:$F,'Item Summary'!X$4)-I61 -> 0 | Y61: =SUMIFS('Order Details'!$Q:$Q,'Order Details'!$E:$E,"Yes",'Order Details'!$I:$I,$Q61,'Order Details'!$F:$F,'Item Summary'!Y$4)-J61 -> 0 | Z61: =SUMIFS('Order Details'!$Q:$Q,'Order Details'!$E:$E,"Yes",'Order Details'!$I:$I,$Q61,'Order Details'!$F:$F,'Item Summary'!Z$4)-K61 -> 0 | ... AB61: =SUMIFS('Order Details'!$Q:$Q,'Order Details'!$E:$E,"Yes",'Order Details'!$I:$I,$Q61,'Order Details'!$F:$F,'Item Summary'!AB$4)-M61 -> 0 | AC61: =SUM(S61:AB61) -> 0
B62: 721548 | C62: =VLOOKUP($B62,'Pricing Table - eff 27-Jan-2026'!$A:$L,9,FALSE)&""" "&VLOOKUP($B62,'Pricing Table - eff 27-Jan-2026'!$A:$L,12,FALSE) -> 96" SAND SAHARA MATTE | D62: =SUMIFS('Order Details'!$Q:$Q,'Order Details'!$E:$E,"Yes",'Order Details'!$I:$I,'Item Summary'!$B62,'Order Details'!$F:$F,'Item Summary'!D$4,'Order Details'!$C:$C,"PO Received")+SUMIFS('Order Details'!$Q:$Q,'Order Details'!$E:$E,"Yes",'Order Details'!$I:$I,'Item Summary'!$B62,'Order Details'!$F:$F,'Item Summary'!D$4,'Order Details'!$C:$C,"Proforma Invoice Sent")+SUMIFS('Order Details'!$Q:$Q,'Order Details'!$E:$E,"Yes",'Order Details'!$I:$I,'Item Summary'!$B62,'Order Details'!$F:$F,'Item Summary'!D$4,'Order Details'!$C:$C,"Downpayment Received")+SUMIFS('Order Details'!$Q:$Q,'Order Details'!$E:$E,"Yes",'Order Details'!$I:$I,'Item Summary'!$B62,'Order Details'!$F:$F,'Item Summary'!D$4,'Order Details'!$C:$C,"In Production") -> 0 | E62: =SUMIFS('Order Details'!$Q:$Q,'Order Details'!$E:$E,"Yes",'Order Details'!$I:$I,'Item Summary'!$B62,'Order Details'!$F:$F,'Item Summary'!E$4,'Order Details'!$C:$C,"PO Received")+SUMIFS('Order Details'!$Q:$Q,'Order Details'!$E:$E,"Yes",'Order Details'!$I:$I,'Item Summary'!$B62,'Order Details'!$F:$F,'Item Summary'!E$4,'Order Details'!$C:$C,"Proforma Invoice Sent")+SUMIFS('Order Details'!$Q:$Q,'Order Details'!$E:$E,"Yes",'Order Details'!$I:$I,'Item Summary'!$B62,'Order Details'!$F:$F,'Item Summary'!E$4,'Order Details'!$C:$C,"Downpayment Received")+SUMIFS('Order Details'!$Q:$Q,'Order Details'!$E:$E,"Yes",'Order Details'!$I:$I,'Item Summary'!$B62,'Order Details'!$F:$F,'Item Summary'!E$4,'Order Details'!$C:$C,"In Production") -> 0 | F62: =SUMIFS('Order Details'!$Q:$Q,'Order Details'!$E:$E,"Yes",'Order Details'!$I:$I,'Item Summary'!$B62,'Order Details'!$F:$F,'Item Summary'!F$4,'Order Details'!$C:$C,"PO Received")+SUMIFS('Order Details'!$Q:$Q,'Order Details'!$E:$E,"Yes",'Order Details'!$I:$I,'Item Summary'!$B62,'Order Details'!$F:$F,'Item Summary'!F$4,'Order Details'!$C:$C,"Proforma Invoice Sent")+SUMIFS('Order Details'!$Q:$Q,'Order Details'!$E:$E,"Yes",'Order Details'!$I:$I,'Item Summary'!$B62,'Order Details'!$F:$F,'Item Summary'!F$4,'Order Details'!$C:$C,"Downpayment Received")+SUMIFS('Order Details'!$Q:$Q,'Order Details'!$E:$E,"Yes",'Order Details'!$I:$I,'Item Summary'!$B62,'Order Details'!$F:$F,'Item Summary'!F$4,'Order Details'!$C:$C,"In Production") -> 0 | G62: =SUMIFS('Order Details'!$Q:$Q,'Order Details'!$E:$E,"Yes",'Order Details'!$I:$I,'Item Summary'!$B62,'Order Details'!$F:$F,'Item Summary'!G$4,'Order Details'!$C:$C,"PO Received")+SUMIFS('Order Details'!$Q:$Q,'Order Details'!$E:$E,"Yes",'Order Details'!$I:$I,'Item Summary'!$B62,'Order Details'!$F:$F,'Item Summary'!G$4,'Order Details'!$C:$C,"Proforma Invoice Sent")+SUMIFS('Order Details'!$Q:$Q,'Order Details'!$E:$E,"Yes",'Order Details'!$I:$I,'Item Summary'!$B62,'Order Details'!$F:$F,'Item Summary'!G$4,'Order Details'!$C:$C,"Downpayment Received")+SUMIFS('Order Details'!$Q:$Q,'Order Details'!$E:$E,"Yes",'Order Details'!$I:$I,'Item Summary'!$B62,'Order Details'!$F:$F,'Item Summary'!G$4,'Order Details'!$C:$C,"In Production") -> 800 | H62: =SUMIFS('Order Details'!$Q:$Q,'Order Details'!$E:$E,"Yes",'Order Details'!$I:$I,'Item Summary'!$B62,'Order Details'!$F:$F,'Item Summary'!H$4,'Order Details'!$C:$C,"PO Received")+SUMIFS('Order Details'!$Q:$Q,'Order Details'!$E:$E,"Yes",'Order Details'!$I:$I,'Item Summary'!$B62,'Order Details'!$F:$F,'Item Summary'!H$4,'Order Details'!$C:$C,"Proforma Invoice Sent")+SUMIFS('Order Details'!$Q:$Q,'Order Details'!$E:$E,"Yes",'Order Details'!$I:$I,'Item Summary'!$B62,'Order Details'!$F:$F,'Item Summary'!H$4,'Order Details'!$C:$C,"Downpayment Received")+SUMIFS('Order Details'!$Q:$Q,'Order Details'!$E:$E,"Yes",'Order Details'!$I:$I,'Item Summary'!$B62,'Order Details'!$F:$F,'Item Summary'!H$4,'Order Details'!$C:$C,"In Production") -> 0 | I62: =SUMIFS('Order Details'!$Q:$Q,'Order Details'!$E:$E,"Yes",'Order Details'!$I:$I,'Item Summary'!$B62,'Order Details'!$F:$F,'Item Summary'!I$4,'Order Details'!$C:$C,"PO Received")+SUMIFS('Order Details'!$Q:$Q,'Order Details'!$E:$E,"Yes",'Order Details'!$I:$I,'Item Summary'!$B62,'Order Details'!$F:$F,'Item Summary'!I$4,'Order Details'!$C:$C,"Proforma Invoice Sent")+SUMIFS('Order Details'!$Q:$Q,'Order Details'!$E:$E,"Yes",'Order Details'!$I:$I,'Item Summary'!$B62,'Order Details'!$F:$F,'Item Summary'!I$4,'Order Details'!$C:$C,"Downpayment Received")+SUMIFS('Order Details'!$Q:$Q,'Order Details'!$E:$E,"Yes",'Order Details'!$I:$I,'Item Summary'!$B62,'Order Details'!$F:$F,'Item Summary'!I$4,'Order Details'!$C:$C,"In Production") -> 0 | J62: =SUMIFS('Order Details'!$Q:$Q,'Order Details'!$E:$E,"Yes",'Order Details'!$I:$I,'Item Summary'!$B62,'Order Details'!$F:$F,'Item Summary'!J$4,'Order Details'!$C:$C,"PO Received")+SUMIFS('Order Details'!$Q:$Q,'Order Details'!$E:$E,"Yes",'Order Details'!$I:$I,'Item Summary'!$B62,'Order Details'!$F:$F,'Item Summary'!J$4,'Order Details'!$C:$C,"Proforma Invoice Sent")+SUMIFS('Order Details'!$Q:$Q,'Order Details'!$E:$E,"Yes",'Order Details'!$I:$I,'Item Summary'!$B62,'Order Details'!$F:$F,'Item Summary'!J$4,'Order Details'!$C:$C,"Downpayment Received")+SUMIFS('Order Details'!$Q:$Q,'Order Details'!$E:$E,"Yes",'Order Details'!$I:$I,'Item Summary'!$B62,'Order Details'!$F:$F,'Item Summary'!J$4,'Order Details'!$C:$C,"In Production") -> 0 | K62: =SUMIFS('Order Details'!$Q:$Q,'Order Details'!$E:$E,"Yes",'Order Details'!$I:$I,'Item Summary'!$B62,'Order Details'!$F:$F,'Item Summary'!K$4,'Order Details'!$C:$C,"PO Received")+SUMIFS('Order Details'!$Q:$Q,'Order Details'!$E:$E,"Yes",'Order Details'!$I:$I,'Item Summary'!$B62,'Order Details'!$F:$F,'Item Summary'!K$4,'Order Details'!$C:$C,"Proforma Invoice Sent")+SUMIFS('Order Details'!$Q:$Q,'Order Details'!$E:$E,"Yes",'Order Details'!$I:$I,'Item Summary'!$B62,'Order Details'!$F:$F,'Item Summary'!K$4,'Order Details'!$C:$C,"Downpayment Received")+SUMIFS('Order Details'!$Q:$Q,'Order Details'!$E:$E,"Yes",'Order Details'!$I:$I,'Item Summary'!$B62,'Order Details'!$F:$F,'Item Summary'!K$4,'Order Details'!$C:$C,"In Production") -> 0 | ... M62: =SUMIFS('Order Details'!$Q:$Q,'Order Details'!$E:$E,"Yes",'Order Details'!$I:$I,'Item Summary'!$B62,'Order Details'!$F:$F,'Item Summary'!M$4,'Order Details'!$C:$C,"PO Received")+SUMIFS('Order Details'!$Q:$Q,'Order Details'!$E:$E,"Yes",'Order Details'!$I:$I,'Item Summary'!$B62,'Order Details'!$F:$F,'Item Summary'!M$4,'Order Details'!$C:$C,"Proforma Invoice Sent")+SUMIFS('Order Details'!$Q:$Q,'Order Details'!$E:$E,"Yes",'Order Details'!$I:$I,'Item Summary'!$B62,'Order Details'!$F:$F,'Item Summary'!M$4,'Order Details'!$C:$C,"Downpayment Received")+SUMIFS('Order Details'!$Q:$Q,'Order Details'!$E:$E,"Yes",'Order Details'!$I:$I,'Item Summary'!$B62,'Order Details'!$F:$F,'Item Summary'!M$4,'Order Details'!$C:$C,"In Production") -> 0 | N62: =SUM(D62:M62) -> 800 | Q62: 721548 | R62: =VLOOKUP($Q62,'Pricing Table - eff 27-Jan-2026'!$A:$L,9,FALSE)&""" "&VLOOKUP($Q62,'Pricing Table - eff 27-Jan-2026'!$A:$L,12,FALSE) -> 96" SAND SAHARA MATTE | S62: =SUMIFS('Order Details'!$Q:$Q,'Order Details'!$E:$E,"Yes",'Order Details'!$I:$I,$Q62,'Order Details'!$F:$F,'Item Summary'!S$4)-D62 -> 0 | T62: =SUMIFS('Order Details'!$Q:$Q,'Order Details'!$E:$E,"Yes",'Order Details'!$I:$I,$Q62,'Order Details'!$F:$F,'Item Summary'!T$4)-E62 -> 0 | U62: =SUMIFS('Order Details'!$Q:$Q,'Order Details'!$E:$E,"Yes",'Order Details'!$I:$I,$Q62,'Order Details'!$F:$F,'Item Summary'!U$4)-F62 -> 0 | V62: =SUMIFS('Order Details'!$Q:$Q,'Order Details'!$E:$E,"Yes",'Order Details'!$I:$I,$Q62,'Order Details'!$F:$F,'Item Summary'!V$4)-G62 -> 0 | W62: =SUMIFS('Order Details'!$Q:$Q,'Order Details'!$E:$E,"Yes",'Order Details'!$I:$I,$Q62,'Order Details'!$F:$F,'Item Summary'!W$4)-H62 -> 0 | X62: =SUMIFS('Order Details'!$Q:$Q,'Order Details'!$E:$E,"Yes",'Order Details'!$I:$I,$Q62,'Order Details'!$F:$F,'Item Summary'!X$4)-I62 -> 0 | Y62: =SUMIFS('Order Details'!$Q:$Q,'Order Details'!$E:$E,"Yes",'Order Details'!$I:$I,$Q62,'Order Details'!$F:$F,'Item Summary'!Y$4)-J62 -> 0 | Z62: =SUMIFS('Order Details'!$Q:$Q,'Order Details'!$E:$E,"Yes",'Order Details'!$I:$I,$Q62,'Order Details'!$F:$F,'Item Summary'!Z$4)-K62 -> 0 | ... AB62: =SUMIFS('Order Details'!$Q:$Q,'Order Details'!$E:$E,"Yes",'Order Details'!$I:$I,$Q62,'Order Details'!$F:$F,'Item Summary'!AB$4)-M62 -> 0 | AC62: =SUM(S62:AB62) -> 0
